Compiled from "ModSettings.java"
public class xaero.common.settings.ModSettings {
  public static int defaultSettings;

  public static final java.lang.String format = "\u00a7";

  protected xaero.common.IXaeroMinimap modMain;

  private xaero.hud.minimap.radar.category.EntityRadarBackwardsCompatibilityConfig entityRadarBackwardsCompatibilityConfig;

  private boolean foundOldRadarSettings;

  public boolean needsLegacySlimeSeedResave;

  private java.lang.String loadedWaypointLines;

  public static int serverSettings;

  private static java.util.HashMap<xaero.hud.path.XaeroPath, java.lang.Long> legacyServerSlimeSeeds;

  private static final java.lang.String[] SHOW_LIGHT_LEVEL_NAMES;

  private static int[] OLD_MINIMAP_SIZES;

  public java.lang.Boolean showCoordsLegacy;

  public java.lang.Boolean showBiomeLegacy;

  public java.lang.Integer showLightLevelLegacy;

  public java.lang.Integer showTimeLegacy;

  public java.lang.Boolean showAnglesLegacy;

  public java.lang.Boolean showDimensionNameLegacy;

  public java.lang.Boolean displayWeatherInfoLegacy;

  public xaero.common.settings.ModSettings(xaero.common.IXaeroMinimap);
    Code:
         0: aload_0
         1: invokespecial #1                  // Method java/lang/Object."<init>":()V
         4: aload_0
         5: aload_1
         6: putfield      #7                  // Field modMain:Lxaero/common/IXaeroMinimap;
         9: aload_0
        10: new           #13                 // class xaero/hud/minimap/radar/category/EntityRadarBackwardsCompatibilityConfig
        13: dup
        14: invokespecial #15                 // Method xaero/hud/minimap/radar/category/EntityRadarBackwardsCompatibilityConfig."<init>":()V
        17: putfield      #16                 // Field entityRadarBackwardsCompatibilityConfig:Lxaero/hud/minimap/radar/category/EntityRadarBackwardsCompatibilityConfig;
        20: aload_1
        21: invokeinterface #20,  1           // InterfaceMethod xaero/common/IXaeroMinimap.getVersionID:()Ljava/lang/String;
        26: ldc           #26                 // String fair
        28: invokevirtual #28                 // Method java/lang/String.endsWith:(Ljava/lang/String;)Z
        31: ifeq          39
        34: ldc           #34                 // int 16188159
        36: goto          41
        39: ldc           #35                 // int 2147483647
        41: putstatic     #36                 // Field defaultSettings:I
        44: getstatic     #40                 // Field serverSettings:I
        47: ifne          56
        50: getstatic     #36                 // Field defaultSettings:I
        53: putstatic     #40                 // Field serverSettings:I
        56: return

  public boolean isKeyRepeat(net.minecraft.client.KeyMapping);
    Code:
         0: iconst_1
         1: ireturn

  public boolean getMinimap();
    Code:
         0: getstatic     #43                 // Field xaero/common/HudMod.INSTANCE:Lxaero/common/HudMod;
         3: invokevirtual #49                 // Method xaero/common/HudMod.getHudConfigs:()Lxaero/lib/common/config/channel/ConfigChannel;
         6: invokevirtual #53                 // Method xaero/lib/common/config/channel/ConfigChannel.getClientConfigManager:()Lxaero/lib/client/config/ClientConfigManager;
         9: getstatic     #59                 // Field xaero/hud/minimap/common/config/option/MinimapProfiledConfigOptions.DISPLAY_MINIMAP:Lxaero/lib/common/config/option/BooleanConfigOption;
        12: invokevirtual #65                 // Method xaero/lib/client/config/ClientConfigManager.getEffective:(Lxaero/lib/common/config/option/ConfigOption;)Ljava/lang/Object;
        15: checkcast     #71                 // class java/lang/Boolean
        18: invokevirtual #73                 // Method java/lang/Boolean.booleanValue:()Z
        21: ireturn

  public void setSlimeChunksSeed(long, xaero.hud.path.XaeroPath);
    Code:
         0: getstatic     #77                 // Field xaero/hud/minimap/BuiltInHudModules.MINIMAP:Lxaero/hud/module/HudModule;
         3: invokevirtual #83                 // Method xaero/hud/module/HudModule.getCurrentSession:()Lxaero/hud/module/ModuleSession;
         6: checkcast     #89                 // class xaero/hud/minimap/module/MinimapSession
         9: astore        4
        11: aload         4
        13: ifnonnull     29
        16: getstatic     #91                 // Field legacyServerSlimeSeeds:Ljava/util/HashMap;
        19: aload_3
        20: lload_1
        21: invokestatic  #95                 // Method java/lang/Long.valueOf:(J)Ljava/lang/Long;
        24: invokevirtual #101                // Method java/util/HashMap.put:(Ljava/lang/Object;Ljava/lang/Object;)Ljava/lang/Object;
        27: pop
        28: return
        29: aload         4
        31: invokevirtual #107                // Method xaero/hud/minimap/module/MinimapSession.getWorldManager:()Lxaero/hud/minimap/world/MinimapWorldManager;
        34: aload_3
        35: invokevirtual #111                // Method xaero/hud/minimap/world/MinimapWorldManager.getWorld:(Lxaero/hud/path/XaeroPath;)Lxaero/hud/minimap/world/MinimapWorld;
        38: astore        5
        40: aload         5
        42: ifnonnull     58
        45: getstatic     #91                 // Field legacyServerSlimeSeeds:Ljava/util/HashMap;
        48: aload_3
        49: lload_1
        50: invokestatic  #95                 // Method java/lang/Long.valueOf:(J)Ljava/lang/Long;
        53: invokevirtual #101                // Method java/util/HashMap.put:(Ljava/lang/Object;Ljava/lang/Object;)Ljava/lang/Object;
        56: pop
        57: return
        58: aload         5
        60: lload_1
        61: invokestatic  #95                 // Method java/lang/Long.valueOf:(J)Ljava/lang/Long;
        64: invokevirtual #117                // Method xaero/hud/minimap/world/MinimapWorld.setSlimeChunkSeed:(Ljava/lang/Long;)V
        67: return

  public java.lang.Long getSlimeChunksSeed(xaero.hud.path.XaeroPath);
    Code:
         0: getstatic     #77                 // Field xaero/hud/minimap/BuiltInHudModules.MINIMAP:Lxaero/hud/module/HudModule;
         3: invokevirtual #83                 // Method xaero/hud/module/HudModule.getCurrentSession:()Lxaero/hud/module/ModuleSession;
         6: checkcast     #89                 // class xaero/hud/minimap/module/MinimapSession
         9: astore_2
        10: aload_2
        11: ifnonnull     20
        14: aload_0
        15: aload_1
        16: invokevirtual #123                // Method getLegacySlimeChunksSeed:(Lxaero/hud/path/XaeroPath;)Ljava/lang/Long;
        19: areturn
        20: aload_2
        21: invokevirtual #107                // Method xaero/hud/minimap/module/MinimapSession.getWorldManager:()Lxaero/hud/minimap/world/MinimapWorldManager;
        24: aload_1
        25: invokevirtual #111                // Method xaero/hud/minimap/world/MinimapWorldManager.getWorld:(Lxaero/hud/path/XaeroPath;)Lxaero/hud/minimap/world/MinimapWorld;
        28: astore_3
        29: aload_3
        30: ifnonnull     39
        33: aload_0
        34: aload_1
        35: invokevirtual #123                // Method getLegacySlimeChunksSeed:(Lxaero/hud/path/XaeroPath;)Ljava/lang/Long;
        38: areturn
        39: aload_3
        40: invokevirtual #127                // Method xaero/hud/minimap/world/MinimapWorld.getSlimeChunkSeed:()Ljava/lang/Long;
        43: areturn

  public java.lang.Long getLegacySlimeChunksSeed(xaero.hud.path.XaeroPath);
    Code:
         0: getstatic     #91                 // Field legacyServerSlimeSeeds:Ljava/util/HashMap;
         3: aload_1
         4: invokevirtual #131                // Method java/util/HashMap.get:(Ljava/lang/Object;)Ljava/lang/Object;
         7: checkcast     #96                 // class java/lang/Long
        10: areturn

  public java.lang.Long removeLegacySlimeChunksSeed(xaero.hud.path.XaeroPath);
    Code:
         0: aload_0
         1: iconst_1
         2: putfield      #135                // Field needsLegacySlimeSeedResave:Z
         5: getstatic     #91                 // Field legacyServerSlimeSeeds:Ljava/util/HashMap;
         8: aload_1
         9: invokevirtual #139                // Method java/util/HashMap.remove:(Ljava/lang/Object;)Ljava/lang/Object;
        12: checkcast     #96                 // class java/lang/Long
        15: areturn

  public boolean getSlimeChunks(xaero.hud.minimap.module.MinimapSession);
    Code:
         0: aload_1
         1: invokestatic  #142                // Method xaero/hud/minimap/config/util/MinimapConfigClientUtils.getEffectiveSlimeChunks:(Lxaero/hud/minimap/module/MinimapSession;)Z
         4: ireturn

  public boolean waypointsGUI(xaero.hud.minimap.module.MinimapSession);
    Code:
         0: aload_1
         1: invokevirtual #148                // Method xaero/hud/minimap/module/MinimapSession.getProcessor:()Lxaero/common/minimap/MinimapProcessor;
         4: astore_2
         5: invokestatic  #152                // Method net/minecraft/client/Minecraft.getInstance:()Lnet/minecraft/client/Minecraft;
         8: getfield      #158                // Field net/minecraft/client/Minecraft.player:Lnet/minecraft/client/player/LocalPlayer;
        11: ifnull        56
        14: aload_1
        15: invokevirtual #162                // Method xaero/hud/minimap/module/MinimapSession.getWorldState:()Lxaero/hud/minimap/world/state/MinimapWorldState;
        18: invokevirtual #166                // Method xaero/hud/minimap/world/state/MinimapWorldState.getAutoWorldPath:()Lxaero/hud/path/XaeroPath;
        21: ifnull        56
        24: aload_2
        25: invokevirtual #172                // Method xaero/common/minimap/MinimapProcessor.getMinimapItem:()Lnet/minecraft/world/item/Item;
        28: ifnull        52
        31: invokestatic  #152                // Method net/minecraft/client/Minecraft.getInstance:()Lnet/minecraft/client/Minecraft;
        34: getfield      #158                // Field net/minecraft/client/Minecraft.player:Lnet/minecraft/client/player/LocalPlayer;
        37: ifnull        52
        40: invokestatic  #152                // Method net/minecraft/client/Minecraft.getInstance:()Lnet/minecraft/client/Minecraft;
        43: getfield      #158                // Field net/minecraft/client/Minecraft.player:Lnet/minecraft/client/player/LocalPlayer;
        46: invokestatic  #178                // Method xaero/common/minimap/MinimapProcessor.hasMinimapItem:(Lnet/minecraft/world/entity/player/Player;)Z
        49: ifeq          56
        52: iconst_1
        53: goto          57
        56: iconst_0
        57: ireturn

  public float getMinimapScale();
    Code:
         0: getstatic     #43                 // Field xaero/common/HudMod.INSTANCE:Lxaero/common/HudMod;
         3: invokevirtual #49                 // Method xaero/common/HudMod.getHudConfigs:()Lxaero/lib/common/config/channel/ConfigChannel;
         6: invokevirtual #53                 // Method xaero/lib/common/config/channel/ConfigChannel.getClientConfigManager:()Lxaero/lib/client/config/ClientConfigManager;
         9: invokestatic  #182                // Method xaero/hud/gui/util/GuiUtils.getMinimapScale:(Lxaero/lib/client/config/ClientConfigManager;)F
        12: freturn

  public float getUIScale(int, int, int);
    Code:
         0: iload_1
         1: iload_2
         2: iload_3
         3: invokestatic  #188                // Method xaero/hud/gui/util/GuiUtils.getUIScale:(III)F
         6: freturn

  public int getAutoUIScale();
    Code:
         0: invokestatic  #192                // Method xaero/hud/gui/util/GuiUtils.getAutoUIScale:()I
         3: ireturn

  private int getMaxWaypointsDistance(int);
    Code:
         0: iload_1
         1: ifgt          6
         4: iconst_0
         5: ireturn
         6: ldc2_w        #196                // double 2.0d
         9: iconst_2
        10: iload_1
        11: iadd
        12: i2d
        13: invokestatic  #198                // Method java/lang/Math.pow:(DD)D
        16: d2i
        17: ireturn

  private boolean assumeUsingFBO();
    Code:
         0: aload_0
         1: getfield      #7                  // Field modMain:Lxaero/common/IXaeroMinimap;
         4: invokeinterface #204,  1          // InterfaceMethod xaero/common/IXaeroMinimap.getMinimap:()Lxaero/hud/minimap/Minimap;
         9: invokevirtual #208                // Method xaero/hud/minimap/Minimap.getMinimapFBORenderer:()Lxaero/common/minimap/render/MinimapFBORenderer;
        12: invokevirtual #214                // Method xaero/common/minimap/render/MinimapFBORenderer.assumeUsingFBO:()Z
        15: ireturn

  public boolean isIgnoreHeightmaps();
    Code:
         0: aload_0
         1: getfield      #7                  // Field modMain:Lxaero/common/IXaeroMinimap;
         4: invokeinterface #219,  1          // InterfaceMethod xaero/common/IXaeroMinimap.getSupportMods:()Lxaero/common/mods/SupportMods;
         9: invokevirtual #223                // Method xaero/common/mods/SupportMods.shouldUseWorldMapChunks:()Z
        12: ifeq          31
        15: aload_0
        16: getfield      #7                  // Field modMain:Lxaero/common/IXaeroMinimap;
        19: invokeinterface #219,  1          // InterfaceMethod xaero/common/IXaeroMinimap.getSupportMods:()Lxaero/common/mods/SupportMods;
        24: getfield      #228                // Field xaero/common/mods/SupportMods.worldmapSupport:Lxaero/common/mods/SupportXaeroWorldmap;
        27: invokevirtual #232                // Method xaero/common/mods/SupportXaeroWorldmap.getWorldMapIgnoreHeightmaps:()Z
        30: ireturn
        31: getstatic     #77                 // Field xaero/hud/minimap/BuiltInHudModules.MINIMAP:Lxaero/hud/module/HudModule;
        34: invokevirtual #83                 // Method xaero/hud/module/HudModule.getCurrentSession:()Lxaero/hud/module/ModuleSession;
        37: checkcast     #89                 // class xaero/hud/minimap/module/MinimapSession
        40: invokevirtual #107                // Method xaero/hud/minimap/module/MinimapSession.getWorldManager:()Lxaero/hud/minimap/world/MinimapWorldManager;
        43: invokevirtual #237                // Method xaero/hud/minimap/world/MinimapWorldManager.getAutoRootContainer:()Lxaero/hud/minimap/world/container/MinimapWorldRootContainer;
        46: astore_1
        47: aload_1
        48: invokevirtual #241                // Method xaero/hud/minimap/world/container/MinimapWorldRootContainer.getConfig:()Lxaero/hud/minimap/world/container/config/RootConfig;
        51: invokevirtual #247                // Method xaero/hud/minimap/world/container/config/RootConfig.isIgnoreHeightmaps:()Z
        54: ireturn

  public void writeSettings(java.io.PrintWriter);
    Code:
         0: return

  public void saveSettings() throws java.io.IOException;
    Code:
         0: aconst_null
         1: astore_1
         2: new           #252                // class java/io/PrintWriter
         5: dup
         6: new           #254                // class java/io/FileWriter
         9: dup
        10: aload_0
        11: getfield      #7                  // Field modMain:Lxaero/common/IXaeroMinimap;
        14: invokeinterface #256,  1          // InterfaceMethod xaero/common/IXaeroMinimap.getConfigFile:()Ljava/nio/file/Path;
        19: invokeinterface #260,  1          // InterfaceMethod java/nio/file/Path.toFile:()Ljava/io/File;
        24: invokespecial #266                // Method java/io/FileWriter."<init>":(Ljava/io/File;)V
        27: invokespecial #269                // Method java/io/PrintWriter."<init>":(Ljava/io/Writer;)V
        30: astore_1
        31: aload_0
        32: aload_1
        33: invokevirtual #272                // Method writeSettings:(Ljava/io/PrintWriter;)V
        36: getstatic     #91                 // Field legacyServerSlimeSeeds:Ljava/util/HashMap;
        39: invokevirtual #276                // Method java/util/HashMap.keySet:()Ljava/util/Set;
        42: invokeinterface #280,  1          // InterfaceMethod java/util/Set.toArray:()[Ljava/lang/Object;
        47: astore_2
        48: getstatic     #91                 // Field legacyServerSlimeSeeds:Ljava/util/HashMap;
        51: invokevirtual #286                // Method java/util/HashMap.values:()Ljava/util/Collection;
        54: invokeinterface #290,  1          // InterfaceMethod java/util/Collection.toArray:()[Ljava/lang/Object;
        59: astore_3
        60: iconst_0
        61: istore        4
        63: iload         4
        65: aload_2
        66: arraylength
        67: if_icmpge     99
        70: aload_1
        71: aload_2
        72: iload         4
        74: aaload
        75: invokestatic  #293                // Method java/lang/String.valueOf:(Ljava/lang/Object;)Ljava/lang/String;
        78: aload_3
        79: iload         4
        81: aaload
        82: invokestatic  #293                // Method java/lang/String.valueOf:(Ljava/lang/Object;)Ljava/lang/String;
        85: invokedynamic #296,  0            // InvokeDynamic #0:makeConcatWithConstants:(Ljava/lang/String;Ljava/lang/String;)Ljava/lang/String;
        90: invokevirtual #300                // Method java/io/PrintWriter.println:(Ljava/lang/String;)V
        93: iinc          4, 1
        96: goto          63
        99: aload_0
       100: getfield      #304                // Field loadedWaypointLines:Ljava/lang/String;
       103: ifnull        124
       106: aload_0
       107: getfield      #304                // Field loadedWaypointLines:Ljava/lang/String;
       110: invokevirtual #308                // Method java/lang/String.isEmpty:()Z
       113: ifne          124
       116: aload_1
       117: aload_0
       118: getfield      #304                // Field loadedWaypointLines:Ljava/lang/String;
       121: invokevirtual #311                // Method java/io/PrintWriter.print:(Ljava/lang/String;)V
       124: aload_0
       125: getfield      #7                  // Field modMain:Lxaero/common/IXaeroMinimap;
       128: invokeinterface #314,  1          // InterfaceMethod xaero/common/IXaeroMinimap.getHudIO:()Lxaero/hud/io/HudIO;
       133: aload_1
       134: invokevirtual #318                // Method xaero/hud/io/HudIO.save:(Ljava/io/PrintWriter;)V
       137: aload_1
       138: ifnull        161
       141: aload_1
       142: invokevirtual #323                // Method java/io/PrintWriter.close:()V
       145: goto          161
       148: astore        5
       150: aload_1
       151: ifnull        158
       154: aload_1
       155: invokevirtual #323                // Method java/io/PrintWriter.close:()V
       158: aload         5
       160: athrow
       161: aload_0
       162: iconst_0
       163: putfield      #135                // Field needsLegacySlimeSeedResave:Z
       166: return
      Exception table:
         from    to  target type
             2   137   148   any
           148   150   148   any

  public void readSetting(java.lang.String[]);
    Code:
         0: aload_1
         1: arraylength
         2: iconst_2
         3: if_icmpge     12
         6: ldc_w         #326                // String
         9: goto          15
        12: aload_1
        13: iconst_1
        14: aaload
        15: astore_2
        16: getstatic     #43                 // Field xaero/common/HudMod.INSTANCE:Lxaero/common/HudMod;
        19: invokevirtual #49                 // Method xaero/common/HudMod.getHudConfigs:()Lxaero/lib/common/config/channel/ConfigChannel;
        22: invokevirtual #53                 // Method xaero/lib/common/config/channel/ConfigChannel.getClientConfigManager:()Lxaero/lib/client/config/ClientConfigManager;
        25: astore_3
        26: aload_1
        27: iconst_0
        28: aaload
        29: ldc_w         #328                // String ignoreUpdate
        32: invokevirtual #330                // Method java/lang/String.equalsIgnoreCase:(Ljava/lang/String;)Z
        35: ifeq          62
        38: aload_3
        39: invokevirtual #333                // Method xaero/lib/client/config/ClientConfigManager.getPrimaryConfigManager:()Lxaero/lib/common/config/single/SingleConfigManager;
        42: invokevirtual #337                // Method xaero/lib/common/config/single/SingleConfigManager.getConfig:()Lxaero/lib/common/config/Config;
        45: getstatic     #342                // Field xaero/hud/minimap/config/primary/option/MinimapPrimaryClientConfigOptions.IGNORED_UPDATE:Lxaero/lib/common/config/option/ConfigOption;
        48: aload_2
        49: invokestatic  #348                // Method java/lang/Integer.parseInt:(Ljava/lang/String;)I
        52: invokestatic  #354                // Method java/lang/Integer.valueOf:(I)Ljava/lang/Integer;
        55: invokevirtual #357                // Method xaero/lib/common/config/Config.set:(Lxaero/lib/common/config/option/ConfigOption;Ljava/lang/Object;)Ljava/lang/Object;
        58: pop
        59: goto          4987
        62: aload_1
        63: iconst_0
        64: aaload
        65: ldc_w         #363                // String updateNotification
        68: invokevirtual #330                // Method java/lang/String.equalsIgnoreCase:(Ljava/lang/String;)Z
        71: ifeq          101
        74: aload_3
        75: invokevirtual #333                // Method xaero/lib/client/config/ClientConfigManager.getPrimaryConfigManager:()Lxaero/lib/common/config/single/SingleConfigManager;
        78: invokevirtual #337                // Method xaero/lib/common/config/single/SingleConfigManager.getConfig:()Lxaero/lib/common/config/Config;
        81: getstatic     #365                // Field xaero/hud/minimap/config/primary/option/MinimapPrimaryClientConfigOptions.UPDATE_NOTIFICATIONS:Lxaero/lib/common/config/option/BooleanConfigOption;
        84: aload_2
        85: ldc_w         #368                // String true
        88: invokevirtual #370                // Method java/lang/String.equals:(Ljava/lang/Object;)Z
        91: invokestatic  #374                // Method java/lang/Boolean.valueOf:(Z)Ljava/lang/Boolean;
        94: invokevirtual #357                // Method xaero/lib/common/config/Config.set:(Lxaero/lib/common/config/option/ConfigOption;Ljava/lang/Object;)Ljava/lang/Object;
        97: pop
        98: goto          4987
       101: aload_1
       102: iconst_0
       103: aaload
       104: ldc_w         #377                // String minimapItemId
       107: invokevirtual #330                // Method java/lang/String.equalsIgnoreCase:(Ljava/lang/String;)Z
       110: ifeq          140
       113: aload_2
       114: aload_1
       115: iconst_2
       116: aaload
       117: invokedynamic #379,  0            // InvokeDynamic #1:makeConcatWithConstants:(Ljava/lang/String;Ljava/lang/String;)Ljava/lang/String;
       122: astore        4
       124: aload_3
       125: invokevirtual #380                // Method xaero/lib/client/config/ClientConfigManager.getCurrentProfile:()Lxaero/lib/common/config/profile/ConfigProfile;
       128: getstatic     #384                // Field xaero/hud/minimap/common/config/option/MinimapProfiledConfigOptions.MINIMAP_ITEM:Lxaero/lib/common/config/option/ConfigOption;
       131: aload         4
       133: invokevirtual #387                // Method xaero/lib/common/config/profile/ConfigProfile.set:(Lxaero/lib/common/config/option/ConfigOption;Ljava/lang/Object;)Ljava/lang/Object;
       136: pop
       137: goto          4987
       140: aload_1
       141: iconst_0
       142: aaload
       143: ldc_w         #390                // String allowWrongWorldTeleportation
       146: invokevirtual #330                // Method java/lang/String.equalsIgnoreCase:(Ljava/lang/String;)Z
       149: ifeq          179
       152: aload_3
       153: invokevirtual #333                // Method xaero/lib/client/config/ClientConfigManager.getPrimaryConfigManager:()Lxaero/lib/common/config/single/SingleConfigManager;
       156: invokevirtual #337                // Method xaero/lib/common/config/single/SingleConfigManager.getConfig:()Lxaero/lib/common/config/Config;
       159: getstatic     #392                // Field xaero/hud/minimap/config/primary/option/MinimapPrimaryClientConfigOptions.WRONG_WORLD_TELEPORT:Lxaero/lib/common/config/option/BooleanConfigOption;
       162: aload_2
       163: ldc_w         #368                // String true
       166: invokevirtual #370                // Method java/lang/String.equals:(Ljava/lang/Object;)Z
       169: invokestatic  #374                // Method java/lang/Boolean.valueOf:(Z)Ljava/lang/Boolean;
       172: invokevirtual #357                // Method xaero/lib/common/config/Config.set:(Lxaero/lib/common/config/option/ConfigOption;Ljava/lang/Object;)Ljava/lang/Object;
       175: pop
       176: goto          4987
       179: aload_1
       180: iconst_0
       181: aaload
       182: ldc_w         #395                // String differentiateByServerAddress
       185: invokevirtual #330                // Method java/lang/String.equalsIgnoreCase:(Ljava/lang/String;)Z
       188: ifeq          218
       191: aload_3
       192: invokevirtual #333                // Method xaero/lib/client/config/ClientConfigManager.getPrimaryConfigManager:()Lxaero/lib/common/config/single/SingleConfigManager;
       195: invokevirtual #337                // Method xaero/lib/common/config/single/SingleConfigManager.getConfig:()Lxaero/lib/common/config/Config;
       198: getstatic     #397                // Field xaero/hud/minimap/config/primary/option/MinimapPrimaryClientConfigOptions.DIFFERENTIATE_BY_SERVER_ADDRESS:Lxaero/lib/common/config/option/BooleanConfigOption;
       201: aload_2
       202: ldc_w         #368                // String true
       205: invokevirtual #370                // Method java/lang/String.equals:(Ljava/lang/Object;)Z
       208: invokestatic  #374                // Method java/lang/Boolean.valueOf:(Z)Ljava/lang/Boolean;
       211: invokevirtual #357                // Method xaero/lib/common/config/Config.set:(Lxaero/lib/common/config/option/ConfigOption;Ljava/lang/Object;)Ljava/lang/Object;
       214: pop
       215: goto          4987
       218: aload_1
       219: iconst_0
       220: aaload
       221: ldc_w         #400                // String debugEntityIcons
       224: invokevirtual #330                // Method java/lang/String.equalsIgnoreCase:(Ljava/lang/String;)Z
       227: ifeq          257
       230: aload_3
       231: invokevirtual #333                // Method xaero/lib/client/config/ClientConfigManager.getPrimaryConfigManager:()Lxaero/lib/common/config/single/SingleConfigManager;
       234: invokevirtual #337                // Method xaero/lib/common/config/single/SingleConfigManager.getConfig:()Lxaero/lib/common/config/Config;
       237: getstatic     #402                // Field xaero/hud/minimap/config/primary/option/MinimapPrimaryClientConfigOptions.DEBUG_ENTITY_ICONS:Lxaero/lib/common/config/option/BooleanConfigOption;
       240: aload_2
       241: ldc_w         #368                // String true
       244: invokevirtual #370                // Method java/lang/String.equals:(Ljava/lang/Object;)Z
       247: invokestatic  #374                // Method java/lang/Boolean.valueOf:(Z)Ljava/lang/Boolean;
       250: invokevirtual #357                // Method xaero/lib/common/config/Config.set:(Lxaero/lib/common/config/option/ConfigOption;Ljava/lang/Object;)Ljava/lang/Object;
       253: pop
       254: goto          4987
       257: aload_1
       258: iconst_0
       259: aaload
       260: ldc_w         #405                // String debugEntityVariantIds
       263: invokevirtual #330                // Method java/lang/String.equalsIgnoreCase:(Ljava/lang/String;)Z
       266: ifeq          296
       269: aload_3
       270: invokevirtual #333                // Method xaero/lib/client/config/ClientConfigManager.getPrimaryConfigManager:()Lxaero/lib/common/config/single/SingleConfigManager;
       273: invokevirtual #337                // Method xaero/lib/common/config/single/SingleConfigManager.getConfig:()Lxaero/lib/common/config/Config;
       276: getstatic     #407                // Field xaero/hud/minimap/config/primary/option/MinimapPrimaryClientConfigOptions.DEBUG_ENTITY_VARIANT_IDS:Lxaero/lib/common/config/option/BooleanConfigOption;
       279: aload_2
       280: ldc_w         #368                // String true
       283: invokevirtual #370                // Method java/lang/String.equals:(Ljava/lang/Object;)Z
       286: invokestatic  #374                // Method java/lang/Boolean.valueOf:(Z)Ljava/lang/Boolean;
       289: invokevirtual #357                // Method xaero/lib/common/config/Config.set:(Lxaero/lib/common/config/option/ConfigOption;Ljava/lang/Object;)Ljava/lang/Object;
       292: pop
       293: goto          4987
       296: aload_1
       297: iconst_0
       298: aaload
       299: ldc_w         #410                // String radarHideInvisibleEntities
       302: invokevirtual #330                // Method java/lang/String.equalsIgnoreCase:(Ljava/lang/String;)Z
       305: ifeq          332
       308: aload_3
       309: invokevirtual #380                // Method xaero/lib/client/config/ClientConfigManager.getCurrentProfile:()Lxaero/lib/common/config/profile/ConfigProfile;
       312: getstatic     #412                // Field xaero/hud/minimap/common/config/option/MinimapProfiledConfigOptions.RADAR_HIDE_INVISIBLE:Lxaero/lib/common/config/option/BooleanConfigOption;
       315: aload_2
       316: ldc_w         #368                // String true
       319: invokevirtual #370                // Method java/lang/String.equals:(Ljava/lang/Object;)Z
       322: invokestatic  #374                // Method java/lang/Boolean.valueOf:(Z)Ljava/lang/Boolean;
       325: invokevirtual #387                // Method xaero/lib/common/config/profile/ConfigProfile.set:(Lxaero/lib/common/config/option/ConfigOption;Ljava/lang/Object;)Ljava/lang/Object;
       328: pop
       329: goto          4987
       332: aload_1
       333: iconst_0
       334: aaload
       335: ldc_w         #415                // String allowInternetAccess
       338: invokevirtual #330                // Method java/lang/String.equalsIgnoreCase:(Ljava/lang/String;)Z
       341: ifeq          396
       344: aload_2
       345: ldc_w         #368                // String true
       348: invokevirtual #370                // Method java/lang/String.equals:(Ljava/lang/Object;)Z
       351: istore        4
       353: iload         4
       355: ifne          393
       358: getstatic     #417                // Field xaero/lib/XaeroLib.INSTANCE:Lxaero/lib/XaeroLib;
       361: invokevirtual #422                // Method xaero/lib/XaeroLib.getLibConfigChannel:()Lxaero/lib/common/config/channel/ConfigChannel;
       364: invokevirtual #425                // Method xaero/lib/common/config/channel/ConfigChannel.getPrimaryCommonConfigManager:()Lxaero/lib/common/config/single/SingleConfigManager;
       367: invokevirtual #337                // Method xaero/lib/common/config/single/SingleConfigManager.getConfig:()Lxaero/lib/common/config/Config;
       370: getstatic     #428                // Field xaero/lib/common/config/primary/option/LibPrimaryCommonConfigOptions.ALLOW_INTERNET:Lxaero/lib/common/config/option/BooleanConfigOption;
       373: iconst_0
       374: invokestatic  #374                // Method java/lang/Boolean.valueOf:(Z)Ljava/lang/Boolean;
       377: invokevirtual #357                // Method xaero/lib/common/config/Config.set:(Lxaero/lib/common/config/option/ConfigOption;Ljava/lang/Object;)Ljava/lang/Object;
       380: pop
       381: getstatic     #417                // Field xaero/lib/XaeroLib.INSTANCE:Lxaero/lib/XaeroLib;
       384: invokevirtual #422                // Method xaero/lib/XaeroLib.getLibConfigChannel:()Lxaero/lib/common/config/channel/ConfigChannel;
       387: invokevirtual #433                // Method xaero/lib/common/config/channel/ConfigChannel.getPrimaryCommonConfigManagerIO:()Lxaero/lib/common/config/single/io/SingleConfigManagerIO;
       390: invokevirtual #437                // Method xaero/lib/common/config/single/io/SingleConfigManagerIO.save:()V
       393: goto          4987
       396: aload_1
       397: iconst_0
       398: aaload
       399: ldc_w         #441                // String minimap
       402: invokevirtual #330                // Method java/lang/String.equalsIgnoreCase:(Ljava/lang/String;)Z
       405: ifeq          425
       408: getstatic     #77                 // Field xaero/hud/minimap/BuiltInHudModules.MINIMAP:Lxaero/hud/module/HudModule;
       411: aload_3
       412: aload_2
       413: ldc_w         #368                // String true
       416: invokevirtual #370                // Method java/lang/String.equals:(Ljava/lang/Object;)Z
       419: invokevirtual #443                // Method xaero/hud/module/HudModule.setActive:(Lxaero/lib/client/config/ClientConfigManager;Z)V
       422: goto          4987
       425: aload_1
       426: iconst_0
       427: aaload
       428: ldc_w         #447                // String caveMaps
       431: invokevirtual #330                // Method java/lang/String.equalsIgnoreCase:(Ljava/lang/String;)Z
       434: ifeq          486
       437: aload_3
       438: invokevirtual #380                // Method xaero/lib/client/config/ClientConfigManager.getCurrentProfile:()Lxaero/lib/common/config/profile/ConfigProfile;
       441: getstatic     #449                // Field xaero/hud/minimap/common/config/option/MinimapProfiledConfigOptions.AUTO_CAVE_MODE:Lxaero/lib/common/config/option/RangeConfigOption;
       444: aload_2
       445: ldc_w         #368                // String true
       448: invokevirtual #370                // Method java/lang/String.equals:(Ljava/lang/Object;)Z
       451: ifeq          458
       454: iconst_1
       455: goto          476
       458: aload_2
       459: ldc_w         #453                // String false
       462: invokevirtual #370                // Method java/lang/String.equals:(Ljava/lang/Object;)Z
       465: ifeq          472
       468: iconst_0
       469: goto          476
       472: aload_2
       473: invokestatic  #348                // Method java/lang/Integer.parseInt:(Ljava/lang/String;)I
       476: invokestatic  #354                // Method java/lang/Integer.valueOf:(I)Ljava/lang/Integer;
       479: invokevirtual #387                // Method xaero/lib/common/config/profile/ConfigProfile.set:(Lxaero/lib/common/config/option/ConfigOption;Ljava/lang/Object;)Ljava/lang/Object;
       482: pop
       483: goto          4987
       486: aload_1
       487: iconst_0
       488: aaload
       489: ldc_w         #455                // String caveZoom
       492: invokevirtual #330                // Method java/lang/String.equalsIgnoreCase:(Ljava/lang/String;)Z
       495: ifeq          549
       498: aload_3
       499: invokevirtual #380                // Method xaero/lib/client/config/ClientConfigManager.getCurrentProfile:()Lxaero/lib/common/config/profile/ConfigProfile;
       502: getstatic     #457                // Field xaero/hud/minimap/common/config/option/MinimapProfiledConfigOptions.CAVE_ZOOM:Lxaero/lib/common/config/option/RangeConfigOption;
       505: aload_2
       506: ldc_w         #368                // String true
       509: invokevirtual #370                // Method java/lang/String.equals:(Ljava/lang/Object;)Z
       512: ifeq          519
       515: iconst_3
       516: goto          539
       519: aload_2
       520: ldc_w         #453                // String false
       523: invokevirtual #370                // Method java/lang/String.equals:(Ljava/lang/Object;)Z
       526: ifeq          533
       529: iconst_1
       530: goto          539
       533: aload_2
       534: invokestatic  #348                // Method java/lang/Integer.parseInt:(Ljava/lang/String;)I
       537: iconst_1
       538: iadd
       539: invokestatic  #354                // Method java/lang/Integer.valueOf:(I)Ljava/lang/Integer;
       542: invokevirtual #387                // Method xaero/lib/common/config/profile/ConfigProfile.set:(Lxaero/lib/common/config/option/ConfigOption;Ljava/lang/Object;)Ljava/lang/Object;
       545: pop
       546: goto          4987
       549: aload_1
       550: iconst_0
       551: aaload
       552: ldc_w         #460                // String showWaypoints
       555: invokevirtual #330                // Method java/lang/String.equalsIgnoreCase:(Ljava/lang/String;)Z
       558: ifeq          585
       561: aload_3
       562: invokevirtual #380                // Method xaero/lib/client/config/ClientConfigManager.getCurrentProfile:()Lxaero/lib/common/config/profile/ConfigProfile;
       565: getstatic     #462                // Field xaero/hud/minimap/common/config/option/MinimapProfiledConfigOptions.WAYPOINTS_ON_MINIMAP:Lxaero/lib/common/config/option/BooleanConfigOption;
       568: aload_2
       569: ldc_w         #368                // String true
       572: invokevirtual #370                // Method java/lang/String.equals:(Ljava/lang/Object;)Z
       575: invokestatic  #374                // Method java/lang/Boolean.valueOf:(Z)Ljava/lang/Boolean;
       578: invokevirtual #387                // Method xaero/lib/common/config/profile/ConfigProfile.set:(Lxaero/lib/common/config/option/ConfigOption;Ljava/lang/Object;)Ljava/lang/Object;
       581: pop
       582: goto          4987
       585: aload_1
       586: iconst_0
       587: aaload
       588: ldc_w         #465                // String deathpoints
       591: invokevirtual #330                // Method java/lang/String.equalsIgnoreCase:(Ljava/lang/String;)Z
       594: ifeq          621
       597: aload_3
       598: invokevirtual #380                // Method xaero/lib/client/config/ClientConfigManager.getCurrentProfile:()Lxaero/lib/common/config/profile/ConfigProfile;
       601: getstatic     #467                // Field xaero/hud/minimap/common/config/option/MinimapProfiledConfigOptions.DEATHPOINTS:Lxaero/lib/common/config/option/BooleanConfigOption;
       604: aload_2
       605: ldc_w         #368                // String true
       608: invokevirtual #370                // Method java/lang/String.equals:(Ljava/lang/Object;)Z
       611: invokestatic  #374                // Method java/lang/Boolean.valueOf:(Z)Ljava/lang/Boolean;
       614: invokevirtual #387                // Method xaero/lib/common/config/profile/ConfigProfile.set:(Lxaero/lib/common/config/option/ConfigOption;Ljava/lang/Object;)Ljava/lang/Object;
       617: pop
       618: goto          4987
       621: aload_1
       622: iconst_0
       623: aaload
       624: ldc_w         #470                // String oldDeathpoints
       627: invokevirtual #330                // Method java/lang/String.equalsIgnoreCase:(Ljava/lang/String;)Z
       630: ifeq          657
       633: aload_3
       634: invokevirtual #380                // Method xaero/lib/client/config/ClientConfigManager.getCurrentProfile:()Lxaero/lib/common/config/profile/ConfigProfile;
       637: getstatic     #472                // Field xaero/hud/minimap/common/config/option/MinimapProfiledConfigOptions.OLD_DEATHPOINTS:Lxaero/lib/common/config/option/BooleanConfigOption;
       640: aload_2
       641: ldc_w         #368                // String true
       644: invokevirtual #370                // Method java/lang/String.equals:(Ljava/lang/Object;)Z
       647: invokestatic  #374                // Method java/lang/Boolean.valueOf:(Z)Ljava/lang/Boolean;
       650: invokevirtual #387                // Method xaero/lib/common/config/profile/ConfigProfile.set:(Lxaero/lib/common/config/option/ConfigOption;Ljava/lang/Object;)Ljava/lang/Object;
       653: pop
       654: goto          4987
       657: aload_1
       658: iconst_0
       659: aaload
       660: ldc_w         #475                // String showIngameWaypoints
       663: invokevirtual #330                // Method java/lang/String.equalsIgnoreCase:(Ljava/lang/String;)Z
       666: ifeq          693
       669: aload_3
       670: invokevirtual #380                // Method xaero/lib/client/config/ClientConfigManager.getCurrentProfile:()Lxaero/lib/common/config/profile/ConfigProfile;
       673: getstatic     #477                // Field xaero/hud/minimap/common/config/option/MinimapProfiledConfigOptions.WAYPOINTS_IN_WORLD:Lxaero/lib/common/config/option/BooleanConfigOption;
       676: aload_2
       677: ldc_w         #368                // String true
       680: invokevirtual #370                // Method java/lang/String.equals:(Ljava/lang/Object;)Z
       683: invokestatic  #374                // Method java/lang/Boolean.valueOf:(Z)Ljava/lang/Boolean;
       686: invokevirtual #387                // Method xaero/lib/common/config/profile/ConfigProfile.set:(Lxaero/lib/common/config/option/ConfigOption;Ljava/lang/Object;)Ljava/lang/Object;
       689: pop
       690: goto          4987
       693: aload_1
       694: iconst_0
       695: aaload
       696: ldc_w         #480                // String displayRedstone
       699: invokevirtual #330                // Method java/lang/String.equalsIgnoreCase:(Ljava/lang/String;)Z
       702: ifeq          729
       705: aload_3
       706: invokevirtual #380                // Method xaero/lib/client/config/ClientConfigManager.getCurrentProfile:()Lxaero/lib/common/config/profile/ConfigProfile;
       709: getstatic     #482                // Field xaero/hud/minimap/common/config/option/MinimapProfiledConfigOptions.DISPLAY_REDSTONE:Lxaero/lib/common/config/option/BooleanConfigOption;
       712: aload_2
       713: ldc_w         #368                // String true
       716: invokevirtual #370                // Method java/lang/String.equals:(Ljava/lang/Object;)Z
       719: invokestatic  #374                // Method java/lang/Boolean.valueOf:(Z)Ljava/lang/Boolean;
       722: invokevirtual #387                // Method xaero/lib/common/config/profile/ConfigProfile.set:(Lxaero/lib/common/config/option/ConfigOption;Ljava/lang/Object;)Ljava/lang/Object;
       725: pop
       726: goto          4987
       729: aload_1
       730: iconst_0
       731: aaload
       732: ldc_w         #485                // String distance
       735: invokevirtual #330                // Method java/lang/String.equalsIgnoreCase:(Ljava/lang/String;)Z
       738: ifeq          762
       741: aload_3
       742: invokevirtual #380                // Method xaero/lib/client/config/ClientConfigManager.getCurrentProfile:()Lxaero/lib/common/config/profile/ConfigProfile;
       745: getstatic     #487                // Field xaero/hud/minimap/common/config/option/MinimapProfiledConfigOptions.WAYPOINT_DISTANCE_IN_WORLD:Lxaero/lib/common/config/option/RangeConfigOption;
       748: aload_2
       749: invokestatic  #348                // Method java/lang/Integer.parseInt:(Ljava/lang/String;)I
       752: invokestatic  #354                // Method java/lang/Integer.valueOf:(I)Ljava/lang/Integer;
       755: invokevirtual #387                // Method xaero/lib/common/config/profile/ConfigProfile.set:(Lxaero/lib/common/config/option/ConfigOption;Ljava/lang/Object;)Ljava/lang/Object;
       758: pop
       759: goto          4987
       762: aload_1
       763: iconst_0
       764: aaload
       765: ldc_w         #490                // String showCoords
       768: invokevirtual #330                // Method java/lang/String.equalsIgnoreCase:(Ljava/lang/String;)Z
       771: ifeq          791
       774: aload_0
       775: aload_2
       776: ldc_w         #368                // String true
       779: invokevirtual #370                // Method java/lang/String.equals:(Ljava/lang/Object;)Z
       782: invokestatic  #374                // Method java/lang/Boolean.valueOf:(Z)Ljava/lang/Boolean;
       785: putfield      #492                // Field showCoordsLegacy:Ljava/lang/Boolean;
       788: goto          4987
       791: aload_1
       792: iconst_0
       793: aaload
       794: ldc_w         #496                // String lockNorth
       797: invokevirtual #330                // Method java/lang/String.equalsIgnoreCase:(Ljava/lang/String;)Z
       800: ifeq          827
       803: aload_3
       804: invokevirtual #380                // Method xaero/lib/client/config/ClientConfigManager.getCurrentProfile:()Lxaero/lib/common/config/profile/ConfigProfile;
       807: getstatic     #498                // Field xaero/hud/minimap/common/config/option/MinimapProfiledConfigOptions.NORTH_LOCKED:Lxaero/lib/common/config/option/BooleanConfigOption;
       810: aload_2
       811: ldc_w         #368                // String true
       814: invokevirtual #370                // Method java/lang/String.equals:(Ljava/lang/Object;)Z
       817: invokestatic  #374                // Method java/lang/Boolean.valueOf:(Z)Ljava/lang/Boolean;
       820: invokevirtual #387                // Method xaero/lib/common/config/profile/ConfigProfile.set:(Lxaero/lib/common/config/option/ConfigOption;Ljava/lang/Object;)Ljava/lang/Object;
       823: pop
       824: goto          4987
       827: aload_1
       828: iconst_0
       829: aaload
       830: ldc_w         #501                // String zoom
       833: invokevirtual #330                // Method java/lang/String.equalsIgnoreCase:(Ljava/lang/String;)Z
       836: ifeq          862
       839: aload_3
       840: invokevirtual #380                // Method xaero/lib/client/config/ClientConfigManager.getCurrentProfile:()Lxaero/lib/common/config/profile/ConfigProfile;
       843: getstatic     #503                // Field xaero/hud/minimap/common/config/option/MinimapProfiledConfigOptions.ZOOM:Lxaero/lib/common/config/option/RangeConfigOption;
       846: aload_2
       847: invokestatic  #348                // Method java/lang/Integer.parseInt:(Ljava/lang/String;)I
       850: iconst_1
       851: iadd
       852: invokestatic  #354                // Method java/lang/Integer.valueOf:(I)Ljava/lang/Integer;
       855: invokevirtual #387                // Method xaero/lib/common/config/profile/ConfigProfile.set:(Lxaero/lib/common/config/option/ConfigOption;Ljava/lang/Object;)Ljava/lang/Object;
       858: pop
       859: goto          4987
       862: aload_1
       863: iconst_0
       864: aaload
       865: ldc_w         #506                // String mapSize
       868: invokevirtual #330                // Method java/lang/String.equalsIgnoreCase:(Ljava/lang/String;)Z
       871: ifeq          927
       874: aload_2
       875: invokestatic  #348                // Method java/lang/Integer.parseInt:(Ljava/lang/String;)I
       878: istore        4
       880: iload         4
       882: iconst_m1
       883: if_icmpne     904
       886: aload_3
       887: invokevirtual #380                // Method xaero/lib/client/config/ClientConfigManager.getCurrentProfile:()Lxaero/lib/common/config/profile/ConfigProfile;
       890: getstatic     #508                // Field xaero/hud/minimap/common/config/option/MinimapProfiledConfigOptions.SIZE:Lxaero/lib/common/config/option/IndexedConfigOption;
       893: iconst_0
       894: invokestatic  #354                // Method java/lang/Integer.valueOf:(I)Ljava/lang/Integer;
       897: invokevirtual #387                // Method xaero/lib/common/config/profile/ConfigProfile.set:(Lxaero/lib/common/config/option/ConfigOption;Ljava/lang/Object;)Ljava/lang/Object;
       900: pop
       901: goto          924
       904: aload_3
       905: invokevirtual #380                // Method xaero/lib/client/config/ClientConfigManager.getCurrentProfile:()Lxaero/lib/common/config/profile/ConfigProfile;
       908: getstatic     #508                // Field xaero/hud/minimap/common/config/option/MinimapProfiledConfigOptions.SIZE:Lxaero/lib/common/config/option/IndexedConfigOption;
       911: getstatic     #512                // Field OLD_MINIMAP_SIZES:[I
       914: iload         4
       916: iaload
       917: invokestatic  #354                // Method java/lang/Integer.valueOf:(I)Ljava/lang/Integer;
       920: invokevirtual #387                // Method xaero/lib/common/config/profile/ConfigProfile.set:(Lxaero/lib/common/config/option/ConfigOption;Ljava/lang/Object;)Ljava/lang/Object;
       923: pop
       924: goto          4987
       927: aload_1
       928: iconst_0
       929: aaload
       930: ldc_w         #516                // String minimapSize
       933: invokevirtual #330                // Method java/lang/String.equalsIgnoreCase:(Ljava/lang/String;)Z
       936: ifeq          960
       939: aload_3
       940: invokevirtual #380                // Method xaero/lib/client/config/ClientConfigManager.getCurrentProfile:()Lxaero/lib/common/config/profile/ConfigProfile;
       943: getstatic     #508                // Field xaero/hud/minimap/common/config/option/MinimapProfiledConfigOptions.SIZE:Lxaero/lib/common/config/option/IndexedConfigOption;
       946: aload_2
       947: invokestatic  #348                // Method java/lang/Integer.parseInt:(Ljava/lang/String;)I
       950: invokestatic  #354                // Method java/lang/Integer.valueOf:(I)Ljava/lang/Integer;
       953: invokevirtual #387                // Method xaero/lib/common/config/profile/ConfigProfile.set:(Lxaero/lib/common/config/option/ConfigOption;Ljava/lang/Object;)Ljava/lang/Object;
       956: pop
       957: goto          4987
       960: aload_1
       961: iconst_0
       962: aaload
       963: ldc_w         #518                // String chunkGrid
       966: invokevirtual #330                // Method java/lang/String.equalsIgnoreCase:(Ljava/lang/String;)Z
       969: ifeq          1021
       972: aload_3
       973: invokevirtual #380                // Method xaero/lib/client/config/ClientConfigManager.getCurrentProfile:()Lxaero/lib/common/config/profile/ConfigProfile;
       976: getstatic     #520                // Field xaero/hud/minimap/common/config/option/MinimapProfiledConfigOptions.CHUNK_GRID:Lxaero/lib/common/config/option/RangeConfigOption;
       979: aload_2
       980: ldc_w         #368                // String true
       983: invokevirtual #370                // Method java/lang/String.equals:(Ljava/lang/Object;)Z
       986: ifeq          993
       989: iconst_0
       990: goto          1011
       993: aload_2
       994: ldc_w         #453                // String false
       997: invokevirtual #370                // Method java/lang/String.equals:(Ljava/lang/Object;)Z
      1000: ifeq          1007
      1003: iconst_m1
      1004: goto          1011
      1007: aload_2
      1008: invokestatic  #348                // Method java/lang/Integer.parseInt:(Ljava/lang/String;)I
      1011: invokestatic  #354                // Method java/lang/Integer.valueOf:(I)Ljava/lang/Integer;
      1014: invokevirtual #387                // Method xaero/lib/common/config/profile/ConfigProfile.set:(Lxaero/lib/common/config/option/ConfigOption;Ljava/lang/Object;)Ljava/lang/Object;
      1017: pop
      1018: goto          4987
      1021: aload_1
      1022: iconst_0
      1023: aaload
      1024: ldc_w         #523                // String slimeChunks
      1027: invokevirtual #330                // Method java/lang/String.equalsIgnoreCase:(Ljava/lang/String;)Z
      1030: ifeq          1057
      1033: aload_3
      1034: invokevirtual #380                // Method xaero/lib/client/config/ClientConfigManager.getCurrentProfile:()Lxaero/lib/common/config/profile/ConfigProfile;
      1037: getstatic     #525                // Field xaero/hud/minimap/common/config/option/MinimapProfiledConfigOptions.SLIME_CHUNKS:Lxaero/lib/common/config/option/BooleanConfigOption;
      1040: aload_2
      1041: ldc_w         #368                // String true
      1044: invokevirtual #370                // Method java/lang/String.equals:(Ljava/lang/Object;)Z
      1047: invokestatic  #374                // Method java/lang/Boolean.valueOf:(Z)Ljava/lang/Boolean;
      1050: invokevirtual #387                // Method xaero/lib/common/config/profile/ConfigProfile.set:(Lxaero/lib/common/config/option/ConfigOption;Ljava/lang/Object;)Ljava/lang/Object;
      1053: pop
      1054: goto          4987
      1057: aload_1
      1058: iconst_0
      1059: aaload
      1060: ldc_w         #528                // String mapSafeMode
      1063: invokevirtual #330                // Method java/lang/String.equalsIgnoreCase:(Ljava/lang/String;)Z
      1066: ifeq          1093
      1069: aload_3
      1070: invokevirtual #380                // Method xaero/lib/client/config/ClientConfigManager.getCurrentProfile:()Lxaero/lib/common/config/profile/ConfigProfile;
      1073: getstatic     #530                // Field xaero/hud/minimap/common/config/option/MinimapProfiledConfigOptions.SAFE_MODE:Lxaero/lib/common/config/option/BooleanConfigOption;
      1076: aload_2
      1077: ldc_w         #368                // String true
      1080: invokevirtual #370                // Method java/lang/String.equals:(Ljava/lang/Object;)Z
      1083: invokestatic  #374                // Method java/lang/Boolean.valueOf:(Z)Ljava/lang/Boolean;
      1086: invokevirtual #387                // Method xaero/lib/common/config/profile/ConfigProfile.set:(Lxaero/lib/common/config/option/ConfigOption;Ljava/lang/Object;)Ljava/lang/Object;
      1089: pop
      1090: goto          4987
      1093: aload_1
      1094: iconst_0
      1095: aaload
      1096: ldc_w         #533                // String minimapOpacity
      1099: invokevirtual #330                // Method java/lang/String.equalsIgnoreCase:(Ljava/lang/String;)Z
      1102: ifeq          1129
      1105: aload_3
      1106: invokevirtual #380                // Method xaero/lib/client/config/ClientConfigManager.getCurrentProfile:()Lxaero/lib/common/config/profile/ConfigProfile;
      1109: getstatic     #535                // Field xaero/hud/minimap/common/config/option/MinimapProfiledConfigOptions.OPACITY:Lxaero/lib/common/config/option/RangeConfigOption;
      1112: aload_2
      1113: invokestatic  #538                // Method java/lang/Double.valueOf:(Ljava/lang/String;)Ljava/lang/Double;
      1116: invokevirtual #543                // Method java/lang/Double.intValue:()I
      1119: invokestatic  #354                // Method java/lang/Integer.valueOf:(I)Ljava/lang/Integer;
      1122: invokevirtual #387                // Method xaero/lib/common/config/profile/ConfigProfile.set:(Lxaero/lib/common/config/option/ConfigOption;Ljava/lang/Object;)Ljava/lang/Object;
      1125: pop
      1126: goto          4987
      1129: aload_1
      1130: iconst_0
      1131: aaload
      1132: ldc_w         #546                // String waypointsIngameIconScale
      1135: invokevirtual #330                // Method java/lang/String.equalsIgnoreCase:(Ljava/lang/String;)Z
      1138: ifeq          1162
      1141: aload_3
      1142: invokevirtual #380                // Method xaero/lib/client/config/ClientConfigManager.getCurrentProfile:()Lxaero/lib/common/config/profile/ConfigProfile;
      1145: getstatic     #548                // Field xaero/hud/minimap/common/config/option/MinimapProfiledConfigOptions.WAYPOINT_ICON_SCALE_IN_WORLD:Lxaero/lib/common/config/option/RangeConfigOption;
      1148: aload_2
      1149: invokestatic  #348                // Method java/lang/Integer.parseInt:(Ljava/lang/String;)I
      1152: invokestatic  #354                // Method java/lang/Integer.valueOf:(I)Ljava/lang/Integer;
      1155: invokevirtual #387                // Method xaero/lib/common/config/profile/ConfigProfile.set:(Lxaero/lib/common/config/option/ConfigOption;Ljava/lang/Object;)Ljava/lang/Object;
      1158: pop
      1159: goto          4987
      1162: aload_1
      1163: iconst_0
      1164: aaload
      1165: ldc_w         #551                // String waypointsIngameDistanceScale
      1168: invokevirtual #330                // Method java/lang/String.equalsIgnoreCase:(Ljava/lang/String;)Z
      1171: ifeq          1195
      1174: aload_3
      1175: invokevirtual #380                // Method xaero/lib/client/config/ClientConfigManager.getCurrentProfile:()Lxaero/lib/common/config/profile/ConfigProfile;
      1178: getstatic     #553                // Field xaero/hud/minimap/common/config/option/MinimapProfiledConfigOptions.WAYPOINT_DISTANCE_SCALE_IN_WORLD:Lxaero/lib/common/config/option/RangeConfigOption;
      1181: aload_2
      1182: invokestatic  #348                // Method java/lang/Integer.parseInt:(Ljava/lang/String;)I
      1185: invokestatic  #354                // Method java/lang/Integer.valueOf:(I)Ljava/lang/Integer;
      1188: invokevirtual #387                // Method xaero/lib/common/config/profile/ConfigProfile.set:(Lxaero/lib/common/config/option/ConfigOption;Ljava/lang/Object;)Ljava/lang/Object;
      1191: pop
      1192: goto          4987
      1195: aload_1
      1196: iconst_0
      1197: aaload
      1198: ldc_w         #556                // String waypointsIngameNameScale
      1201: invokevirtual #330                // Method java/lang/String.equalsIgnoreCase:(Ljava/lang/String;)Z
      1204: ifeq          1228
      1207: aload_3
      1208: invokevirtual #380                // Method xaero/lib/client/config/ClientConfigManager.getCurrentProfile:()Lxaero/lib/common/config/profile/ConfigProfile;
      1211: getstatic     #558                // Field xaero/hud/minimap/common/config/option/MinimapProfiledConfigOptions.WAYPOINT_NAME_SCALE_IN_WORLD:Lxaero/lib/common/config/option/RangeConfigOption;
      1214: aload_2
      1215: invokestatic  #348                // Method java/lang/Integer.parseInt:(Ljava/lang/String;)I
      1218: invokestatic  #354                // Method java/lang/Integer.valueOf:(I)Ljava/lang/Integer;
      1221: invokevirtual #387                // Method xaero/lib/common/config/profile/ConfigProfile.set:(Lxaero/lib/common/config/option/ConfigOption;Ljava/lang/Object;)Ljava/lang/Object;
      1224: pop
      1225: goto          4987
      1228: aload_1
      1229: iconst_0
      1230: aaload
      1231: ldc_w         #561                // String waypointsIngameCloseScale
      1234: invokevirtual #330                // Method java/lang/String.equalsIgnoreCase:(Ljava/lang/String;)Z
      1237: ifeq          1258
      1240: aload_3
      1241: invokevirtual #380                // Method xaero/lib/client/config/ClientConfigManager.getCurrentProfile:()Lxaero/lib/common/config/profile/ConfigProfile;
      1244: getstatic     #563                // Field xaero/hud/minimap/common/config/option/MinimapProfiledConfigOptions.WAYPOINT_CLOSE_SCALE_IN_WORLD:Lxaero/lib/common/config/option/SteppedConfigOption;
      1247: aload_2
      1248: invokestatic  #538                // Method java/lang/Double.valueOf:(Ljava/lang/String;)Ljava/lang/Double;
      1251: invokevirtual #387                // Method xaero/lib/common/config/profile/ConfigProfile.set:(Lxaero/lib/common/config/option/ConfigOption;Ljava/lang/Object;)Ljava/lang/Object;
      1254: pop
      1255: goto          4987
      1258: aload_1
      1259: iconst_0
      1260: aaload
      1261: ldc_w         #567                // String antiAliasing
      1264: invokevirtual #330                // Method java/lang/String.equalsIgnoreCase:(Ljava/lang/String;)Z
      1267: ifeq          1294
      1270: aload_3
      1271: invokevirtual #380                // Method xaero/lib/client/config/ClientConfigManager.getCurrentProfile:()Lxaero/lib/common/config/profile/ConfigProfile;
      1274: getstatic     #569                // Field xaero/hud/minimap/common/config/option/MinimapProfiledConfigOptions.ANTI_ALIASING:Lxaero/lib/common/config/option/BooleanConfigOption;
      1277: aload_2
      1278: ldc_w         #368                // String true
      1281: invokevirtual #370                // Method java/lang/String.equals:(Ljava/lang/Object;)Z
      1284: invokestatic  #374                // Method java/lang/Boolean.valueOf:(Z)Ljava/lang/Boolean;
      1287: invokevirtual #387                // Method xaero/lib/common/config/profile/ConfigProfile.set:(Lxaero/lib/common/config/option/ConfigOption;Ljava/lang/Object;)Ljava/lang/Object;
      1290: pop
      1291: goto          4987
      1294: aload_1
      1295: iconst_0
      1296: aaload
      1297: ldc_w         #572                // String blockColours
      1300: invokevirtual #330                // Method java/lang/String.equalsIgnoreCase:(Ljava/lang/String;)Z
      1303: ifeq          1327
      1306: aload_3
      1307: invokevirtual #380                // Method xaero/lib/client/config/ClientConfigManager.getCurrentProfile:()Lxaero/lib/common/config/profile/ConfigProfile;
      1310: getstatic     #574                // Field xaero/hud/minimap/common/config/option/MinimapProfiledConfigOptions.BLOCK_COLORS:Lxaero/lib/common/config/option/RangeConfigOption;
      1313: aload_2
      1314: invokestatic  #348                // Method java/lang/Integer.parseInt:(Ljava/lang/String;)I
      1317: invokestatic  #354                // Method java/lang/Integer.valueOf:(I)Ljava/lang/Integer;
      1320: invokevirtual #387                // Method xaero/lib/common/config/profile/ConfigProfile.set:(Lxaero/lib/common/config/option/ConfigOption;Ljava/lang/Object;)Ljava/lang/Object;
      1323: pop
      1324: goto          4987
      1327: aload_1
      1328: iconst_0
      1329: aaload
      1330: ldc_w         #577                // String lighting
      1333: invokevirtual #330                // Method java/lang/String.equalsIgnoreCase:(Ljava/lang/String;)Z
      1336: ifeq          1363
      1339: aload_3
      1340: invokevirtual #380                // Method xaero/lib/client/config/ClientConfigManager.getCurrentProfile:()Lxaero/lib/common/config/profile/ConfigProfile;
      1343: getstatic     #579                // Field xaero/hud/minimap/common/config/option/MinimapProfiledConfigOptions.LIGHTING:Lxaero/lib/common/config/option/BooleanConfigOption;
      1346: aload_2
      1347: ldc_w         #368                // String true
      1350: invokevirtual #370                // Method java/lang/String.equals:(Ljava/lang/Object;)Z
      1353: invokestatic  #374                // Method java/lang/Boolean.valueOf:(Z)Ljava/lang/Boolean;
      1356: invokevirtual #387                // Method xaero/lib/common/config/profile/ConfigProfile.set:(Lxaero/lib/common/config/option/ConfigOption;Ljava/lang/Object;)Ljava/lang/Object;
      1359: pop
      1360: goto          4987
      1363: aload_1
      1364: iconst_0
      1365: aaload
      1366: ldc_w         #582                // String dotsStyle
      1369: invokevirtual #330                // Method java/lang/String.equalsIgnoreCase:(Ljava/lang/String;)Z
      1372: ifeq          1396
      1375: aload_3
      1376: invokevirtual #380                // Method xaero/lib/client/config/ClientConfigManager.getCurrentProfile:()Lxaero/lib/common/config/profile/ConfigProfile;
      1379: getstatic     #584                // Field xaero/hud/minimap/common/config/option/MinimapProfiledConfigOptions.RADAR_DOTS_STYLE:Lxaero/lib/common/config/option/RangeConfigOption;
      1382: aload_2
      1383: invokestatic  #348                // Method java/lang/Integer.parseInt:(Ljava/lang/String;)I
      1386: invokestatic  #354                // Method java/lang/Integer.valueOf:(I)Ljava/lang/Integer;
      1389: invokevirtual #387                // Method xaero/lib/common/config/profile/ConfigProfile.set:(Lxaero/lib/common/config/option/ConfigOption;Ljava/lang/Object;)Ljava/lang/Object;
      1392: pop
      1393: goto          4987
      1396: aload_1
      1397: iconst_0
      1398: aaload
      1399: ldc_w         #587                // String dotNameScale
      1402: invokevirtual #330                // Method java/lang/String.equalsIgnoreCase:(Ljava/lang/String;)Z
      1405: ifeq          1426
      1408: aload_3
      1409: invokevirtual #380                // Method xaero/lib/client/config/ClientConfigManager.getCurrentProfile:()Lxaero/lib/common/config/profile/ConfigProfile;
      1412: getstatic     #589                // Field xaero/hud/minimap/common/config/option/MinimapProfiledConfigOptions.RADAR_NAME_SCALE:Lxaero/lib/common/config/option/SteppedConfigOption;
      1415: aload_2
      1416: invokestatic  #538                // Method java/lang/Double.valueOf:(Ljava/lang/String;)Ljava/lang/Double;
      1419: invokevirtual #387                // Method xaero/lib/common/config/profile/ConfigProfile.set:(Lxaero/lib/common/config/option/ConfigOption;Ljava/lang/Object;)Ljava/lang/Object;
      1422: pop
      1423: goto          4987
      1426: aload_1
      1427: iconst_0
      1428: aaload
      1429: ldc_w         #592                // String compassOverEverything
      1432: invokevirtual #330                // Method java/lang/String.equalsIgnoreCase:(Ljava/lang/String;)Z
      1435: ifeq          1462
      1438: aload_3
      1439: invokevirtual #380                // Method xaero/lib/client/config/ClientConfigManager.getCurrentProfile:()Lxaero/lib/common/config/profile/ConfigProfile;
      1442: getstatic     #594                // Field xaero/hud/minimap/common/config/option/MinimapProfiledConfigOptions.COMPASS_OVER_EVERYTHING:Lxaero/lib/common/config/option/BooleanConfigOption;
      1445: aload_2
      1446: ldc_w         #368                // String true
      1449: invokevirtual #370                // Method java/lang/String.equals:(Ljava/lang/Object;)Z
      1452: invokestatic  #374                // Method java/lang/Boolean.valueOf:(Z)Ljava/lang/Boolean;
      1455: invokevirtual #387                // Method xaero/lib/common/config/profile/ConfigProfile.set:(Lxaero/lib/common/config/option/ConfigOption;Ljava/lang/Object;)Ljava/lang/Object;
      1458: pop
      1459: goto          4987
      1462: aload_1
      1463: iconst_0
      1464: aaload
      1465: ldc_w         #597                // String showBiome
      1468: invokevirtual #330                // Method java/lang/String.equalsIgnoreCase:(Ljava/lang/String;)Z
      1471: ifeq          1491
      1474: aload_0
      1475: aload_2
      1476: ldc_w         #368                // String true
      1479: invokevirtual #370                // Method java/lang/String.equals:(Ljava/lang/Object;)Z
      1482: invokestatic  #374                // Method java/lang/Boolean.valueOf:(Z)Ljava/lang/Boolean;
      1485: putfield      #599                // Field showBiomeLegacy:Ljava/lang/Boolean;
      1488: goto          4987
      1491: aload_1
      1492: iconst_0
      1493: aaload
      1494: ldc_w         #602                // String showFlowers
      1497: invokevirtual #330                // Method java/lang/String.equalsIgnoreCase:(Ljava/lang/String;)Z
      1500: ifeq          1527
      1503: aload_3
      1504: invokevirtual #380                // Method xaero/lib/client/config/ClientConfigManager.getCurrentProfile:()Lxaero/lib/common/config/profile/ConfigProfile;
      1507: getstatic     #604                // Field xaero/hud/minimap/common/config/option/MinimapProfiledConfigOptions.DISPLAY_FLOWERS:Lxaero/lib/common/config/option/BooleanConfigOption;
      1510: aload_2
      1511: ldc_w         #368                // String true
      1514: invokevirtual #370                // Method java/lang/String.equals:(Ljava/lang/Object;)Z
      1517: invokestatic  #374                // Method java/lang/Boolean.valueOf:(Z)Ljava/lang/Boolean;
      1520: invokevirtual #387                // Method xaero/lib/common/config/profile/ConfigProfile.set:(Lxaero/lib/common/config/option/ConfigOption;Ljava/lang/Object;)Ljava/lang/Object;
      1523: pop
      1524: goto          4987
      1527: aload_1
      1528: iconst_0
      1529: aaload
      1530: ldc_w         #607                // String keepWaypointNames
      1533: invokevirtual #330                // Method java/lang/String.equalsIgnoreCase:(Ljava/lang/String;)Z
      1536: ifeq          1563
      1539: aload_3
      1540: invokevirtual #380                // Method xaero/lib/client/config/ClientConfigManager.getCurrentProfile:()Lxaero/lib/common/config/profile/ConfigProfile;
      1543: getstatic     #609                // Field xaero/hud/minimap/common/config/option/MinimapProfiledConfigOptions.WAYPOINT_NAME_IN_WORLD:Lxaero/lib/common/config/option/BooleanConfigOption;
      1546: aload_2
      1547: ldc_w         #368                // String true
      1550: invokevirtual #370                // Method java/lang/String.equals:(Ljava/lang/Object;)Z
      1553: invokestatic  #374                // Method java/lang/Boolean.valueOf:(Z)Ljava/lang/Boolean;
      1556: invokevirtual #387                // Method xaero/lib/common/config/profile/ConfigProfile.set:(Lxaero/lib/common/config/option/ConfigOption;Ljava/lang/Object;)Ljava/lang/Object;
      1559: pop
      1560: goto          4987
      1563: aload_1
      1564: iconst_0
      1565: aaload
      1566: ldc_w         #612                // String waypointsDistance
      1569: invokevirtual #330                // Method java/lang/String.equalsIgnoreCase:(Ljava/lang/String;)Z
      1572: ifeq          1644
      1575: aload_2
      1576: invokestatic  #538                // Method java/lang/Double.valueOf:(Ljava/lang/String;)Ljava/lang/Double;
      1579: invokevirtual #614                // Method java/lang/Double.doubleValue:()D
      1582: dstore        4
      1584: dload         4
      1586: dconst_0
      1587: dcmpg
      1588: ifgt          1595
      1591: iconst_0
      1592: goto          1619
      1595: ldc2_w        #618                // double 3.0d
      1598: dload         4
      1600: invokestatic  #620                // Method java/lang/Math.log:(D)D
      1603: ldc2_w        #196                // double 2.0d
      1606: invokestatic  #620                // Method java/lang/Math.log:(D)D
      1609: ddiv
      1610: invokestatic  #624                // Method java/lang/Math.ceil:(D)D
      1613: invokestatic  #627                // Method java/lang/Math.max:(DD)D
      1616: d2i
      1617: iconst_2
      1618: isub
      1619: istore        6
      1621: aload_3
      1622: invokevirtual #380                // Method xaero/lib/client/config/ClientConfigManager.getCurrentProfile:()Lxaero/lib/common/config/profile/ConfigProfile;
      1625: getstatic     #630                // Field xaero/hud/minimap/common/config/option/MinimapProfiledConfigOptions.WAYPOINT_MAX_DISTANCE:Lxaero/lib/common/config/option/IndexedConfigOption;
      1628: aload_0
      1629: iload         6
      1631: invokevirtual #633                // Method getMaxWaypointsDistance:(I)I
      1634: invokestatic  #354                // Method java/lang/Integer.valueOf:(I)Ljava/lang/Integer;
      1637: invokevirtual #387                // Method xaero/lib/common/config/profile/ConfigProfile.set:(Lxaero/lib/common/config/option/ConfigOption;Ljava/lang/Object;)Ljava/lang/Object;
      1640: pop
      1641: goto          4987
      1644: aload_1
      1645: iconst_0
      1646: aaload
      1647: ldc_w         #637                // String waypointsDistanceExp
      1650: invokevirtual #330                // Method java/lang/String.equalsIgnoreCase:(Ljava/lang/String;)Z
      1653: ifeq          1681
      1656: aload_3
      1657: invokevirtual #380                // Method xaero/lib/client/config/ClientConfigManager.getCurrentProfile:()Lxaero/lib/common/config/profile/ConfigProfile;
      1660: getstatic     #630                // Field xaero/hud/minimap/common/config/option/MinimapProfiledConfigOptions.WAYPOINT_MAX_DISTANCE:Lxaero/lib/common/config/option/IndexedConfigOption;
      1663: aload_0
      1664: aload_2
      1665: invokestatic  #348                // Method java/lang/Integer.parseInt:(Ljava/lang/String;)I
      1668: invokevirtual #633                // Method getMaxWaypointsDistance:(I)I
      1671: invokestatic  #354                // Method java/lang/Integer.valueOf:(I)Ljava/lang/Integer;
      1674: invokevirtual #387                // Method xaero/lib/common/config/profile/ConfigProfile.set:(Lxaero/lib/common/config/option/ConfigOption;Ljava/lang/Object;)Ljava/lang/Object;
      1677: pop
      1678: goto          4987
      1681: aload_1
      1682: iconst_0
      1683: aaload
      1684: ldc_w         #639                // String waypointsDistanceMin
      1687: invokevirtual #330                // Method java/lang/String.equalsIgnoreCase:(Ljava/lang/String;)Z
      1690: ifeq          1711
      1693: aload_3
      1694: invokevirtual #380                // Method xaero/lib/client/config/ClientConfigManager.getCurrentProfile:()Lxaero/lib/common/config/profile/ConfigProfile;
      1697: getstatic     #641                // Field xaero/hud/minimap/common/config/option/MinimapProfiledConfigOptions.WAYPOINT_MIN_DISTANCE_IN_WORLD:Lxaero/lib/common/config/option/SteppedConfigOption;
      1700: aload_2
      1701: invokestatic  #538                // Method java/lang/Double.valueOf:(Ljava/lang/String;)Ljava/lang/Double;
      1704: invokevirtual #387                // Method xaero/lib/common/config/profile/ConfigProfile.set:(Lxaero/lib/common/config/option/ConfigOption;Ljava/lang/Object;)Ljava/lang/Object;
      1707: pop
      1708: goto          4987
      1711: aload_1
      1712: iconst_0
      1713: aaload
      1714: ldc_w         #644                // String waypointTp
      1717: invokevirtual #330                // Method java/lang/String.equalsIgnoreCase:(Ljava/lang/String;)Z
      1720: ifeq          1760
      1723: aload_3
      1724: invokevirtual #380                // Method xaero/lib/client/config/ClientConfigManager.getCurrentProfile:()Lxaero/lib/common/config/profile/ConfigProfile;
      1727: getstatic     #646                // Field xaero/hud/minimap/common/config/option/MinimapProfiledConfigOptions.WAYPOINT_DEFAULT_TELEPORT_FORMAT:Lxaero/lib/common/config/option/ConfigOption;
      1730: aload_2
      1731: invokedynamic #649,  0            // InvokeDynamic #2:makeConcatWithConstants:(Ljava/lang/String;)Ljava/lang/String;
      1736: invokevirtual #387                // Method xaero/lib/common/config/profile/ConfigProfile.set:(Lxaero/lib/common/config/option/ConfigOption;Ljava/lang/Object;)Ljava/lang/Object;
      1739: pop
      1740: aload_3
      1741: invokevirtual #380                // Method xaero/lib/client/config/ClientConfigManager.getCurrentProfile:()Lxaero/lib/common/config/profile/ConfigProfile;
      1744: getstatic     #652                // Field xaero/hud/minimap/common/config/option/MinimapProfiledConfigOptions.WAYPOINT_DEFAULT_TELEPORT_ROTATION_FORMAT:Lxaero/lib/common/config/option/ConfigOption;
      1747: aload_2
      1748: invokedynamic #655,  0            // InvokeDynamic #3:makeConcatWithConstants:(Ljava/lang/String;)Ljava/lang/String;
      1753: invokevirtual #387                // Method xaero/lib/common/config/profile/ConfigProfile.set:(Lxaero/lib/common/config/option/ConfigOption;Ljava/lang/Object;)Ljava/lang/Object;
      1756: pop
      1757: goto          4987
      1760: aload_1
      1761: iconst_0
      1762: aaload
      1763: ldc_w         #656                // String waypointTPCommand
      1766: invokevirtual #330                // Method java/lang/String.equalsIgnoreCase:(Ljava/lang/String;)Z
      1769: ifeq          1827
      1772: aload_3
      1773: invokevirtual #380                // Method xaero/lib/client/config/ClientConfigManager.getCurrentProfile:()Lxaero/lib/common/config/profile/ConfigProfile;
      1776: getstatic     #646                // Field xaero/hud/minimap/common/config/option/MinimapProfiledConfigOptions.WAYPOINT_DEFAULT_TELEPORT_FORMAT:Lxaero/lib/common/config/option/ConfigOption;
      1779: aload_2
      1780: ldc_w         #658                // String ^col^
      1783: ldc_w         #660                // String :
      1786: invokevirtual #662                // Method java/lang/String.replace:(Ljava/lang/CharSequence;Ljava/lang/CharSequence;)Ljava/lang/String;
      1789: invokedynamic #666,  0            // InvokeDynamic #4:makeConcatWithConstants:(Ljava/lang/String;)Ljava/lang/String;
      1794: invokevirtual #387                // Method xaero/lib/common/config/profile/ConfigProfile.set:(Lxaero/lib/common/config/option/ConfigOption;Ljava/lang/Object;)Ljava/lang/Object;
      1797: pop
      1798: aload_3
      1799: invokevirtual #380                // Method xaero/lib/client/config/ClientConfigManager.getCurrentProfile:()Lxaero/lib/common/config/profile/ConfigProfile;
      1802: getstatic     #652                // Field xaero/hud/minimap/common/config/option/MinimapProfiledConfigOptions.WAYPOINT_DEFAULT_TELEPORT_ROTATION_FORMAT:Lxaero/lib/common/config/option/ConfigOption;
      1805: aload_2
      1806: ldc_w         #658                // String ^col^
      1809: ldc_w         #660                // String :
      1812: invokevirtual #662                // Method java/lang/String.replace:(Ljava/lang/CharSequence;Ljava/lang/CharSequence;)Ljava/lang/String;
      1815: invokedynamic #667,  0            // InvokeDynamic #5:makeConcatWithConstants:(Ljava/lang/String;)Ljava/lang/String;
      1820: invokevirtual #387                // Method xaero/lib/common/config/profile/ConfigProfile.set:(Lxaero/lib/common/config/option/ConfigOption;Ljava/lang/Object;)Ljava/lang/Object;
      1823: pop
      1824: goto          4987
      1827: aload_1
      1828: iconst_0
      1829: aaload
      1830: ldc_w         #668                // String defaultWaypointTPCommandFormat
      1833: invokevirtual #330                // Method java/lang/String.equalsIgnoreCase:(Ljava/lang/String;)Z
      1836: ifeq          1863
      1839: aload_3
      1840: invokevirtual #380                // Method xaero/lib/client/config/ClientConfigManager.getCurrentProfile:()Lxaero/lib/common/config/profile/ConfigProfile;
      1843: getstatic     #646                // Field xaero/hud/minimap/common/config/option/MinimapProfiledConfigOptions.WAYPOINT_DEFAULT_TELEPORT_FORMAT:Lxaero/lib/common/config/option/ConfigOption;
      1846: aload_2
      1847: ldc_w         #658                // String ^col^
      1850: ldc_w         #660                // String :
      1853: invokevirtual #662                // Method java/lang/String.replace:(Ljava/lang/CharSequence;Ljava/lang/CharSequence;)Ljava/lang/String;
      1856: invokevirtual #387                // Method xaero/lib/common/config/profile/ConfigProfile.set:(Lxaero/lib/common/config/option/ConfigOption;Ljava/lang/Object;)Ljava/lang/Object;
      1859: pop
      1860: goto          4987
      1863: aload_1
      1864: iconst_0
      1865: aaload
      1866: ldc_w         #670                // String defaultWaypointTPCommandRotationFormat
      1869: invokevirtual #330                // Method java/lang/String.equalsIgnoreCase:(Ljava/lang/String;)Z
      1872: ifeq          1899
      1875: aload_3
      1876: invokevirtual #380                // Method xaero/lib/client/config/ClientConfigManager.getCurrentProfile:()Lxaero/lib/common/config/profile/ConfigProfile;
      1879: getstatic     #652                // Field xaero/hud/minimap/common/config/option/MinimapProfiledConfigOptions.WAYPOINT_DEFAULT_TELEPORT_ROTATION_FORMAT:Lxaero/lib/common/config/option/ConfigOption;
      1882: aload_2
      1883: ldc_w         #658                // String ^col^
      1886: ldc_w         #660                // String :
      1889: invokevirtual #662                // Method java/lang/String.replace:(Ljava/lang/CharSequence;Ljava/lang/CharSequence;)Ljava/lang/String;
      1892: invokevirtual #387                // Method xaero/lib/common/config/profile/ConfigProfile.set:(Lxaero/lib/common/config/option/ConfigOption;Ljava/lang/Object;)Ljava/lang/Object;
      1895: pop
      1896: goto          4987
      1899: aload_1
      1900: iconst_0
      1901: aaload
      1902: ldc_w         #672                // String arrowScale
      1905: invokevirtual #330                // Method java/lang/String.equalsIgnoreCase:(Ljava/lang/String;)Z
      1908: ifeq          1929
      1911: aload_3
      1912: invokevirtual #380                // Method xaero/lib/client/config/ClientConfigManager.getCurrentProfile:()Lxaero/lib/common/config/profile/ConfigProfile;
      1915: getstatic     #674                // Field xaero/hud/minimap/common/config/option/MinimapProfiledConfigOptions.ARROW_SCALE:Lxaero/lib/common/config/option/SteppedConfigOption;
      1918: aload_2
      1919: invokestatic  #538                // Method java/lang/Double.valueOf:(Ljava/lang/String;)Ljava/lang/Double;
      1922: invokevirtual #387                // Method xaero/lib/common/config/profile/ConfigProfile.set:(Lxaero/lib/common/config/option/ConfigOption;Ljava/lang/Object;)Ljava/lang/Object;
      1925: pop
      1926: goto          4987
      1929: aload_1
      1930: iconst_0
      1931: aaload
      1932: ldc_w         #677                // String arrowColour
      1935: invokevirtual #330                // Method java/lang/String.equalsIgnoreCase:(Ljava/lang/String;)Z
      1938: ifeq          1962
      1941: aload_3
      1942: invokevirtual #380                // Method xaero/lib/client/config/ClientConfigManager.getCurrentProfile:()Lxaero/lib/common/config/profile/ConfigProfile;
      1945: getstatic     #679                // Field xaero/hud/minimap/common/config/option/MinimapProfiledConfigOptions.ARROW_COLOR:Lxaero/lib/common/config/option/RangeConfigOption;
      1948: aload_2
      1949: invokestatic  #348                // Method java/lang/Integer.parseInt:(Ljava/lang/String;)I
      1952: invokestatic  #354                // Method java/lang/Integer.valueOf:(I)Ljava/lang/Integer;
      1955: invokevirtual #387                // Method xaero/lib/common/config/profile/ConfigProfile.set:(Lxaero/lib/common/config/option/ConfigOption;Ljava/lang/Object;)Ljava/lang/Object;
      1958: pop
      1959: goto          4987
      1962: aload_1
      1963: iconst_0
      1964: aaload
      1965: ldc_w         #682                // String seed
      1968: invokevirtual #330                // Method java/lang/String.equalsIgnoreCase:(Ljava/lang/String;)Z
      1971: ifeq          2004
      1974: getstatic     #91                 // Field legacyServerSlimeSeeds:Ljava/util/HashMap;
      1977: new           #684                // class xaero/hud/path/XaeroPathReader
      1980: dup
      1981: invokespecial #686                // Method xaero/hud/path/XaeroPathReader."<init>":()V
      1984: aload_2
      1985: invokevirtual #687                // Method xaero/hud/path/XaeroPathReader.read:(Ljava/lang/String;)Lxaero/hud/path/XaeroPath;
      1988: aload_1
      1989: iconst_2
      1990: aaload
      1991: invokestatic  #691                // Method java/lang/Long.parseLong:(Ljava/lang/String;)J
      1994: invokestatic  #95                 // Method java/lang/Long.valueOf:(J)Ljava/lang/Long;
      1997: invokevirtual #101                // Method java/util/HashMap.put:(Ljava/lang/Object;Ljava/lang/Object;)Ljava/lang/Object;
      2000: pop
      2001: goto          4987
      2004: aload_1
      2005: iconst_0
      2006: aaload
      2007: ldc_w         #695                // String smoothDots
      2010: invokevirtual #330                // Method java/lang/String.equalsIgnoreCase:(Ljava/lang/String;)Z
      2013: ifeq          2040
      2016: aload_3
      2017: invokevirtual #380                // Method xaero/lib/client/config/ClientConfigManager.getCurrentProfile:()Lxaero/lib/common/config/profile/ConfigProfile;
      2020: getstatic     #697                // Field xaero/hud/minimap/common/config/option/MinimapProfiledConfigOptions.RADAR_SMOOTH_DOTS:Lxaero/lib/common/config/option/BooleanConfigOption;
      2023: aload_2
      2024: ldc_w         #368                // String true
      2027: invokevirtual #370                // Method java/lang/String.equals:(Ljava/lang/Object;)Z
      2030: invokestatic  #374                // Method java/lang/Boolean.valueOf:(Z)Ljava/lang/Boolean;
      2033: invokevirtual #387                // Method xaero/lib/common/config/profile/ConfigProfile.set:(Lxaero/lib/common/config/option/ConfigOption;Ljava/lang/Object;)Ljava/lang/Object;
      2036: pop
      2037: goto          4987
      2040: aload_1
      2041: iconst_0
      2042: aaload
      2043: ldc_w         #700                // String worldMap
      2046: invokevirtual #330                // Method java/lang/String.equalsIgnoreCase:(Ljava/lang/String;)Z
      2049: ifeq          2076
      2052: aload_3
      2053: invokevirtual #380                // Method xaero/lib/client/config/ClientConfigManager.getCurrentProfile:()Lxaero/lib/common/config/profile/ConfigProfile;
      2056: getstatic     #702                // Field xaero/hud/minimap/common/config/option/MinimapProfiledConfigOptions.DISPLAY_WORLD_MAP_CHUNKS:Lxaero/lib/common/config/option/BooleanConfigOption;
      2059: aload_2
      2060: ldc_w         #368                // String true
      2063: invokevirtual #370                // Method java/lang/String.equals:(Ljava/lang/Object;)Z
      2066: invokestatic  #374                // Method java/lang/Boolean.valueOf:(Z)Ljava/lang/Boolean;
      2069: invokevirtual #387                // Method xaero/lib/common/config/profile/ConfigProfile.set:(Lxaero/lib/common/config/option/ConfigOption;Ljava/lang/Object;)Ljava/lang/Object;
      2072: pop
      2073: goto          4987
      2076: aload_1
      2077: iconst_0
      2078: aaload
      2079: ldc_w         #705                // String terrainDepth
      2082: invokevirtual #330                // Method java/lang/String.equalsIgnoreCase:(Ljava/lang/String;)Z
      2085: ifeq          2112
      2088: aload_3
      2089: invokevirtual #380                // Method xaero/lib/client/config/ClientConfigManager.getCurrentProfile:()Lxaero/lib/common/config/profile/ConfigProfile;
      2092: getstatic     #707                // Field xaero/hud/minimap/common/config/option/MinimapProfiledConfigOptions.TERRAIN_DEPTH:Lxaero/lib/common/config/option/BooleanConfigOption;
      2095: aload_2
      2096: ldc_w         #368                // String true
      2099: invokevirtual #370                // Method java/lang/String.equals:(Ljava/lang/Object;)Z
      2102: invokestatic  #374                // Method java/lang/Boolean.valueOf:(Z)Ljava/lang/Boolean;
      2105: invokevirtual #387                // Method xaero/lib/common/config/profile/ConfigProfile.set:(Lxaero/lib/common/config/option/ConfigOption;Ljava/lang/Object;)Ljava/lang/Object;
      2108: pop
      2109: goto          4987
      2112: aload_1
      2113: iconst_0
      2114: aaload
      2115: ldc_w         #710                // String terrainSlopes
      2118: invokevirtual #330                // Method java/lang/String.equalsIgnoreCase:(Ljava/lang/String;)Z
      2121: ifeq          2173
      2124: aload_3
      2125: invokevirtual #380                // Method xaero/lib/client/config/ClientConfigManager.getCurrentProfile:()Lxaero/lib/common/config/profile/ConfigProfile;
      2128: getstatic     #712                // Field xaero/hud/minimap/common/config/option/MinimapProfiledConfigOptions.TERRAIN_SLOPES:Lxaero/lib/common/config/option/RangeConfigOption;
      2131: aload_2
      2132: ldc_w         #368                // String true
      2135: invokevirtual #370                // Method java/lang/String.equals:(Ljava/lang/Object;)Z
      2138: ifeq          2145
      2141: iconst_2
      2142: goto          2163
      2145: aload_2
      2146: ldc_w         #453                // String false
      2149: invokevirtual #370                // Method java/lang/String.equals:(Ljava/lang/Object;)Z
      2152: ifeq          2159
      2155: iconst_0
      2156: goto          2163
      2159: aload_2
      2160: invokestatic  #348                // Method java/lang/Integer.parseInt:(Ljava/lang/String;)I
      2163: invokestatic  #354                // Method java/lang/Integer.valueOf:(I)Ljava/lang/Integer;
      2166: invokevirtual #387                // Method xaero/lib/common/config/profile/ConfigProfile.set:(Lxaero/lib/common/config/option/ConfigOption;Ljava/lang/Object;)Ljava/lang/Object;
      2169: pop
      2170: goto          4987
      2173: aload_1
      2174: iconst_0
      2175: aaload
      2176: ldc_w         #715                // String alwaysArrow
      2179: invokevirtual #330                // Method java/lang/String.equalsIgnoreCase:(Ljava/lang/String;)Z
      2182: ifeq          2213
      2185: aload_2
      2186: ldc_w         #368                // String true
      2189: invokevirtual #370                // Method java/lang/String.equals:(Ljava/lang/Object;)Z
      2192: ifeq          2213
      2195: aload_3
      2196: invokevirtual #380                // Method xaero/lib/client/config/ClientConfigManager.getCurrentProfile:()Lxaero/lib/common/config/profile/ConfigProfile;
      2199: getstatic     #717                // Field xaero/hud/minimap/common/config/option/MinimapProfiledConfigOptions.RADAR_MAIN_ENTITY:Lxaero/lib/common/config/option/RangeConfigOption;
      2202: iconst_2
      2203: invokestatic  #354                // Method java/lang/Integer.valueOf:(I)Ljava/lang/Integer;
      2206: invokevirtual #387                // Method xaero/lib/common/config/profile/ConfigProfile.set:(Lxaero/lib/common/config/option/ConfigOption;Ljava/lang/Object;)Ljava/lang/Object;
      2209: pop
      2210: goto          4987
      2213: aload_1
      2214: iconst_0
      2215: aaload
      2216: ldc_w         #720                // String mainEntityAs
      2219: invokevirtual #330                // Method java/lang/String.equalsIgnoreCase:(Ljava/lang/String;)Z
      2222: ifeq          2246
      2225: aload_3
      2226: invokevirtual #380                // Method xaero/lib/client/config/ClientConfigManager.getCurrentProfile:()Lxaero/lib/common/config/profile/ConfigProfile;
      2229: getstatic     #717                // Field xaero/hud/minimap/common/config/option/MinimapProfiledConfigOptions.RADAR_MAIN_ENTITY:Lxaero/lib/common/config/option/RangeConfigOption;
      2232: aload_2
      2233: invokestatic  #348                // Method java/lang/Integer.parseInt:(Ljava/lang/String;)I
      2236: invokestatic  #354                // Method java/lang/Integer.valueOf:(I)Ljava/lang/Integer;
      2239: invokevirtual #387                // Method xaero/lib/common/config/profile/ConfigProfile.set:(Lxaero/lib/common/config/option/ConfigOption;Ljava/lang/Object;)Ljava/lang/Object;
      2242: pop
      2243: goto          4987
      2246: aload_1
      2247: iconst_0
      2248: aaload
      2249: ldc_w         #722                // String blockTransparency
      2252: invokevirtual #330                // Method java/lang/String.equalsIgnoreCase:(Ljava/lang/String;)Z
      2255: ifeq          2282
      2258: aload_3
      2259: invokevirtual #380                // Method xaero/lib/client/config/ClientConfigManager.getCurrentProfile:()Lxaero/lib/common/config/profile/ConfigProfile;
      2262: getstatic     #724                // Field xaero/hud/minimap/common/config/option/MinimapProfiledConfigOptions.BLOCK_TRANSPARENCY:Lxaero/lib/common/config/option/BooleanConfigOption;
      2265: aload_2
      2266: ldc_w         #368                // String true
      2269: invokevirtual #370                // Method java/lang/String.equals:(Ljava/lang/Object;)Z
      2272: invokestatic  #374                // Method java/lang/Boolean.valueOf:(Z)Ljava/lang/Boolean;
      2275: invokevirtual #387                // Method xaero/lib/common/config/profile/ConfigProfile.set:(Lxaero/lib/common/config/option/ConfigOption;Ljava/lang/Object;)Ljava/lang/Object;
      2278: pop
      2279: goto          4987
      2282: aload_1
      2283: iconst_0
      2284: aaload
      2285: ldc_w         #727                // String waypointOpacityIngame
      2288: invokevirtual #330                // Method java/lang/String.equalsIgnoreCase:(Ljava/lang/String;)Z
      2291: ifeq          2315
      2294: aload_3
      2295: invokevirtual #380                // Method xaero/lib/client/config/ClientConfigManager.getCurrentProfile:()Lxaero/lib/common/config/profile/ConfigProfile;
      2298: getstatic     #729                // Field xaero/hud/minimap/common/config/option/MinimapProfiledConfigOptions.WAYPOINT_OPACITY_IN_WORLD:Lxaero/lib/common/config/option/RangeConfigOption;
      2301: aload_2
      2302: invokestatic  #348                // Method java/lang/Integer.parseInt:(Ljava/lang/String;)I
      2305: invokestatic  #354                // Method java/lang/Integer.valueOf:(I)Ljava/lang/Integer;
      2308: invokevirtual #387                // Method xaero/lib/common/config/profile/ConfigProfile.set:(Lxaero/lib/common/config/option/ConfigOption;Ljava/lang/Object;)Ljava/lang/Object;
      2311: pop
      2312: goto          4987
      2315: aload_1
      2316: iconst_0
      2317: aaload
      2318: ldc_w         #732                // String waypointOpacityMap
      2321: invokevirtual #330                // Method java/lang/String.equalsIgnoreCase:(Ljava/lang/String;)Z
      2324: ifeq          2348
      2327: aload_3
      2328: invokevirtual #380                // Method xaero/lib/client/config/ClientConfigManager.getCurrentProfile:()Lxaero/lib/common/config/profile/ConfigProfile;
      2331: getstatic     #734                // Field xaero/hud/minimap/common/config/option/MinimapProfiledConfigOptions.WAYPOINT_OPACITY_ON_MINIMAP:Lxaero/lib/common/config/option/RangeConfigOption;
      2334: aload_2
      2335: invokestatic  #348                // Method java/lang/Integer.parseInt:(Ljava/lang/String;)I
      2338: invokestatic  #354                // Method java/lang/Integer.valueOf:(I)Ljava/lang/Integer;
      2341: invokevirtual #387                // Method xaero/lib/common/config/profile/ConfigProfile.set:(Lxaero/lib/common/config/option/ConfigOption;Ljava/lang/Object;)Ljava/lang/Object;
      2344: pop
      2345: goto          4987
      2348: aload_1
      2349: iconst_0
      2350: aaload
      2351: ldc_w         #737                // String hideWorldNames
      2354: invokevirtual #330                // Method java/lang/String.equalsIgnoreCase:(Ljava/lang/String;)Z
      2357: ifeq          2409
      2360: aload_3
      2361: invokevirtual #380                // Method xaero/lib/client/config/ClientConfigManager.getCurrentProfile:()Lxaero/lib/common/config/profile/ConfigProfile;
      2364: getstatic     #739                // Field xaero/hud/minimap/common/config/option/MinimapProfiledConfigOptions.HIDE_WORLD_NAMES:Lxaero/lib/common/config/option/RangeConfigOption;
      2367: aload_2
      2368: ldc_w         #368                // String true
      2371: invokevirtual #370                // Method java/lang/String.equals:(Ljava/lang/Object;)Z
      2374: ifeq          2381
      2377: iconst_2
      2378: goto          2399
      2381: aload_2
      2382: ldc_w         #453                // String false
      2385: invokevirtual #370                // Method java/lang/String.equals:(Ljava/lang/Object;)Z
      2388: ifeq          2395
      2391: iconst_1
      2392: goto          2399
      2395: aload_2
      2396: invokestatic  #348                // Method java/lang/Integer.parseInt:(Ljava/lang/String;)I
      2399: invokestatic  #354                // Method java/lang/Integer.valueOf:(I)Ljava/lang/Integer;
      2402: invokevirtual #387                // Method xaero/lib/common/config/profile/ConfigProfile.set:(Lxaero/lib/common/config/option/ConfigOption;Ljava/lang/Object;)Ljava/lang/Object;
      2405: pop
      2406: goto          4987
      2409: aload_1
      2410: iconst_0
      2411: aaload
      2412: ldc_w         #742                // String openSlimeSettings
      2415: invokevirtual #330                // Method java/lang/String.equalsIgnoreCase:(Ljava/lang/String;)Z
      2418: ifeq          2445
      2421: aload_3
      2422: invokevirtual #380                // Method xaero/lib/client/config/ClientConfigManager.getCurrentProfile:()Lxaero/lib/common/config/profile/ConfigProfile;
      2425: getstatic     #744                // Field xaero/hud/minimap/common/config/option/MinimapProfiledConfigOptions.OPEN_SLIME_CHUNKS_SCREEN:Lxaero/lib/common/config/option/BooleanConfigOption;
      2428: aload_2
      2429: ldc_w         #368                // String true
      2432: invokevirtual #370                // Method java/lang/String.equals:(Ljava/lang/Object;)Z
      2435: invokestatic  #374                // Method java/lang/Boolean.valueOf:(Z)Ljava/lang/Boolean;
      2438: invokevirtual #387                // Method xaero/lib/common/config/profile/ConfigProfile.set:(Lxaero/lib/common/config/option/ConfigOption;Ljava/lang/Object;)Ljava/lang/Object;
      2441: pop
      2442: goto          4987
      2445: aload_1
      2446: iconst_0
      2447: aaload
      2448: ldc_w         #747                // String alwaysShowDistance
      2451: invokevirtual #330                // Method java/lang/String.equalsIgnoreCase:(Ljava/lang/String;)Z
      2454: ifeq          2481
      2457: aload_3
      2458: invokevirtual #380                // Method xaero/lib/client/config/ClientConfigManager.getCurrentProfile:()Lxaero/lib/common/config/profile/ConfigProfile;
      2461: getstatic     #749                // Field xaero/hud/minimap/common/config/option/MinimapProfiledConfigOptions.WAYPOINT_SHORT_DISTANCE_IN_WORLD:Lxaero/lib/common/config/option/BooleanConfigOption;
      2464: aload_2
      2465: ldc_w         #368                // String true
      2468: invokevirtual #370                // Method java/lang/String.equals:(Ljava/lang/Object;)Z
      2471: invokestatic  #374                // Method java/lang/Boolean.valueOf:(Z)Ljava/lang/Boolean;
      2474: invokevirtual #387                // Method xaero/lib/common/config/profile/ConfigProfile.set:(Lxaero/lib/common/config/option/ConfigOption;Ljava/lang/Object;)Ljava/lang/Object;
      2477: pop
      2478: goto          4987
      2481: aload_1
      2482: iconst_0
      2483: aaload
      2484: ldc_w         #752                // String showLightLevel
      2487: invokevirtual #330                // Method java/lang/String.equalsIgnoreCase:(Ljava/lang/String;)Z
      2490: ifeq          2535
      2493: aload_0
      2494: aload_2
      2495: ldc_w         #368                // String true
      2498: invokevirtual #370                // Method java/lang/String.equals:(Ljava/lang/Object;)Z
      2501: ifeq          2508
      2504: iconst_1
      2505: goto          2526
      2508: aload_2
      2509: ldc_w         #453                // String false
      2512: invokevirtual #370                // Method java/lang/String.equals:(Ljava/lang/Object;)Z
      2515: ifeq          2522
      2518: iconst_0
      2519: goto          2526
      2522: aload_2
      2523: invokestatic  #348                // Method java/lang/Integer.parseInt:(Ljava/lang/String;)I
      2526: invokestatic  #354                // Method java/lang/Integer.valueOf:(I)Ljava/lang/Integer;
      2529: putfield      #754                // Field showLightLevelLegacy:Ljava/lang/Integer;
      2532: goto          4987
      2535: aload_1
      2536: iconst_0
      2537: aaload
      2538: ldc_w         #758                // String renderLayerIndex
      2541: invokevirtual #330                // Method java/lang/String.equalsIgnoreCase:(Ljava/lang/String;)Z
      2544: ifeq          2568
      2547: aload_3
      2548: invokevirtual #380                // Method xaero/lib/client/config/ClientConfigManager.getCurrentProfile:()Lxaero/lib/common/config/profile/ConfigProfile;
      2551: getstatic     #760                // Field xaero/hud/minimap/common/config/option/MinimapProfiledConfigOptions.RENDER_LAYER:Lxaero/lib/common/config/option/RangeConfigOption;
      2554: aload_2
      2555: invokestatic  #348                // Method java/lang/Integer.parseInt:(Ljava/lang/String;)I
      2558: invokestatic  #354                // Method java/lang/Integer.valueOf:(I)Ljava/lang/Integer;
      2561: invokevirtual #387                // Method xaero/lib/common/config/profile/ConfigProfile.set:(Lxaero/lib/common/config/option/ConfigOption;Ljava/lang/Object;)Ljava/lang/Object;
      2564: pop
      2565: goto          4987
      2568: aload_1
      2569: iconst_0
      2570: aaload
      2571: ldc_w         #763                // String crossDimensionalTp
      2574: invokevirtual #330                // Method java/lang/String.equalsIgnoreCase:(Ljava/lang/String;)Z
      2577: ifeq          2604
      2580: aload_3
      2581: invokevirtual #380                // Method xaero/lib/client/config/ClientConfigManager.getCurrentProfile:()Lxaero/lib/common/config/profile/ConfigProfile;
      2584: getstatic     #765                // Field xaero/hud/minimap/common/config/option/MinimapProfiledConfigOptions.WAYPOINT_TELEPORT_CROSS_DIMENSION:Lxaero/lib/common/config/option/BooleanConfigOption;
      2587: aload_2
      2588: ldc_w         #368                // String true
      2591: invokevirtual #370                // Method java/lang/String.equals:(Ljava/lang/Object;)Z
      2594: invokestatic  #374                // Method java/lang/Boolean.valueOf:(Z)Ljava/lang/Boolean;
      2597: invokevirtual #387                // Method xaero/lib/common/config/profile/ConfigProfile.set:(Lxaero/lib/common/config/option/ConfigOption;Ljava/lang/Object;)Ljava/lang/Object;
      2600: pop
      2601: goto          4987
      2604: aload_1
      2605: iconst_0
      2606: aaload
      2607: ldc_w         #768                // String showTime
      2610: invokevirtual #330                // Method java/lang/String.equalsIgnoreCase:(Ljava/lang/String;)Z
      2613: ifeq          2630
      2616: aload_0
      2617: aload_2
      2618: invokestatic  #348                // Method java/lang/Integer.parseInt:(Ljava/lang/String;)I
      2621: invokestatic  #354                // Method java/lang/Integer.valueOf:(I)Ljava/lang/Integer;
      2624: putfield      #770                // Field showTimeLegacy:Ljava/lang/Integer;
      2627: goto          4987
      2630: aload_1
      2631: iconst_0
      2632: aaload
      2633: ldc_w         #773                // String biomeColorsVanillaMode
      2636: invokevirtual #330                // Method java/lang/String.equalsIgnoreCase:(Ljava/lang/String;)Z
      2639: ifeq          2666
      2642: aload_3
      2643: invokevirtual #380                // Method xaero/lib/client/config/ClientConfigManager.getCurrentProfile:()Lxaero/lib/common/config/profile/ConfigProfile;
      2646: getstatic     #775                // Field xaero/hud/minimap/common/config/option/MinimapProfiledConfigOptions.BIOMES_IN_VANILLA_COLORS:Lxaero/lib/common/config/option/BooleanConfigOption;
      2649: aload_2
      2650: ldc_w         #368                // String true
      2653: invokevirtual #370                // Method java/lang/String.equals:(Ljava/lang/Object;)Z
      2656: invokestatic  #374                // Method java/lang/Boolean.valueOf:(Z)Ljava/lang/Boolean;
      2659: invokevirtual #387                // Method xaero/lib/common/config/profile/ConfigProfile.set:(Lxaero/lib/common/config/option/ConfigOption;Ljava/lang/Object;)Ljava/lang/Object;
      2662: pop
      2663: goto          4987
      2666: aload_1
      2667: iconst_0
      2668: aaload
      2669: ldc_w         #778                // String lookingAtAngle
      2672: invokevirtual #330                // Method java/lang/String.equalsIgnoreCase:(Ljava/lang/String;)Z
      2675: ifeq          2699
      2678: aload_3
      2679: invokevirtual #380                // Method xaero/lib/client/config/ClientConfigManager.getCurrentProfile:()Lxaero/lib/common/config/profile/ConfigProfile;
      2682: getstatic     #780                // Field xaero/hud/minimap/common/config/option/MinimapProfiledConfigOptions.WAYPOINT_HORIZONTAL_POINTING_ANGLE:Lxaero/lib/common/config/option/RangeConfigOption;
      2685: aload_2
      2686: invokestatic  #348                // Method java/lang/Integer.parseInt:(Ljava/lang/String;)I
      2689: invokestatic  #354                // Method java/lang/Integer.valueOf:(I)Ljava/lang/Integer;
      2692: invokevirtual #387                // Method xaero/lib/common/config/profile/ConfigProfile.set:(Lxaero/lib/common/config/option/ConfigOption;Ljava/lang/Object;)Ljava/lang/Object;
      2695: pop
      2696: goto          4987
      2699: aload_1
      2700: iconst_0
      2701: aaload
      2702: ldc_w         #783                // String lookingAtAngleVertical
      2705: invokevirtual #330                // Method java/lang/String.equalsIgnoreCase:(Ljava/lang/String;)Z
      2708: ifeq          2732
      2711: aload_3
      2712: invokevirtual #380                // Method xaero/lib/client/config/ClientConfigManager.getCurrentProfile:()Lxaero/lib/common/config/profile/ConfigProfile;
      2715: getstatic     #785                // Field xaero/hud/minimap/common/config/option/MinimapProfiledConfigOptions.WAYPOINT_VERTICAL_POINTING_ANGLE:Lxaero/lib/common/config/option/RangeConfigOption;
      2718: aload_2
      2719: invokestatic  #348                // Method java/lang/Integer.parseInt:(Ljava/lang/String;)I
      2722: invokestatic  #354                // Method java/lang/Integer.valueOf:(I)Ljava/lang/Integer;
      2725: invokevirtual #387                // Method xaero/lib/common/config/profile/ConfigProfile.set:(Lxaero/lib/common/config/option/ConfigOption;Ljava/lang/Object;)Ljava/lang/Object;
      2728: pop
      2729: goto          4987
      2732: aload_1
      2733: iconst_0
      2734: aaload
      2735: ldc_w         #788                // String centeredEnlarged
      2738: invokevirtual #330                // Method java/lang/String.equalsIgnoreCase:(Ljava/lang/String;)Z
      2741: ifeq          2768
      2744: aload_3
      2745: invokevirtual #380                // Method xaero/lib/client/config/ClientConfigManager.getCurrentProfile:()Lxaero/lib/common/config/profile/ConfigProfile;
      2748: getstatic     #790                // Field xaero/hud/minimap/common/config/option/MinimapProfiledConfigOptions.CENTERED_ENLARGED:Lxaero/lib/common/config/option/BooleanConfigOption;
      2751: aload_2
      2752: ldc_w         #368                // String true
      2755: invokevirtual #370                // Method java/lang/String.equals:(Ljava/lang/Object;)Z
      2758: invokestatic  #374                // Method java/lang/Boolean.valueOf:(Z)Ljava/lang/Boolean;
      2761: invokevirtual #387                // Method xaero/lib/common/config/profile/ConfigProfile.set:(Lxaero/lib/common/config/option/ConfigOption;Ljava/lang/Object;)Ljava/lang/Object;
      2764: pop
      2765: goto          4987
      2768: aload_1
      2769: iconst_0
      2770: aaload
      2771: ldc_w         #793                // String zoomedOutEnlarged
      2774: invokevirtual #330                // Method java/lang/String.equalsIgnoreCase:(Ljava/lang/String;)Z
      2777: ifeq          2812
      2780: aload_3
      2781: invokevirtual #380                // Method xaero/lib/client/config/ClientConfigManager.getCurrentProfile:()Lxaero/lib/common/config/profile/ConfigProfile;
      2784: getstatic     #795                // Field xaero/hud/minimap/common/config/option/MinimapProfiledConfigOptions.ZOOM_ENLARGED:Lxaero/lib/common/config/option/RangeConfigOption;
      2787: aload_2
      2788: ldc_w         #368                // String true
      2791: invokevirtual #370                // Method java/lang/String.equals:(Ljava/lang/Object;)Z
      2794: ifeq          2801
      2797: iconst_1
      2798: goto          2802
      2801: iconst_0
      2802: invokestatic  #354                // Method java/lang/Integer.valueOf:(I)Ljava/lang/Integer;
      2805: invokevirtual #387                // Method xaero/lib/common/config/profile/ConfigProfile.set:(Lxaero/lib/common/config/option/ConfigOption;Ljava/lang/Object;)Ljava/lang/Object;
      2808: pop
      2809: goto          4987
      2812: aload_1
      2813: iconst_0
      2814: aaload
      2815: ldc_w         #798                // String zoomOnEnlarged
      2818: invokevirtual #330                // Method java/lang/String.equalsIgnoreCase:(Ljava/lang/String;)Z
      2821: ifeq          2845
      2824: aload_3
      2825: invokevirtual #380                // Method xaero/lib/client/config/ClientConfigManager.getCurrentProfile:()Lxaero/lib/common/config/profile/ConfigProfile;
      2828: getstatic     #795                // Field xaero/hud/minimap/common/config/option/MinimapProfiledConfigOptions.ZOOM_ENLARGED:Lxaero/lib/common/config/option/RangeConfigOption;
      2831: aload_2
      2832: invokestatic  #348                // Method java/lang/Integer.parseInt:(Ljava/lang/String;)I
      2835: invokestatic  #354                // Method java/lang/Integer.valueOf:(I)Ljava/lang/Integer;
      2838: invokevirtual #387                // Method xaero/lib/common/config/profile/ConfigProfile.set:(Lxaero/lib/common/config/option/ConfigOption;Ljava/lang/Object;)Ljava/lang/Object;
      2841: pop
      2842: goto          4987
      2845: aload_1
      2846: iconst_0
      2847: aaload
      2848: ldc_w         #800                // String minimapTextAlign
      2851: invokevirtual #330                // Method java/lang/String.equalsIgnoreCase:(Ljava/lang/String;)Z
      2854: ifeq          2878
      2857: aload_3
      2858: invokevirtual #380                // Method xaero/lib/client/config/ClientConfigManager.getCurrentProfile:()Lxaero/lib/common/config/profile/ConfigProfile;
      2861: getstatic     #802                // Field xaero/hud/minimap/common/config/option/MinimapProfiledConfigOptions.INFO_DISPLAY_ALIGNMENT:Lxaero/lib/common/config/option/RangeConfigOption;
      2864: aload_2
      2865: invokestatic  #348                // Method java/lang/Integer.parseInt:(Ljava/lang/String;)I
      2868: invokestatic  #354                // Method java/lang/Integer.valueOf:(I)Ljava/lang/Integer;
      2871: invokevirtual #387                // Method xaero/lib/common/config/profile/ConfigProfile.set:(Lxaero/lib/common/config/option/ConfigOption;Ljava/lang/Object;)Ljava/lang/Object;
      2874: pop
      2875: goto          4987
      2878: aload_1
      2879: iconst_0
      2880: aaload
      2881: ldc_w         #805                // String showAngles
      2884: invokevirtual #330                // Method java/lang/String.equalsIgnoreCase:(Ljava/lang/String;)Z
      2887: ifeq          2907
      2890: aload_0
      2891: aload_2
      2892: ldc_w         #368                // String true
      2895: invokevirtual #370                // Method java/lang/String.equals:(Ljava/lang/Object;)Z
      2898: invokestatic  #374                // Method java/lang/Boolean.valueOf:(Z)Ljava/lang/Boolean;
      2901: putfield      #807                // Field showAnglesLegacy:Ljava/lang/Boolean;
      2904: goto          4987
      2907: aload_1
      2908: iconst_0
      2909: aaload
      2910: ldc_w         #810                // String waypointsMutualEdit
      2913: invokevirtual #330                // Method java/lang/String.equalsIgnoreCase:(Ljava/lang/String;)Z
      2916: ifeq          2946
      2919: aload_3
      2920: invokevirtual #333                // Method xaero/lib/client/config/ClientConfigManager.getPrimaryConfigManager:()Lxaero/lib/common/config/single/SingleConfigManager;
      2923: invokevirtual #337                // Method xaero/lib/common/config/single/SingleConfigManager.getConfig:()Lxaero/lib/common/config/Config;
      2926: getstatic     #812                // Field xaero/hud/minimap/config/primary/option/MinimapPrimaryClientConfigOptions.WAYPOINT_MUTUAL_EDIT:Lxaero/lib/common/config/option/BooleanConfigOption;
      2929: aload_2
      2930: ldc_w         #368                // String true
      2933: invokevirtual #370                // Method java/lang/String.equals:(Ljava/lang/Object;)Z
      2936: invokestatic  #374                // Method java/lang/Boolean.valueOf:(Z)Ljava/lang/Boolean;
      2939: invokevirtual #357                // Method xaero/lib/common/config/Config.set:(Lxaero/lib/common/config/option/ConfigOption;Ljava/lang/Object;)Ljava/lang/Object;
      2942: pop
      2943: goto          4987
      2946: aload_1
      2947: iconst_0
      2948: aaload
      2949: ldc_w         #815                // String compass
      2952: invokevirtual #330                // Method java/lang/String.equalsIgnoreCase:(Ljava/lang/String;)Z
      2955: ifeq          2990
      2958: aload_3
      2959: invokevirtual #380                // Method xaero/lib/client/config/ClientConfigManager.getCurrentProfile:()Lxaero/lib/common/config/profile/ConfigProfile;
      2962: getstatic     #817                // Field xaero/hud/minimap/common/config/option/MinimapProfiledConfigOptions.COMPASS_LOCATION:Lxaero/lib/common/config/option/RangeConfigOption;
      2965: aload_2
      2966: ldc_w         #368                // String true
      2969: invokevirtual #370                // Method java/lang/String.equals:(Ljava/lang/Object;)Z
      2972: ifeq          2979
      2975: iconst_1
      2976: goto          2980
      2979: iconst_0
      2980: invokestatic  #354                // Method java/lang/Integer.valueOf:(I)Ljava/lang/Integer;
      2983: invokevirtual #387                // Method xaero/lib/common/config/profile/ConfigProfile.set:(Lxaero/lib/common/config/option/ConfigOption;Ljava/lang/Object;)Ljava/lang/Object;
      2986: pop
      2987: goto          4987
      2990: aload_1
      2991: iconst_0
      2992: aaload
      2993: ldc_w         #820                // String compassLocation
      2996: invokevirtual #330                // Method java/lang/String.equalsIgnoreCase:(Ljava/lang/String;)Z
      2999: ifeq          3023
      3002: aload_3
      3003: invokevirtual #380                // Method xaero/lib/client/config/ClientConfigManager.getCurrentProfile:()Lxaero/lib/common/config/profile/ConfigProfile;
      3006: getstatic     #817                // Field xaero/hud/minimap/common/config/option/MinimapProfiledConfigOptions.COMPASS_LOCATION:Lxaero/lib/common/config/option/RangeConfigOption;
      3009: aload_2
      3010: invokestatic  #348                // Method java/lang/Integer.parseInt:(Ljava/lang/String;)I
      3013: invokestatic  #354                // Method java/lang/Integer.valueOf:(I)Ljava/lang/Integer;
      3016: invokevirtual #387                // Method xaero/lib/common/config/profile/ConfigProfile.set:(Lxaero/lib/common/config/option/ConfigOption;Ljava/lang/Object;)Ljava/lang/Object;
      3019: pop
      3020: goto          4987
      3023: aload_1
      3024: iconst_0
      3025: aaload
      3026: ldc_w         #822                // String compassDirectionScale
      3029: invokevirtual #330                // Method java/lang/String.equalsIgnoreCase:(Ljava/lang/String;)Z
      3032: ifeq          3056
      3035: aload_3
      3036: invokevirtual #380                // Method xaero/lib/client/config/ClientConfigManager.getCurrentProfile:()Lxaero/lib/common/config/profile/ConfigProfile;
      3039: getstatic     #824                // Field xaero/hud/minimap/common/config/option/MinimapProfiledConfigOptions.COMPASS_SCALE:Lxaero/lib/common/config/option/RangeConfigOption;
      3042: aload_2
      3043: invokestatic  #348                // Method java/lang/Integer.parseInt:(Ljava/lang/String;)I
      3046: invokestatic  #354                // Method java/lang/Integer.valueOf:(I)Ljava/lang/Integer;
      3049: invokevirtual #387                // Method xaero/lib/common/config/profile/ConfigProfile.set:(Lxaero/lib/common/config/option/ConfigOption;Ljava/lang/Object;)Ljava/lang/Object;
      3052: pop
      3053: goto          4987
      3056: aload_1
      3057: iconst_0
      3058: aaload
      3059: ldc_w         #827                // String caveMapsDepth
      3062: invokevirtual #330                // Method java/lang/String.equalsIgnoreCase:(Ljava/lang/String;)Z
      3065: ifeq          3089
      3068: aload_3
      3069: invokevirtual #380                // Method xaero/lib/client/config/ClientConfigManager.getCurrentProfile:()Lxaero/lib/common/config/profile/ConfigProfile;
      3072: getstatic     #829                // Field xaero/hud/minimap/common/config/option/MinimapProfiledConfigOptions.CAVE_MODE_DEPTH:Lxaero/lib/common/config/option/RangeConfigOption;
      3075: aload_2
      3076: invokestatic  #348                // Method java/lang/Integer.parseInt:(Ljava/lang/String;)I
      3079: invokestatic  #354                // Method java/lang/Integer.valueOf:(I)Ljava/lang/Integer;
      3082: invokevirtual #387                // Method xaero/lib/common/config/profile/ConfigProfile.set:(Lxaero/lib/common/config/option/ConfigOption;Ljava/lang/Object;)Ljava/lang/Object;
      3085: pop
      3086: goto          4987
      3089: aload_1
      3090: iconst_0
      3091: aaload
      3092: ldc_w         #832                // String hideWaypointCoordinates
      3095: invokevirtual #330                // Method java/lang/String.equalsIgnoreCase:(Ljava/lang/String;)Z
      3098: ifeq          3125
      3101: aload_3
      3102: invokevirtual #380                // Method xaero/lib/client/config/ClientConfigManager.getCurrentProfile:()Lxaero/lib/common/config/profile/ConfigProfile;
      3105: getstatic     #834                // Field xaero/hud/minimap/common/config/option/MinimapProfiledConfigOptions.HIDE_WAYPOINT_COORDINATES:Lxaero/lib/common/config/option/BooleanConfigOption;
      3108: aload_2
      3109: ldc_w         #368                // String true
      3112: invokevirtual #370                // Method java/lang/String.equals:(Ljava/lang/Object;)Z
      3115: invokestatic  #374                // Method java/lang/Boolean.valueOf:(Z)Ljava/lang/Boolean;
      3118: invokevirtual #387                // Method xaero/lib/common/config/profile/ConfigProfile.set:(Lxaero/lib/common/config/option/ConfigOption;Ljava/lang/Object;)Ljava/lang/Object;
      3121: pop
      3122: goto          4987
      3125: aload_1
      3126: iconst_0
      3127: aaload
      3128: ldc_w         #837                // String renderAllSets
      3131: invokevirtual #330                // Method java/lang/String.equalsIgnoreCase:(Ljava/lang/String;)Z
      3134: ifeq          3161
      3137: aload_3
      3138: invokevirtual #380                // Method xaero/lib/client/config/ClientConfigManager.getCurrentProfile:()Lxaero/lib/common/config/profile/ConfigProfile;
      3141: getstatic     #839                // Field xaero/hud/minimap/common/config/option/MinimapProfiledConfigOptions.WAYPOINTS_ALL_SETS:Lxaero/lib/common/config/option/BooleanConfigOption;
      3144: aload_2
      3145: ldc_w         #368                // String true
      3148: invokevirtual #370                // Method java/lang/String.equals:(Ljava/lang/Object;)Z
      3151: invokestatic  #374                // Method java/lang/Boolean.valueOf:(Z)Ljava/lang/Boolean;
      3154: invokevirtual #387                // Method xaero/lib/common/config/profile/ConfigProfile.set:(Lxaero/lib/common/config/option/ConfigOption;Ljava/lang/Object;)Ljava/lang/Object;
      3157: pop
      3158: goto          4987
      3161: aload_1
      3162: iconst_0
      3163: aaload
      3164: ldc_w         #842                // String playerArrowOpacity
      3167: invokevirtual #330                // Method java/lang/String.equalsIgnoreCase:(Ljava/lang/String;)Z
      3170: ifeq          3194
      3173: aload_3
      3174: invokevirtual #380                // Method xaero/lib/client/config/ClientConfigManager.getCurrentProfile:()Lxaero/lib/common/config/profile/ConfigProfile;
      3177: getstatic     #844                // Field xaero/hud/minimap/common/config/option/MinimapProfiledConfigOptions.ARROW_OPACITY:Lxaero/lib/common/config/option/RangeConfigOption;
      3180: aload_2
      3181: invokestatic  #348                // Method java/lang/Integer.parseInt:(Ljava/lang/String;)I
      3184: invokestatic  #354                // Method java/lang/Integer.valueOf:(I)Ljava/lang/Integer;
      3187: invokevirtual #387                // Method xaero/lib/common/config/profile/ConfigProfile.set:(Lxaero/lib/common/config/option/ConfigOption;Ljava/lang/Object;)Ljava/lang/Object;
      3190: pop
      3191: goto          4987
      3194: aload_1
      3195: iconst_0
      3196: aaload
      3197: ldc_w         #847                // String waypointsBottom
      3200: invokevirtual #330                // Method java/lang/String.equalsIgnoreCase:(Ljava/lang/String;)Z
      3203: ifeq          3230
      3206: aload_3
      3207: invokevirtual #380                // Method xaero/lib/client/config/ClientConfigManager.getCurrentProfile:()Lxaero/lib/common/config/profile/ConfigProfile;
      3210: getstatic     #849                // Field xaero/hud/minimap/common/config/option/MinimapProfiledConfigOptions.NEW_WAYPOINTS_TO_BOTTOM:Lxaero/lib/common/config/option/BooleanConfigOption;
      3213: aload_2
      3214: ldc_w         #368                // String true
      3217: invokevirtual #370                // Method java/lang/String.equals:(Ljava/lang/Object;)Z
      3220: invokestatic  #374                // Method java/lang/Boolean.valueOf:(Z)Ljava/lang/Boolean;
      3223: invokevirtual #387                // Method xaero/lib/common/config/profile/ConfigProfile.set:(Lxaero/lib/common/config/option/ConfigOption;Ljava/lang/Object;)Ljava/lang/Object;
      3226: pop
      3227: goto          4987
      3230: aload_1
      3231: iconst_0
      3232: aaload
      3233: ldc_w         #852                // String minimapShape
      3236: invokevirtual #330                // Method java/lang/String.equalsIgnoreCase:(Ljava/lang/String;)Z
      3239: ifeq          3263
      3242: aload_3
      3243: invokevirtual #380                // Method xaero/lib/client/config/ClientConfigManager.getCurrentProfile:()Lxaero/lib/common/config/profile/ConfigProfile;
      3246: getstatic     #854                // Field xaero/hud/minimap/common/config/option/MinimapProfiledConfigOptions.SHAPE:Lxaero/lib/common/config/option/RangeConfigOption;
      3249: aload_2
      3250: invokestatic  #348                // Method java/lang/Integer.parseInt:(Ljava/lang/String;)I
      3253: invokestatic  #354                // Method java/lang/Integer.valueOf:(I)Ljava/lang/Integer;
      3256: invokevirtual #387                // Method xaero/lib/common/config/profile/ConfigProfile.set:(Lxaero/lib/common/config/option/ConfigOption;Ljava/lang/Object;)Ljava/lang/Object;
      3259: pop
      3260: goto          4987
      3263: aload_1
      3264: iconst_0
      3265: aaload
      3266: ldc_w         #857                // String lightOverlayType
      3269: invokevirtual #330                // Method java/lang/String.equalsIgnoreCase:(Ljava/lang/String;)Z
      3272: ifeq          3296
      3275: aload_3
      3276: invokevirtual #380                // Method xaero/lib/client/config/ClientConfigManager.getCurrentProfile:()Lxaero/lib/common/config/profile/ConfigProfile;
      3279: getstatic     #859                // Field xaero/hud/minimap/common/config/option/MinimapProfiledConfigOptions.LIGHT_OVERLAY_TYPE:Lxaero/lib/common/config/option/RangeConfigOption;
      3282: aload_2
      3283: invokestatic  #348                // Method java/lang/Integer.parseInt:(Ljava/lang/String;)I
      3286: invokestatic  #354                // Method java/lang/Integer.valueOf:(I)Ljava/lang/Integer;
      3289: invokevirtual #387                // Method xaero/lib/common/config/profile/ConfigProfile.set:(Lxaero/lib/common/config/option/ConfigOption;Ljava/lang/Object;)Ljava/lang/Object;
      3292: pop
      3293: goto          4987
      3296: aload_1
      3297: iconst_0
      3298: aaload
      3299: ldc_w         #862                // String lightOverlayMaxLight
      3302: invokevirtual #330                // Method java/lang/String.equalsIgnoreCase:(Ljava/lang/String;)Z
      3305: ifeq          3329
      3308: aload_3
      3309: invokevirtual #380                // Method xaero/lib/client/config/ClientConfigManager.getCurrentProfile:()Lxaero/lib/common/config/profile/ConfigProfile;
      3312: getstatic     #864                // Field xaero/hud/minimap/common/config/option/MinimapProfiledConfigOptions.LIGHT_OVERLAY_MAX_LIGHT:Lxaero/lib/common/config/option/RangeConfigOption;
      3315: aload_2
      3316: invokestatic  #348                // Method java/lang/Integer.parseInt:(Ljava/lang/String;)I
      3319: invokestatic  #354                // Method java/lang/Integer.valueOf:(I)Ljava/lang/Integer;
      3322: invokevirtual #387                // Method xaero/lib/common/config/profile/ConfigProfile.set:(Lxaero/lib/common/config/option/ConfigOption;Ljava/lang/Object;)Ljava/lang/Object;
      3325: pop
      3326: goto          4987
      3329: aload_1
      3330: iconst_0
      3331: aaload
      3332: ldc_w         #867                // String lightOverlayMinLight
      3335: invokevirtual #330                // Method java/lang/String.equalsIgnoreCase:(Ljava/lang/String;)Z
      3338: ifeq          3362
      3341: aload_3
      3342: invokevirtual #380                // Method xaero/lib/client/config/ClientConfigManager.getCurrentProfile:()Lxaero/lib/common/config/profile/ConfigProfile;
      3345: getstatic     #869                // Field xaero/hud/minimap/common/config/option/MinimapProfiledConfigOptions.LIGHT_OVERLAY_MIN_LIGHT:Lxaero/lib/common/config/option/RangeConfigOption;
      3348: aload_2
      3349: invokestatic  #348                // Method java/lang/Integer.parseInt:(Ljava/lang/String;)I
      3352: invokestatic  #354                // Method java/lang/Integer.valueOf:(I)Ljava/lang/Integer;
      3355: invokevirtual #387                // Method xaero/lib/common/config/profile/ConfigProfile.set:(Lxaero/lib/common/config/option/ConfigOption;Ljava/lang/Object;)Ljava/lang/Object;
      3358: pop
      3359: goto          4987
      3362: aload_1
      3363: iconst_0
      3364: aaload
      3365: ldc_w         #872                // String lightOverlayColor
      3368: invokevirtual #330                // Method java/lang/String.equalsIgnoreCase:(Ljava/lang/String;)Z
      3371: ifeq          3395
      3374: aload_3
      3375: invokevirtual #380                // Method xaero/lib/client/config/ClientConfigManager.getCurrentProfile:()Lxaero/lib/common/config/profile/ConfigProfile;
      3378: getstatic     #874                // Field xaero/hud/minimap/common/config/option/MinimapProfiledConfigOptions.LIGHT_OVERLAY_COLOR:Lxaero/lib/common/config/option/RangeConfigOption;
      3381: aload_2
      3382: invokestatic  #348                // Method java/lang/Integer.parseInt:(Ljava/lang/String;)I
      3385: invokestatic  #354                // Method java/lang/Integer.valueOf:(I)Ljava/lang/Integer;
      3388: invokevirtual #387                // Method xaero/lib/common/config/profile/ConfigProfile.set:(Lxaero/lib/common/config/option/ConfigOption;Ljava/lang/Object;)Ljava/lang/Object;
      3391: pop
      3392: goto          4987
      3395: aload_1
      3396: iconst_0
      3397: aaload
      3398: ldc_w         #877                // String uiScale
      3401: invokevirtual #330                // Method java/lang/String.equalsIgnoreCase:(Ljava/lang/String;)Z
      3404: ifeq          3428
      3407: aload_3
      3408: invokevirtual #380                // Method xaero/lib/client/config/ClientConfigManager.getCurrentProfile:()Lxaero/lib/common/config/profile/ConfigProfile;
      3411: getstatic     #879                // Field xaero/hud/minimap/common/config/option/MinimapProfiledConfigOptions.UI_SCALE:Lxaero/lib/common/config/option/RangeConfigOption;
      3414: aload_2
      3415: invokestatic  #348                // Method java/lang/Integer.parseInt:(Ljava/lang/String;)I
      3418: invokestatic  #354                // Method java/lang/Integer.valueOf:(I)Ljava/lang/Integer;
      3421: invokevirtual #387                // Method xaero/lib/common/config/profile/ConfigProfile.set:(Lxaero/lib/common/config/option/ConfigOption;Ljava/lang/Object;)Ljava/lang/Object;
      3424: pop
      3425: goto          4987
      3428: aload_1
      3429: iconst_0
      3430: aaload
      3431: ldc_w         #882                // String bossHealthPushBox
      3434: invokevirtual #330                // Method java/lang/String.equalsIgnoreCase:(Ljava/lang/String;)Z
      3437: ifeq          3461
      3440: aload_3
      3441: invokevirtual #380                // Method xaero/lib/client/config/ClientConfigManager.getCurrentProfile:()Lxaero/lib/common/config/profile/ConfigProfile;
      3444: getstatic     #884                // Field xaero/hud/minimap/common/config/option/MinimapProfiledConfigOptions.BOSS_HEALTH_PUSH_BOX:Lxaero/lib/common/config/option/RangeConfigOption;
      3447: aload_2
      3448: invokestatic  #348                // Method java/lang/Integer.parseInt:(Ljava/lang/String;)I
      3451: invokestatic  #354                // Method java/lang/Integer.valueOf:(I)Ljava/lang/Integer;
      3454: invokevirtual #387                // Method xaero/lib/common/config/profile/ConfigProfile.set:(Lxaero/lib/common/config/option/ConfigOption;Ljava/lang/Object;)Ljava/lang/Object;
      3457: pop
      3458: goto          4987
      3461: aload_1
      3462: iconst_0
      3463: aaload
      3464: ldc_w         #887                // String potionEffectPushBox
      3467: invokevirtual #330                // Method java/lang/String.equalsIgnoreCase:(Ljava/lang/String;)Z
      3470: ifeq          3494
      3473: aload_3
      3474: invokevirtual #380                // Method xaero/lib/client/config/ClientConfigManager.getCurrentProfile:()Lxaero/lib/common/config/profile/ConfigProfile;
      3477: getstatic     #889                // Field xaero/hud/minimap/common/config/option/MinimapProfiledConfigOptions.POTION_EFFECT_PUSH_BOX:Lxaero/lib/common/config/option/RangeConfigOption;
      3480: aload_2
      3481: invokestatic  #348                // Method java/lang/Integer.parseInt:(Ljava/lang/String;)I
      3484: invokestatic  #354                // Method java/lang/Integer.valueOf:(I)Ljava/lang/Integer;
      3487: invokevirtual #387                // Method xaero/lib/common/config/profile/ConfigProfile.set:(Lxaero/lib/common/config/option/ConfigOption;Ljava/lang/Object;)Ljava/lang/Object;
      3490: pop
      3491: goto          4987
      3494: aload_1
      3495: iconst_0
      3496: aaload
      3497: ldc_w         #892                // String minimapFrame
      3500: invokevirtual #330                // Method java/lang/String.equalsIgnoreCase:(Ljava/lang/String;)Z
      3503: ifeq          3527
      3506: aload_3
      3507: invokevirtual #380                // Method xaero/lib/client/config/ClientConfigManager.getCurrentProfile:()Lxaero/lib/common/config/profile/ConfigProfile;
      3510: getstatic     #894                // Field xaero/hud/minimap/common/config/option/MinimapProfiledConfigOptions.FRAME:Lxaero/lib/common/config/option/RangeConfigOption;
      3513: aload_2
      3514: invokestatic  #348                // Method java/lang/Integer.parseInt:(Ljava/lang/String;)I
      3517: invokestatic  #354                // Method java/lang/Integer.valueOf:(I)Ljava/lang/Integer;
      3520: invokevirtual #387                // Method xaero/lib/common/config/profile/ConfigProfile.set:(Lxaero/lib/common/config/option/ConfigOption;Ljava/lang/Object;)Ljava/lang/Object;
      3523: pop
      3524: goto          4987
      3527: aload_1
      3528: iconst_0
      3529: aaload
      3530: ldc_w         #897                // String minimapFrameColor
      3533: invokevirtual #330                // Method java/lang/String.equalsIgnoreCase:(Ljava/lang/String;)Z
      3536: ifeq          3560
      3539: aload_3
      3540: invokevirtual #380                // Method xaero/lib/client/config/ClientConfigManager.getCurrentProfile:()Lxaero/lib/common/config/profile/ConfigProfile;
      3543: getstatic     #899                // Field xaero/hud/minimap/common/config/option/MinimapProfiledConfigOptions.FRAME_COLOR:Lxaero/lib/common/config/option/RangeConfigOption;
      3546: aload_2
      3547: invokestatic  #348                // Method java/lang/Integer.parseInt:(Ljava/lang/String;)I
      3550: invokestatic  #354                // Method java/lang/Integer.valueOf:(I)Ljava/lang/Integer;
      3553: invokevirtual #387                // Method xaero/lib/common/config/profile/ConfigProfile.set:(Lxaero/lib/common/config/option/ConfigOption;Ljava/lang/Object;)Ljava/lang/Object;
      3556: pop
      3557: goto          4987
      3560: aload_1
      3561: iconst_0
      3562: aaload
      3563: ldc_w         #902                // String compassColor
      3566: invokevirtual #330                // Method java/lang/String.equalsIgnoreCase:(Ljava/lang/String;)Z
      3569: ifeq          3593
      3572: aload_3
      3573: invokevirtual #380                // Method xaero/lib/client/config/ClientConfigManager.getCurrentProfile:()Lxaero/lib/common/config/profile/ConfigProfile;
      3576: getstatic     #904                // Field xaero/hud/minimap/common/config/option/MinimapProfiledConfigOptions.COMPASS_SHADOW_COLOR:Lxaero/lib/common/config/option/RangeConfigOption;
      3579: aload_2
      3580: invokestatic  #348                // Method java/lang/Integer.parseInt:(Ljava/lang/String;)I
      3583: invokestatic  #354                // Method java/lang/Integer.valueOf:(I)Ljava/lang/Integer;
      3586: invokevirtual #387                // Method xaero/lib/common/config/profile/ConfigProfile.set:(Lxaero/lib/common/config/option/ConfigOption;Ljava/lang/Object;)Ljava/lang/Object;
      3589: pop
      3590: goto          4987
      3593: aload_1
      3594: iconst_0
      3595: aaload
      3596: ldc_w         #907                // String northCompassColor
      3599: invokevirtual #330                // Method java/lang/String.equalsIgnoreCase:(Ljava/lang/String;)Z
      3602: ifeq          3626
      3605: aload_3
      3606: invokevirtual #380                // Method xaero/lib/client/config/ClientConfigManager.getCurrentProfile:()Lxaero/lib/common/config/profile/ConfigProfile;
      3609: getstatic     #909                // Field xaero/hud/minimap/common/config/option/MinimapProfiledConfigOptions.COMPASS_NORTH_SHADOW_COLOR:Lxaero/lib/common/config/option/RangeConfigOption;
      3612: aload_2
      3613: invokestatic  #348                // Method java/lang/Integer.parseInt:(Ljava/lang/String;)I
      3616: invokestatic  #354                // Method java/lang/Integer.valueOf:(I)Ljava/lang/Integer;
      3619: invokevirtual #387                // Method xaero/lib/common/config/profile/ConfigProfile.set:(Lxaero/lib/common/config/option/ConfigOption;Ljava/lang/Object;)Ljava/lang/Object;
      3622: pop
      3623: goto          4987
      3626: aload_1
      3627: iconst_0
      3628: aaload
      3629: ldc_w         #912                // String showDimensionName
      3632: invokevirtual #330                // Method java/lang/String.equalsIgnoreCase:(Ljava/lang/String;)Z
      3635: ifeq          3655
      3638: aload_0
      3639: aload_2
      3640: ldc_w         #368                // String true
      3643: invokevirtual #370                // Method java/lang/String.equals:(Ljava/lang/Object;)Z
      3646: invokestatic  #374                // Method java/lang/Boolean.valueOf:(Z)Ljava/lang/Boolean;
      3649: putfield      #914                // Field showDimensionNameLegacy:Ljava/lang/Boolean;
      3652: goto          4987
      3655: aload_1
      3656: iconst_0
      3657: aaload
      3658: ldc_w         #917                // String displayMultipleWaypointInfo
      3661: invokevirtual #330                // Method java/lang/String.equalsIgnoreCase:(Ljava/lang/String;)Z
      3664: ifeq          3688
      3667: aload_3
      3668: invokevirtual #380                // Method xaero/lib/client/config/ClientConfigManager.getCurrentProfile:()Lxaero/lib/common/config/profile/ConfigProfile;
      3671: getstatic     #919                // Field xaero/hud/minimap/common/config/option/MinimapProfiledConfigOptions.MULTIPLE_WAYPOINTS_INFO:Lxaero/lib/common/config/option/RangeConfigOption;
      3674: aload_2
      3675: invokestatic  #348                // Method java/lang/Integer.parseInt:(Ljava/lang/String;)I
      3678: invokestatic  #354                // Method java/lang/Integer.valueOf:(I)Ljava/lang/Integer;
      3681: invokevirtual #387                // Method xaero/lib/common/config/profile/ConfigProfile.set:(Lxaero/lib/common/config/option/ConfigOption;Ljava/lang/Object;)Ljava/lang/Object;
      3684: pop
      3685: goto          4987
      3688: aload_1
      3689: iconst_0
      3690: aaload
      3691: ldc_w         #922                // String entityRadar
      3694: invokevirtual #330                // Method java/lang/String.equalsIgnoreCase:(Ljava/lang/String;)Z
      3697: ifeq          3724
      3700: aload_3
      3701: invokevirtual #380                // Method xaero/lib/client/config/ClientConfigManager.getCurrentProfile:()Lxaero/lib/common/config/profile/ConfigProfile;
      3704: getstatic     #924                // Field xaero/hud/minimap/common/config/option/MinimapProfiledConfigOptions.DISPLAY_RADAR:Lxaero/lib/common/config/option/BooleanConfigOption;
      3707: aload_2
      3708: ldc_w         #368                // String true
      3711: invokevirtual #370                // Method java/lang/String.equals:(Ljava/lang/Object;)Z
      3714: invokestatic  #374                // Method java/lang/Boolean.valueOf:(Z)Ljava/lang/Boolean;
      3717: invokevirtual #387                // Method xaero/lib/common/config/profile/ConfigProfile.set:(Lxaero/lib/common/config/option/ConfigOption;Ljava/lang/Object;)Ljava/lang/Object;
      3720: pop
      3721: goto          4987
      3724: aload_0
      3725: getfield      #16                 // Field entityRadarBackwardsCompatibilityConfig:Lxaero/hud/minimap/radar/category/EntityRadarBackwardsCompatibilityConfig;
      3728: aload_1
      3729: invokevirtual #927                // Method xaero/hud/minimap/radar/category/EntityRadarBackwardsCompatibilityConfig.readSetting:([Ljava/lang/String;)Z
      3732: ifeq          3741
      3735: aload_0
      3736: iconst_1
      3737: putfield      #931                // Field foundOldRadarSettings:Z
      3740: return
      3741: aload_1
      3742: iconst_0
      3743: aaload
      3744: ldc_w         #934                // String adjustHeightForCarpetLikeBlocks
      3747: invokevirtual #330                // Method java/lang/String.equalsIgnoreCase:(Ljava/lang/String;)Z
      3750: ifeq          3777
      3753: aload_3
      3754: invokevirtual #380                // Method xaero/lib/client/config/ClientConfigManager.getCurrentProfile:()Lxaero/lib/common/config/profile/ConfigProfile;
      3757: getstatic     #936                // Field xaero/hud/minimap/common/config/option/MinimapProfiledConfigOptions.ADJUST_HEIGHT_FOR_SHORT_BLOCKS:Lxaero/lib/common/config/option/BooleanConfigOption;
      3760: aload_2
      3761: ldc_w         #368                // String true
      3764: invokevirtual #370                // Method java/lang/String.equals:(Ljava/lang/Object;)Z
      3767: invokestatic  #374                // Method java/lang/Boolean.valueOf:(Z)Ljava/lang/Boolean;
      3770: invokevirtual #387                // Method xaero/lib/common/config/profile/ConfigProfile.set:(Lxaero/lib/common/config/option/ConfigOption;Ljava/lang/Object;)Ljava/lang/Object;
      3773: pop
      3774: goto          4987
      3777: aload_1
      3778: iconst_0
      3779: aaload
      3780: ldc_w         #939                // String autoConvertWaypointDistanceToKmThreshold
      3783: invokevirtual #330                // Method java/lang/String.equalsIgnoreCase:(Ljava/lang/String;)Z
      3786: ifeq          3810
      3789: aload_3
      3790: invokevirtual #380                // Method xaero/lib/client/config/ClientConfigManager.getCurrentProfile:()Lxaero/lib/common/config/profile/ConfigProfile;
      3793: getstatic     #941                // Field xaero/hud/minimap/common/config/option/MinimapProfiledConfigOptions.WAYPOINT_CONVERT_DISTANCE_TO_KM_AT:Lxaero/lib/common/config/option/IndexedConfigOption;
      3796: aload_2
      3797: invokestatic  #348                // Method java/lang/Integer.parseInt:(Ljava/lang/String;)I
      3800: invokestatic  #354                // Method java/lang/Integer.valueOf:(I)Ljava/lang/Integer;
      3803: invokevirtual #387                // Method xaero/lib/common/config/profile/ConfigProfile.set:(Lxaero/lib/common/config/option/ConfigOption;Ljava/lang/Object;)Ljava/lang/Object;
      3806: pop
      3807: goto          4987
      3810: aload_1
      3811: iconst_0
      3812: aaload
      3813: ldc_w         #944                // String waypointDistancePrecision
      3816: invokevirtual #330                // Method java/lang/String.equalsIgnoreCase:(Ljava/lang/String;)Z
      3819: ifeq          3843
      3822: aload_3
      3823: invokevirtual #380                // Method xaero/lib/client/config/ClientConfigManager.getCurrentProfile:()Lxaero/lib/common/config/profile/ConfigProfile;
      3826: getstatic     #946                // Field xaero/hud/minimap/common/config/option/MinimapProfiledConfigOptions.WAYPOINT_DISTANCE_PRECISION:Lxaero/lib/common/config/option/RangeConfigOption;
      3829: aload_2
      3830: invokestatic  #348                // Method java/lang/Integer.parseInt:(Ljava/lang/String;)I
      3833: invokestatic  #354                // Method java/lang/Integer.valueOf:(I)Ljava/lang/Integer;
      3836: invokevirtual #387                // Method xaero/lib/common/config/profile/ConfigProfile.set:(Lxaero/lib/common/config/option/ConfigOption;Ljava/lang/Object;)Ljava/lang/Object;
      3839: pop
      3840: goto          4987
      3843: aload_1
      3844: iconst_0
      3845: aaload
      3846: ldc_w         #949                // String mainDotSize
      3849: invokevirtual #330                // Method java/lang/String.equalsIgnoreCase:(Ljava/lang/String;)Z
      3852: ifeq          3876
      3855: aload_3
      3856: invokevirtual #380                // Method xaero/lib/client/config/ClientConfigManager.getCurrentProfile:()Lxaero/lib/common/config/profile/ConfigProfile;
      3859: getstatic     #951                // Field xaero/hud/minimap/common/config/option/MinimapProfiledConfigOptions.RADAR_MAIN_DOT_SIZE:Lxaero/lib/common/config/option/RangeConfigOption;
      3862: aload_2
      3863: invokestatic  #348                // Method java/lang/Integer.parseInt:(Ljava/lang/String;)I
      3866: invokestatic  #354                // Method java/lang/Integer.valueOf:(I)Ljava/lang/Integer;
      3869: invokevirtual #387                // Method xaero/lib/common/config/profile/ConfigProfile.set:(Lxaero/lib/common/config/option/ConfigOption;Ljava/lang/Object;)Ljava/lang/Object;
      3872: pop
      3873: goto          4987
      3876: aload_1
      3877: iconst_0
      3878: aaload
      3879: ldc_w         #954                // String partialYTeleportation
      3882: invokevirtual #330                // Method java/lang/String.equalsIgnoreCase:(Ljava/lang/String;)Z
      3885: ifeq          3912
      3888: aload_3
      3889: invokevirtual #380                // Method xaero/lib/client/config/ClientConfigManager.getCurrentProfile:()Lxaero/lib/common/config/profile/ConfigProfile;
      3892: getstatic     #956                // Field xaero/hud/minimap/common/config/option/MinimapProfiledConfigOptions.WAYPOINT_PARTIAL_Y_TELEPORT:Lxaero/lib/common/config/option/BooleanConfigOption;
      3895: aload_2
      3896: ldc_w         #368                // String true
      3899: invokevirtual #370                // Method java/lang/String.equals:(Ljava/lang/Object;)Z
      3902: invokestatic  #374                // Method java/lang/Boolean.valueOf:(Z)Ljava/lang/Boolean;
      3905: invokevirtual #387                // Method xaero/lib/common/config/profile/ConfigProfile.set:(Lxaero/lib/common/config/option/ConfigOption;Ljava/lang/Object;)Ljava/lang/Object;
      3908: pop
      3909: goto          4987
      3912: aload_1
      3913: iconst_0
      3914: aaload
      3915: ldc_w         #959                // String deleteReachedDeathpoints
      3918: invokevirtual #330                // Method java/lang/String.equalsIgnoreCase:(Ljava/lang/String;)Z
      3921: ifeq          3948
      3924: aload_3
      3925: invokevirtual #380                // Method xaero/lib/client/config/ClientConfigManager.getCurrentProfile:()Lxaero/lib/common/config/profile/ConfigProfile;
      3928: getstatic     #961                // Field xaero/hud/minimap/common/config/option/MinimapProfiledConfigOptions.DELETE_REACHED_DEATHPOINTS:Lxaero/lib/common/config/option/BooleanConfigOption;
      3931: aload_2
      3932: ldc_w         #368                // String true
      3935: invokevirtual #370                // Method java/lang/String.equals:(Ljava/lang/Object;)Z
      3938: invokestatic  #374                // Method java/lang/Boolean.valueOf:(Z)Ljava/lang/Boolean;
      3941: invokevirtual #387                // Method xaero/lib/common/config/profile/ConfigProfile.set:(Lxaero/lib/common/config/option/ConfigOption;Ljava/lang/Object;)Ljava/lang/Object;
      3944: pop
      3945: goto          4987
      3948: aload_1
      3949: iconst_0
      3950: aaload
      3951: ldc_w         #964                // String hideMinimapUnderScreen
      3954: invokevirtual #330                // Method java/lang/String.equalsIgnoreCase:(Ljava/lang/String;)Z
      3957: ifeq          3984
      3960: aload_3
      3961: invokevirtual #380                // Method xaero/lib/client/config/ClientConfigManager.getCurrentProfile:()Lxaero/lib/common/config/profile/ConfigProfile;
      3964: getstatic     #966                // Field xaero/hud/minimap/common/config/option/MinimapProfiledConfigOptions.HIDE_UNDER_SCREEN:Lxaero/lib/common/config/option/BooleanConfigOption;
      3967: aload_2
      3968: ldc_w         #368                // String true
      3971: invokevirtual #370                // Method java/lang/String.equals:(Ljava/lang/Object;)Z
      3974: invokestatic  #374                // Method java/lang/Boolean.valueOf:(Z)Ljava/lang/Boolean;
      3977: invokevirtual #387                // Method xaero/lib/common/config/profile/ConfigProfile.set:(Lxaero/lib/common/config/option/ConfigOption;Ljava/lang/Object;)Ljava/lang/Object;
      3980: pop
      3981: goto          4987
      3984: aload_1
      3985: iconst_0
      3986: aaload
      3987: ldc_w         #969                // String manualCaveModeStart
      3990: invokevirtual #330                // Method java/lang/String.equalsIgnoreCase:(Ljava/lang/String;)Z
      3993: ifeq          4017
      3996: aload_3
      3997: invokevirtual #380                // Method xaero/lib/client/config/ClientConfigManager.getCurrentProfile:()Lxaero/lib/common/config/profile/ConfigProfile;
      4000: getstatic     #971                // Field xaero/hud/minimap/common/config/option/MinimapProfiledConfigOptions.MANUAL_CAVE_MODE_START:Lxaero/lib/common/config/option/IndexedConfigOption;
      4003: aload_2
      4004: invokestatic  #348                // Method java/lang/Integer.parseInt:(Ljava/lang/String;)I
      4007: invokestatic  #354                // Method java/lang/Integer.valueOf:(I)Ljava/lang/Integer;
      4010: invokevirtual #387                // Method xaero/lib/common/config/profile/ConfigProfile.set:(Lxaero/lib/common/config/option/ConfigOption;Ljava/lang/Object;)Ljava/lang/Object;
      4013: pop
      4014: goto          4987
      4017: aload_1
      4018: iconst_0
      4019: aaload
      4020: ldc_w         #974                // String manualCaveModeStartAuto
      4023: invokevirtual #330                // Method java/lang/String.equalsIgnoreCase:(Ljava/lang/String;)Z
      4026: ifeq          4061
      4029: aload_2
      4030: ldc_w         #368                // String true
      4033: invokevirtual #370                // Method java/lang/String.equals:(Ljava/lang/Object;)Z
      4036: istore        4
      4038: iload         4
      4040: ifeq          4058
      4043: aload_3
      4044: invokevirtual #380                // Method xaero/lib/client/config/ClientConfigManager.getCurrentProfile:()Lxaero/lib/common/config/profile/ConfigProfile;
      4047: getstatic     #971                // Field xaero/hud/minimap/common/config/option/MinimapProfiledConfigOptions.MANUAL_CAVE_MODE_START:Lxaero/lib/common/config/option/IndexedConfigOption;
      4050: iconst_0
      4051: invokestatic  #354                // Method java/lang/Integer.valueOf:(I)Ljava/lang/Integer;
      4054: invokevirtual #387                // Method xaero/lib/common/config/profile/ConfigProfile.set:(Lxaero/lib/common/config/option/ConfigOption;Ljava/lang/Object;)Ljava/lang/Object;
      4057: pop
      4058: goto          4987
      4061: aload_1
      4062: iconst_0
      4063: aaload
      4064: ldc_w         #976                // String chunkGridLineWidth
      4067: invokevirtual #330                // Method java/lang/String.equalsIgnoreCase:(Ljava/lang/String;)Z
      4070: ifeq          4094
      4073: aload_3
      4074: invokevirtual #380                // Method xaero/lib/client/config/ClientConfigManager.getCurrentProfile:()Lxaero/lib/common/config/profile/ConfigProfile;
      4077: getstatic     #978                // Field xaero/hud/minimap/common/config/option/MinimapProfiledConfigOptions.CHUNK_GRID_LINE_WIDTH:Lxaero/lib/common/config/option/RangeConfigOption;
      4080: aload_2
      4081: invokestatic  #348                // Method java/lang/Integer.parseInt:(Ljava/lang/String;)I
      4084: invokestatic  #354                // Method java/lang/Integer.valueOf:(I)Ljava/lang/Integer;
      4087: invokevirtual #387                // Method xaero/lib/common/config/profile/ConfigProfile.set:(Lxaero/lib/common/config/option/ConfigOption;Ljava/lang/Object;)Ljava/lang/Object;
      4090: pop
      4091: goto          4987
      4094: aload_1
      4095: iconst_0
      4096: aaload
      4097: ldc_w         #981                // String hideMinimapUnderF3
      4100: invokevirtual #330                // Method java/lang/String.equalsIgnoreCase:(Ljava/lang/String;)Z
      4103: ifeq          4130
      4106: aload_3
      4107: invokevirtual #380                // Method xaero/lib/client/config/ClientConfigManager.getCurrentProfile:()Lxaero/lib/common/config/profile/ConfigProfile;
      4110: getstatic     #983                // Field xaero/hud/minimap/common/config/option/MinimapProfiledConfigOptions.HIDE_UNDER_F3:Lxaero/lib/common/config/option/BooleanConfigOption;
      4113: aload_2
      4114: ldc_w         #368                // String true
      4117: invokevirtual #370                // Method java/lang/String.equals:(Ljava/lang/Object;)Z
      4120: invokestatic  #374                // Method java/lang/Boolean.valueOf:(Z)Ljava/lang/Boolean;
      4123: invokevirtual #387                // Method xaero/lib/common/config/profile/ConfigProfile.set:(Lxaero/lib/common/config/option/ConfigOption;Ljava/lang/Object;)Ljava/lang/Object;
      4126: pop
      4127: goto          4987
      4130: aload_1
      4131: iconst_0
      4132: aaload
      4133: ldc_w         #986                // String temporaryWaypointsGlobal
      4136: invokevirtual #330                // Method java/lang/String.equalsIgnoreCase:(Ljava/lang/String;)Z
      4139: ifeq          4166
      4142: aload_3
      4143: invokevirtual #380                // Method xaero/lib/client/config/ClientConfigManager.getCurrentProfile:()Lxaero/lib/common/config/profile/ConfigProfile;
      4146: getstatic     #988                // Field xaero/hud/minimap/common/config/option/MinimapProfiledConfigOptions.TEMPORARY_WAYPOINTS_GLOBAL:Lxaero/lib/common/config/option/BooleanConfigOption;
      4149: aload_2
      4150: ldc_w         #368                // String true
      4153: invokevirtual #370                // Method java/lang/String.equals:(Ljava/lang/Object;)Z
      4156: invokestatic  #374                // Method java/lang/Boolean.valueOf:(Z)Ljava/lang/Boolean;
      4159: invokevirtual #387                // Method xaero/lib/common/config/profile/ConfigProfile.set:(Lxaero/lib/common/config/option/ConfigOption;Ljava/lang/Object;)Ljava/lang/Object;
      4162: pop
      4163: goto          4987
      4166: aload_1
      4167: iconst_0
      4168: aaload
      4169: ldc_w         #991                // String keepUnlockedWhenEnlarged
      4172: invokevirtual #330                // Method java/lang/String.equalsIgnoreCase:(Ljava/lang/String;)Z
      4175: ifeq          4202
      4178: aload_3
      4179: invokevirtual #380                // Method xaero/lib/client/config/ClientConfigManager.getCurrentProfile:()Lxaero/lib/common/config/profile/ConfigProfile;
      4182: getstatic     #993                // Field xaero/hud/minimap/common/config/option/MinimapProfiledConfigOptions.KEEP_ENLARGED_UNLOCKED:Lxaero/lib/common/config/option/BooleanConfigOption;
      4185: aload_2
      4186: ldc_w         #368                // String true
      4189: invokevirtual #370                // Method java/lang/String.equals:(Ljava/lang/Object;)Z
      4192: invokestatic  #374                // Method java/lang/Boolean.valueOf:(Z)Ljava/lang/Boolean;
      4195: invokevirtual #387                // Method xaero/lib/common/config/profile/ConfigProfile.set:(Lxaero/lib/common/config/option/ConfigOption;Ljava/lang/Object;)Ljava/lang/Object;
      4198: pop
      4199: goto          4987
      4202: aload_1
      4203: iconst_0
      4204: aaload
      4205: ldc_w         #996                // String enlargedMinimapAToggle
      4208: invokevirtual #330                // Method java/lang/String.equalsIgnoreCase:(Ljava/lang/String;)Z
      4211: ifeq          4238
      4214: aload_3
      4215: invokevirtual #380                // Method xaero/lib/client/config/ClientConfigManager.getCurrentProfile:()Lxaero/lib/common/config/profile/ConfigProfile;
      4218: getstatic     #998                // Field xaero/hud/minimap/common/config/option/MinimapProfiledConfigOptions.TOGGLED_ENLARGED:Lxaero/lib/common/config/option/BooleanConfigOption;
      4221: aload_2
      4222: ldc_w         #368                // String true
      4225: invokevirtual #370                // Method java/lang/String.equals:(Ljava/lang/Object;)Z
      4228: invokestatic  #374                // Method java/lang/Boolean.valueOf:(Z)Ljava/lang/Boolean;
      4231: invokevirtual #387                // Method xaero/lib/common/config/profile/ConfigProfile.set:(Lxaero/lib/common/config/option/ConfigOption;Ljava/lang/Object;)Ljava/lang/Object;
      4234: pop
      4235: goto          4987
      4238: aload_1
      4239: iconst_0
      4240: aaload
      4241: ldc_w         #1001               // String displayStainedGlass
      4244: invokevirtual #330                // Method java/lang/String.equalsIgnoreCase:(Ljava/lang/String;)Z
      4247: ifeq          4274
      4250: aload_3
      4251: invokevirtual #380                // Method xaero/lib/client/config/ClientConfigManager.getCurrentProfile:()Lxaero/lib/common/config/profile/ConfigProfile;
      4254: getstatic     #1003               // Field xaero/hud/minimap/common/config/option/MinimapProfiledConfigOptions.DISPLAY_STAINED_GLASS:Lxaero/lib/common/config/option/BooleanConfigOption;
      4257: aload_2
      4258: ldc_w         #368                // String true
      4261: invokevirtual #370                // Method java/lang/String.equals:(Ljava/lang/Object;)Z
      4264: invokestatic  #374                // Method java/lang/Boolean.valueOf:(Z)Ljava/lang/Boolean;
      4267: invokevirtual #387                // Method xaero/lib/common/config/profile/ConfigProfile.set:(Lxaero/lib/common/config/option/ConfigOption;Ljava/lang/Object;)Ljava/lang/Object;
      4270: pop
      4271: goto          4987
      4274: aload_1
      4275: iconst_0
      4276: aaload
      4277: ldc_w         #1006               // String waypointOnMapScale
      4280: invokevirtual #330                // Method java/lang/String.equalsIgnoreCase:(Ljava/lang/String;)Z
      4283: ifeq          4307
      4286: aload_3
      4287: invokevirtual #380                // Method xaero/lib/client/config/ClientConfigManager.getCurrentProfile:()Lxaero/lib/common/config/profile/ConfigProfile;
      4290: getstatic     #1008               // Field xaero/hud/minimap/common/config/option/MinimapProfiledConfigOptions.WAYPOINT_ICON_SCALE_ON_MINIMAP:Lxaero/lib/common/config/option/RangeConfigOption;
      4293: aload_2
      4294: invokestatic  #348                // Method java/lang/Integer.parseInt:(Ljava/lang/String;)I
      4297: invokestatic  #354                // Method java/lang/Integer.valueOf:(I)Ljava/lang/Integer;
      4300: invokevirtual #387                // Method xaero/lib/common/config/profile/ConfigProfile.set:(Lxaero/lib/common/config/option/ConfigOption;Ljava/lang/Object;)Ljava/lang/Object;
      4303: pop
      4304: goto          4987
      4307: aload_1
      4308: iconst_0
      4309: aaload
      4310: ldc_w         #1011               // String switchToAutoOnDeath
      4313: invokevirtual #330                // Method java/lang/String.equalsIgnoreCase:(Ljava/lang/String;)Z
      4316: ifeq          4343
      4319: aload_3
      4320: invokevirtual #380                // Method xaero/lib/client/config/ClientConfigManager.getCurrentProfile:()Lxaero/lib/common/config/profile/ConfigProfile;
      4323: getstatic     #1013               // Field xaero/hud/minimap/common/config/option/MinimapProfiledConfigOptions.AUTO_WAYPOINTS_ON_DEATH:Lxaero/lib/common/config/option/BooleanConfigOption;
      4326: aload_2
      4327: ldc_w         #368                // String true
      4330: invokevirtual #370                // Method java/lang/String.equals:(Ljava/lang/Object;)Z
      4333: invokestatic  #374                // Method java/lang/Boolean.valueOf:(Z)Ljava/lang/Boolean;
      4336: invokevirtual #387                // Method xaero/lib/common/config/profile/ConfigProfile.set:(Lxaero/lib/common/config/option/ConfigOption;Ljava/lang/Object;)Ljava/lang/Object;
      4339: pop
      4340: goto          4987
      4343: aload_1
      4344: iconst_0
      4345: aaload
      4346: ldc_w         #1016               // String displayWeatherInfo
      4349: invokevirtual #330                // Method java/lang/String.equalsIgnoreCase:(Ljava/lang/String;)Z
      4352: ifeq          4372
      4355: aload_0
      4356: aload_2
      4357: ldc_w         #368                // String true
      4360: invokevirtual #370                // Method java/lang/String.equals:(Ljava/lang/Object;)Z
      4363: invokestatic  #374                // Method java/lang/Boolean.valueOf:(Z)Ljava/lang/Boolean;
      4366: putfield      #1018               // Field displayWeatherInfoLegacy:Ljava/lang/Boolean;
      4369: goto          4987
      4372: aload_1
      4373: iconst_0
      4374: aaload
      4375: ldc_w         #1021               // String infoDisplayBackgroundOpacity
      4378: invokevirtual #330                // Method java/lang/String.equalsIgnoreCase:(Ljava/lang/String;)Z
      4381: ifeq          4405
      4384: aload_3
      4385: invokevirtual #380                // Method xaero/lib/client/config/ClientConfigManager.getCurrentProfile:()Lxaero/lib/common/config/profile/ConfigProfile;
      4388: getstatic     #1023               // Field xaero/hud/minimap/common/config/option/MinimapProfiledConfigOptions.INFO_DISPLAY_BG_OPACITY:Lxaero/lib/common/config/option/RangeConfigOption;
      4391: aload_2
      4392: invokestatic  #348                // Method java/lang/Integer.parseInt:(Ljava/lang/String;)I
      4395: invokestatic  #354                // Method java/lang/Integer.valueOf:(I)Ljava/lang/Integer;
      4398: invokevirtual #387                // Method xaero/lib/common/config/profile/ConfigProfile.set:(Lxaero/lib/common/config/option/ConfigOption;Ljava/lang/Object;)Ljava/lang/Object;
      4401: pop
      4402: goto          4987
      4405: aload_1
      4406: iconst_0
      4407: aaload
      4408: ldc_w         #1026               // String caveModeToggleTimer
      4411: invokevirtual #330                // Method java/lang/String.equalsIgnoreCase:(Ljava/lang/String;)Z
      4414: ifeq          4439
      4417: aload_3
      4418: invokevirtual #380                // Method xaero/lib/client/config/ClientConfigManager.getCurrentProfile:()Lxaero/lib/common/config/profile/ConfigProfile;
      4421: getstatic     #1028               // Field xaero/hud/minimap/common/config/option/MinimapProfiledConfigOptions.CAVE_MODE_TOGGLE_TIMER:Lxaero/lib/common/config/option/SteppedConfigOption;
      4424: aload_2
      4425: invokestatic  #348                // Method java/lang/Integer.parseInt:(Ljava/lang/String;)I
      4428: i2d
      4429: invokestatic  #1031               // Method java/lang/Double.valueOf:(D)Ljava/lang/Double;
      4432: invokevirtual #387                // Method xaero/lib/common/config/profile/ConfigProfile.set:(Lxaero/lib/common/config/option/ConfigOption;Ljava/lang/Object;)Ljava/lang/Object;
      4435: pop
      4436: goto          4987
      4439: aload_1
      4440: iconst_0
      4441: aaload
      4442: ldc_w         #1034               // String legibleCaveMaps
      4445: invokevirtual #330                // Method java/lang/String.equalsIgnoreCase:(Ljava/lang/String;)Z
      4448: ifeq          4475
      4451: aload_3
      4452: invokevirtual #380                // Method xaero/lib/client/config/ClientConfigManager.getCurrentProfile:()Lxaero/lib/common/config/profile/ConfigProfile;
      4455: getstatic     #1036               // Field xaero/hud/minimap/common/config/option/MinimapProfiledConfigOptions.LEGIBLE_CAVE_MAPS:Lxaero/lib/common/config/option/BooleanConfigOption;
      4458: aload_2
      4459: ldc_w         #368                // String true
      4462: invokevirtual #370                // Method java/lang/String.equals:(Ljava/lang/Object;)Z
      4465: invokestatic  #374                // Method java/lang/Boolean.valueOf:(Z)Ljava/lang/Boolean;
      4468: invokevirtual #387                // Method xaero/lib/common/config/profile/ConfigProfile.set:(Lxaero/lib/common/config/option/ConfigOption;Ljava/lang/Object;)Ljava/lang/Object;
      4471: pop
      4472: goto          4987
      4475: aload_1
      4476: iconst_0
      4477: aaload
      4478: ldc_w         #1039               // String biomeBlending
      4481: invokevirtual #330                // Method java/lang/String.equalsIgnoreCase:(Ljava/lang/String;)Z
      4484: ifeq          4511
      4487: aload_3
      4488: invokevirtual #380                // Method xaero/lib/client/config/ClientConfigManager.getCurrentProfile:()Lxaero/lib/common/config/profile/ConfigProfile;
      4491: getstatic     #1041               // Field xaero/hud/minimap/common/config/option/MinimapProfiledConfigOptions.BIOME_BLENDING:Lxaero/lib/common/config/option/BooleanConfigOption;
      4494: aload_2
      4495: ldc_w         #368                // String true
      4498: invokevirtual #370                // Method java/lang/String.equals:(Ljava/lang/Object;)Z
      4501: invokestatic  #374                // Method java/lang/Boolean.valueOf:(Z)Ljava/lang/Boolean;
      4504: invokevirtual #387                // Method xaero/lib/common/config/profile/ConfigProfile.set:(Lxaero/lib/common/config/option/ConfigOption;Ljava/lang/Object;)Ljava/lang/Object;
      4507: pop
      4508: goto          4987
      4511: aload_1
      4512: iconst_0
      4513: aaload
      4514: ldc_w         #1044               // String displayPacPlayers
      4517: invokevirtual #330                // Method java/lang/String.equalsIgnoreCase:(Ljava/lang/String;)Z
      4520: ifne          4535
      4523: aload_1
      4524: iconst_0
      4525: aaload
      4526: ldc_w         #1046               // String displayTrackedPlayers
      4529: invokevirtual #330                // Method java/lang/String.equalsIgnoreCase:(Ljava/lang/String;)Z
      4532: ifeq          4580
      4535: aload_3
      4536: invokevirtual #380                // Method xaero/lib/client/config/ClientConfigManager.getCurrentProfile:()Lxaero/lib/common/config/profile/ConfigProfile;
      4539: getstatic     #1048               // Field xaero/hud/minimap/common/config/option/MinimapProfiledConfigOptions.TRACKED_PLAYERS_ON_MINIMAP:Lxaero/lib/common/config/option/BooleanConfigOption;
      4542: aload_2
      4543: ldc_w         #368                // String true
      4546: invokevirtual #370                // Method java/lang/String.equals:(Ljava/lang/Object;)Z
      4549: invokestatic  #374                // Method java/lang/Boolean.valueOf:(Z)Ljava/lang/Boolean;
      4552: invokevirtual #387                // Method xaero/lib/common/config/profile/ConfigProfile.set:(Lxaero/lib/common/config/option/ConfigOption;Ljava/lang/Object;)Ljava/lang/Object;
      4555: pop
      4556: aload_3
      4557: invokevirtual #380                // Method xaero/lib/client/config/ClientConfigManager.getCurrentProfile:()Lxaero/lib/common/config/profile/ConfigProfile;
      4560: getstatic     #1051               // Field xaero/hud/minimap/common/config/option/MinimapProfiledConfigOptions.TRACKED_PLAYERS_IN_WORLD:Lxaero/lib/common/config/option/BooleanConfigOption;
      4563: aload_2
      4564: ldc_w         #368                // String true
      4567: invokevirtual #370                // Method java/lang/String.equals:(Ljava/lang/Object;)Z
      4570: invokestatic  #374                // Method java/lang/Boolean.valueOf:(Z)Ljava/lang/Boolean;
      4573: invokevirtual #387                // Method xaero/lib/common/config/profile/ConfigProfile.set:(Lxaero/lib/common/config/option/ConfigOption;Ljava/lang/Object;)Ljava/lang/Object;
      4576: pop
      4577: goto          4987
      4580: aload_1
      4581: iconst_0
      4582: aaload
      4583: ldc_w         #1054               // String displayTrackedPlayersOnMap
      4586: invokevirtual #330                // Method java/lang/String.equalsIgnoreCase:(Ljava/lang/String;)Z
      4589: ifeq          4616
      4592: aload_3
      4593: invokevirtual #380                // Method xaero/lib/client/config/ClientConfigManager.getCurrentProfile:()Lxaero/lib/common/config/profile/ConfigProfile;
      4596: getstatic     #1048               // Field xaero/hud/minimap/common/config/option/MinimapProfiledConfigOptions.TRACKED_PLAYERS_ON_MINIMAP:Lxaero/lib/common/config/option/BooleanConfigOption;
      4599: aload_2
      4600: ldc_w         #368                // String true
      4603: invokevirtual #370                // Method java/lang/String.equals:(Ljava/lang/Object;)Z
      4606: invokestatic  #374                // Method java/lang/Boolean.valueOf:(Z)Ljava/lang/Boolean;
      4609: invokevirtual #387                // Method xaero/lib/common/config/profile/ConfigProfile.set:(Lxaero/lib/common/config/option/ConfigOption;Ljava/lang/Object;)Ljava/lang/Object;
      4612: pop
      4613: goto          4987
      4616: aload_1
      4617: iconst_0
      4618: aaload
      4619: ldc_w         #1056               // String displayTrackedPlayersInWorld
      4622: invokevirtual #330                // Method java/lang/String.equalsIgnoreCase:(Ljava/lang/String;)Z
      4625: ifeq          4652
      4628: aload_3
      4629: invokevirtual #380                // Method xaero/lib/client/config/ClientConfigManager.getCurrentProfile:()Lxaero/lib/common/config/profile/ConfigProfile;
      4632: getstatic     #1051               // Field xaero/hud/minimap/common/config/option/MinimapProfiledConfigOptions.TRACKED_PLAYERS_IN_WORLD:Lxaero/lib/common/config/option/BooleanConfigOption;
      4635: aload_2
      4636: ldc_w         #368                // String true
      4639: invokevirtual #370                // Method java/lang/String.equals:(Ljava/lang/Object;)Z
      4642: invokestatic  #374                // Method java/lang/Boolean.valueOf:(Z)Ljava/lang/Boolean;
      4645: invokevirtual #387                // Method xaero/lib/common/config/profile/ConfigProfile.set:(Lxaero/lib/common/config/option/ConfigOption;Ljava/lang/Object;)Ljava/lang/Object;
      4648: pop
      4649: goto          4987
      4652: aload_1
      4653: iconst_0
      4654: aaload
      4655: ldc_w         #1058               // String dimensionScaledMaxWaypointDistance
      4658: invokevirtual #330                // Method java/lang/String.equalsIgnoreCase:(Ljava/lang/String;)Z
      4661: ifeq          4688
      4664: aload_3
      4665: invokevirtual #380                // Method xaero/lib/client/config/ClientConfigManager.getCurrentProfile:()Lxaero/lib/common/config/profile/ConfigProfile;
      4668: getstatic     #1060               // Field xaero/hud/minimap/common/config/option/MinimapProfiledConfigOptions.WAYPOINT_MAX_DISTANCE_DIMENSION_SCALE:Lxaero/lib/common/config/option/BooleanConfigOption;
      4671: aload_2
      4672: ldc_w         #368                // String true
      4675: invokevirtual #370                // Method java/lang/String.equals:(Ljava/lang/Object;)Z
      4678: invokestatic  #374                // Method java/lang/Boolean.valueOf:(Z)Ljava/lang/Boolean;
      4681: invokevirtual #387                // Method xaero/lib/common/config/profile/ConfigProfile.set:(Lxaero/lib/common/config/option/ConfigOption;Ljava/lang/Object;)Ljava/lang/Object;
      4684: pop
      4685: goto          4987
      4688: aload_1
      4689: iconst_0
      4690: aaload
      4691: ldc_w         #1063               // String trackedPlayerWorldIconScale
      4694: invokevirtual #330                // Method java/lang/String.equalsIgnoreCase:(Ljava/lang/String;)Z
      4697: ifeq          4723
      4700: aload_3
      4701: invokevirtual #380                // Method xaero/lib/client/config/ClientConfigManager.getCurrentProfile:()Lxaero/lib/common/config/profile/ConfigProfile;
      4704: getstatic     #1065               // Field xaero/hud/minimap/common/config/option/MinimapProfiledConfigOptions.TRACKED_PLAYER_WORLD_ICON_SCALE:Lxaero/lib/common/config/option/RangeConfigOption;
      4707: aload_1
      4708: iconst_1
      4709: aaload
      4710: invokestatic  #348                // Method java/lang/Integer.parseInt:(Ljava/lang/String;)I
      4713: invokestatic  #354                // Method java/lang/Integer.valueOf:(I)Ljava/lang/Integer;
      4716: invokevirtual #387                // Method xaero/lib/common/config/profile/ConfigProfile.set:(Lxaero/lib/common/config/option/ConfigOption;Ljava/lang/Object;)Ljava/lang/Object;
      4719: pop
      4720: goto          4987
      4723: aload_1
      4724: iconst_0
      4725: aaload
      4726: ldc_w         #1068               // String trackedPlayerWorldNameScale
      4729: invokevirtual #330                // Method java/lang/String.equalsIgnoreCase:(Ljava/lang/String;)Z
      4732: ifeq          4758
      4735: aload_3
      4736: invokevirtual #380                // Method xaero/lib/client/config/ClientConfigManager.getCurrentProfile:()Lxaero/lib/common/config/profile/ConfigProfile;
      4739: getstatic     #1070               // Field xaero/hud/minimap/common/config/option/MinimapProfiledConfigOptions.TRACKED_PLAYER_WORLD_NAME_SCALE:Lxaero/lib/common/config/option/RangeConfigOption;
      4742: aload_1
      4743: iconst_1
      4744: aaload
      4745: invokestatic  #348                // Method java/lang/Integer.parseInt:(Ljava/lang/String;)I
      4748: invokestatic  #354                // Method java/lang/Integer.valueOf:(I)Ljava/lang/Integer;
      4751: invokevirtual #387                // Method xaero/lib/common/config/profile/ConfigProfile.set:(Lxaero/lib/common/config/option/ConfigOption;Ljava/lang/Object;)Ljava/lang/Object;
      4754: pop
      4755: goto          4987
      4758: aload_1
      4759: iconst_0
      4760: aaload
      4761: ldc_w         #1073               // String trackedPlayerMinimapIconScale
      4764: invokevirtual #330                // Method java/lang/String.equalsIgnoreCase:(Ljava/lang/String;)Z
      4767: ifeq          4793
      4770: aload_3
      4771: invokevirtual #380                // Method xaero/lib/client/config/ClientConfigManager.getCurrentProfile:()Lxaero/lib/common/config/profile/ConfigProfile;
      4774: getstatic     #1075               // Field xaero/hud/minimap/common/config/option/MinimapProfiledConfigOptions.TRACKED_PLAYER_MINIMAP_ICON_SCALE:Lxaero/lib/common/config/option/RangeConfigOption;
      4777: aload_1
      4778: iconst_1
      4779: aaload
      4780: invokestatic  #348                // Method java/lang/Integer.parseInt:(Ljava/lang/String;)I
      4783: invokestatic  #354                // Method java/lang/Integer.valueOf:(I)Ljava/lang/Integer;
      4786: invokevirtual #387                // Method xaero/lib/common/config/profile/ConfigProfile.set:(Lxaero/lib/common/config/option/ConfigOption;Ljava/lang/Object;)Ljava/lang/Object;
      4789: pop
      4790: goto          4987
      4793: aload_1
      4794: iconst_0
      4795: aaload
      4796: ldc_w         #1078               // String displayClaims
      4799: invokevirtual #330                // Method java/lang/String.equalsIgnoreCase:(Ljava/lang/String;)Z
      4802: ifeq          4829
      4805: aload_3
      4806: invokevirtual #380                // Method xaero/lib/client/config/ClientConfigManager.getCurrentProfile:()Lxaero/lib/common/config/profile/ConfigProfile;
      4809: getstatic     #1080               // Field xaero/hud/minimap/common/config/option/MinimapProfiledConfigOptions.OPAC_CLAIMS:Lxaero/lib/common/config/option/BooleanConfigOption;
      4812: aload_2
      4813: ldc_w         #368                // String true
      4816: invokevirtual #370                // Method java/lang/String.equals:(Ljava/lang/Object;)Z
      4819: invokestatic  #374                // Method java/lang/Boolean.valueOf:(Z)Ljava/lang/Boolean;
      4822: invokevirtual #387                // Method xaero/lib/common/config/profile/ConfigProfile.set:(Lxaero/lib/common/config/option/ConfigOption;Ljava/lang/Object;)Ljava/lang/Object;
      4825: pop
      4826: goto          4987
      4829: aload_1
      4830: iconst_0
      4831: aaload
      4832: ldc_w         #1083               // String displayCurrentClaim
      4835: invokevirtual #330                // Method java/lang/String.equalsIgnoreCase:(Ljava/lang/String;)Z
      4838: ifeq          4865
      4841: aload_3
      4842: invokevirtual #380                // Method xaero/lib/client/config/ClientConfigManager.getCurrentProfile:()Lxaero/lib/common/config/profile/ConfigProfile;
      4845: getstatic     #1085               // Field xaero/hud/minimap/common/config/option/MinimapProfiledConfigOptions.OPAC_CURRENT_CLAIM:Lxaero/lib/common/config/option/BooleanConfigOption;
      4848: aload_2
      4849: ldc_w         #368                // String true
      4852: invokevirtual #370                // Method java/lang/String.equals:(Ljava/lang/Object;)Z
      4855: invokestatic  #374                // Method java/lang/Boolean.valueOf:(Z)Ljava/lang/Boolean;
      4858: invokevirtual #387                // Method xaero/lib/common/config/profile/ConfigProfile.set:(Lxaero/lib/common/config/option/ConfigOption;Ljava/lang/Object;)Ljava/lang/Object;
      4861: pop
      4862: goto          4987
      4865: aload_1
      4866: iconst_0
      4867: aaload
      4868: ldc_w         #1088               // String claimsOpacity
      4871: invokevirtual #330                // Method java/lang/String.equalsIgnoreCase:(Ljava/lang/String;)Z
      4874: ifeq          4924
      4877: aload_2
      4878: invokestatic  #348                // Method java/lang/Integer.parseInt:(Ljava/lang/String;)I
      4881: istore        4
      4883: aload_3
      4884: invokevirtual #380                // Method xaero/lib/client/config/ClientConfigManager.getCurrentProfile:()Lxaero/lib/common/config/profile/ConfigProfile;
      4887: getstatic     #1090               // Field xaero/hud/minimap/common/config/option/MinimapProfiledConfigOptions.OPAC_CLAIMS_BORDER_OPACITY:Lxaero/lib/common/config/option/RangeConfigOption;
      4890: iload         4
      4892: invokestatic  #354                // Method java/lang/Integer.valueOf:(I)Ljava/lang/Integer;
      4895: invokevirtual #387                // Method xaero/lib/common/config/profile/ConfigProfile.set:(Lxaero/lib/common/config/option/ConfigOption;Ljava/lang/Object;)Ljava/lang/Object;
      4898: pop
      4899: aload_3
      4900: invokevirtual #380                // Method xaero/lib/client/config/ClientConfigManager.getCurrentProfile:()Lxaero/lib/common/config/profile/ConfigProfile;
      4903: getstatic     #1093               // Field xaero/hud/minimap/common/config/option/MinimapProfiledConfigOptions.OPAC_CLAIMS_FILL_OPACITY:Lxaero/lib/common/config/option/RangeConfigOption;
      4906: iload         4
      4908: bipush        58
      4910: imul
      4911: bipush        100
      4913: idiv
      4914: invokestatic  #354                // Method java/lang/Integer.valueOf:(I)Ljava/lang/Integer;
      4917: invokevirtual #387                // Method xaero/lib/common/config/profile/ConfigProfile.set:(Lxaero/lib/common/config/option/ConfigOption;Ljava/lang/Object;)Ljava/lang/Object;
      4920: pop
      4921: goto          4987
      4924: aload_1
      4925: iconst_0
      4926: aaload
      4927: ldc_w         #1096               // String claimsBorderOpacity
      4930: invokevirtual #330                // Method java/lang/String.equalsIgnoreCase:(Ljava/lang/String;)Z
      4933: ifeq          4957
      4936: aload_3
      4937: invokevirtual #380                // Method xaero/lib/client/config/ClientConfigManager.getCurrentProfile:()Lxaero/lib/common/config/profile/ConfigProfile;
      4940: getstatic     #1090               // Field xaero/hud/minimap/common/config/option/MinimapProfiledConfigOptions.OPAC_CLAIMS_BORDER_OPACITY:Lxaero/lib/common/config/option/RangeConfigOption;
      4943: aload_2
      4944: invokestatic  #348                // Method java/lang/Integer.parseInt:(Ljava/lang/String;)I
      4947: invokestatic  #354                // Method java/lang/Integer.valueOf:(I)Ljava/lang/Integer;
      4950: invokevirtual #387                // Method xaero/lib/common/config/profile/ConfigProfile.set:(Lxaero/lib/common/config/option/ConfigOption;Ljava/lang/Object;)Ljava/lang/Object;
      4953: pop
      4954: goto          4987
      4957: aload_1
      4958: iconst_0
      4959: aaload
      4960: ldc_w         #1098               // String claimsFillOpacity
      4963: invokevirtual #330                // Method java/lang/String.equalsIgnoreCase:(Ljava/lang/String;)Z
      4966: ifeq          4987
      4969: aload_3
      4970: invokevirtual #380                // Method xaero/lib/client/config/ClientConfigManager.getCurrentProfile:()Lxaero/lib/common/config/profile/ConfigProfile;
      4973: getstatic     #1093               // Field xaero/hud/minimap/common/config/option/MinimapProfiledConfigOptions.OPAC_CLAIMS_FILL_OPACITY:Lxaero/lib/common/config/option/RangeConfigOption;
      4976: aload_2
      4977: invokestatic  #348                // Method java/lang/Integer.parseInt:(Ljava/lang/String;)I
      4980: invokestatic  #354                // Method java/lang/Integer.valueOf:(I)Ljava/lang/Integer;
      4983: invokevirtual #387                // Method xaero/lib/common/config/profile/ConfigProfile.set:(Lxaero/lib/common/config/option/ConfigOption;Ljava/lang/Object;)Ljava/lang/Object;
      4986: pop
      4987: return

  public void loadDefaultSettings(boolean) throws java.io.IOException;
    Code:
         0: aload_0
         1: getfield      #7                  // Field modMain:Lxaero/common/IXaeroMinimap;
         4: invokeinterface #256,  1          // InterfaceMethod xaero/common/IXaeroMinimap.getConfigFile:()Ljava/nio/file/Path;
         9: astore_2
        10: aload_2
        11: invokeinterface #1100,  1         // InterfaceMethod java/nio/file/Path.getParent:()Ljava/nio/file/Path;
        16: ldc_w         #1103               // String defaultconfigs
        19: invokeinterface #1105,  2         // InterfaceMethod java/nio/file/Path.resolveSibling:(Ljava/lang/String;)Ljava/nio/file/Path;
        24: getstatic     #43                 // Field xaero/common/HudMod.INSTANCE:Lxaero/common/HudMod;
        27: invokevirtual #1109               // Method xaero/common/HudMod.getOldConfigFileName:()Ljava/lang/String;
        30: invokeinterface #1112,  2         // InterfaceMethod java/nio/file/Path.resolve:(Ljava/lang/String;)Ljava/nio/file/Path;
        35: astore_3
        36: aload_3
        37: iconst_0
        38: anewarray     #1115               // class java/nio/file/LinkOption
        41: invokestatic  #1117               // Method java/nio/file/Files.exists:(Ljava/nio/file/Path;[Ljava/nio/file/LinkOption;)Z
        44: ifeq          58
        47: aload_0
        48: aload_3
        49: invokeinterface #260,  1          // InterfaceMethod java/nio/file/Path.toFile:()Ljava/io/File;
        54: iload_1
        55: invokevirtual #1123               // Method loadSettingsFile:(Ljava/io/File;Z)V
        58: aload_2
        59: invokeinterface #1100,  1         // InterfaceMethod java/nio/file/Path.getParent:()Ljava/nio/file/Path;
        64: ldc_w         #1103               // String defaultconfigs
        67: invokeinterface #1105,  2         // InterfaceMethod java/nio/file/Path.resolveSibling:(Ljava/lang/String;)Ljava/nio/file/Path;
        72: aload_2
        73: invokeinterface #1127,  1         // InterfaceMethod java/nio/file/Path.getFileName:()Ljava/nio/file/Path;
        78: invokeinterface #1130,  2         // InterfaceMethod java/nio/file/Path.resolve:(Ljava/nio/file/Path;)Ljava/nio/file/Path;
        83: invokeinterface #260,  1          // InterfaceMethod java/nio/file/Path.toFile:()Ljava/io/File;
        88: astore        4
        90: aload         4
        92: invokevirtual #1133               // Method java/io/File.exists:()Z
        95: ifeq          105
        98: aload_0
        99: aload         4
       101: iload_1
       102: invokevirtual #1123               // Method loadSettingsFile:(Ljava/io/File;Z)V
       105: return

  public void loadSettings(boolean) throws java.io.IOException;
    Code:
         0: aload_0
         1: iload_1
         2: invokevirtual #1137               // Method loadDefaultSettings:(Z)V
         5: aload_0
         6: getfield      #7                  // Field modMain:Lxaero/common/IXaeroMinimap;
         9: invokeinterface #256,  1          // InterfaceMethod xaero/common/IXaeroMinimap.getConfigFile:()Ljava/nio/file/Path;
        14: astore_2
        15: aload_2
        16: invokeinterface #1100,  1         // InterfaceMethod java/nio/file/Path.getParent:()Ljava/nio/file/Path;
        21: astore_3
        22: aload_3
        23: iconst_0
        24: anewarray     #1115               // class java/nio/file/LinkOption
        27: invokestatic  #1117               // Method java/nio/file/Files.exists:(Ljava/nio/file/Path;[Ljava/nio/file/LinkOption;)Z
        30: ifne          42
        33: aload_3
        34: iconst_0
        35: anewarray     #1141               // class java/nio/file/attribute/FileAttribute
        38: invokestatic  #1143               // Method java/nio/file/Files.createDirectories:(Ljava/nio/file/Path;[Ljava/nio/file/attribute/FileAttribute;)Ljava/nio/file/Path;
        41: pop
        42: aload_2
        43: iconst_0
        44: anewarray     #1115               // class java/nio/file/LinkOption
        47: invokestatic  #1117               // Method java/nio/file/Files.exists:(Ljava/nio/file/Path;[Ljava/nio/file/LinkOption;)Z
        50: ifeq          64
        53: aload_0
        54: aload_2
        55: invokeinterface #260,  1          // InterfaceMethod java/nio/file/Path.toFile:()Ljava/io/File;
        60: iload_1
        61: invokevirtual #1123               // Method loadSettingsFile:(Ljava/io/File;Z)V
        64: aload_0
        65: invokevirtual #1147               // Method saveSettings:()V
        68: return

  private void loadSettingsFile(java.io.File, boolean) throws java.io.IOException;
    Code:
         0: aconst_null
         1: astore_3
         2: new           #1150               // class java/io/BufferedReader
         5: dup
         6: new           #1152               // class java/io/FileReader
         9: dup
        10: aload_1
        11: invokespecial #1154               // Method java/io/FileReader."<init>":(Ljava/io/File;)V
        14: invokespecial #1155               // Method java/io/BufferedReader."<init>":(Ljava/io/Reader;)V
        17: astore_3
        18: new           #1158               // class java/lang/StringBuilder
        21: dup
        22: invokespecial #1160               // Method java/lang/StringBuilder."<init>":()V
        25: astore        5
        27: new           #1158               // class java/lang/StringBuilder
        30: dup
        31: invokespecial #1160               // Method java/lang/StringBuilder."<init>":()V
        34: astore        6
        36: aload_3
        37: invokevirtual #1161               // Method java/io/BufferedReader.readLine:()Ljava/lang/String;
        40: dup
        41: astore        4
        43: ifnull        253
        46: aload_0
        47: getfield      #7                  // Field modMain:Lxaero/common/IXaeroMinimap;
        50: invokeinterface #314,  1          // InterfaceMethod xaero/common/IXaeroMinimap.getHudIO:()Lxaero/hud/io/HudIO;
        55: aload         4
        57: iload_2
        58: invokevirtual #1164               // Method xaero/hud/io/HudIO.load:(Ljava/lang/String;Z)Z
        61: ifeq          67
        64: goto          36
        67: aload         4
        69: ldc_w         #660                // String :
        72: invokevirtual #1168               // Method java/lang/String.split:(Ljava/lang/String;)[Ljava/lang/String;
        75: astore        7
        77: aload         7
        79: iconst_0
        80: aaload
        81: ldc_w         #1172               // String waypoint
        84: invokevirtual #370                // Method java/lang/String.equals:(Ljava/lang/Object;)Z
        87: ifne          103
        90: aload         7
        92: iconst_0
        93: aaload
        94: ldc_w         #1174               // String world
        97: invokevirtual #370                // Method java/lang/String.equals:(Ljava/lang/Object;)Z
       100: ifeq          120
       103: aload         5
       105: aload         4
       107: invokevirtual #1176               // Method java/lang/StringBuilder.append:(Ljava/lang/String;)Ljava/lang/StringBuilder;
       110: ldc_w         #1180               // String \n
       113: invokevirtual #1176               // Method java/lang/StringBuilder.append:(Ljava/lang/String;)Ljava/lang/StringBuilder;
       116: pop
       117: goto          36
       120: iload_2
       121: ifne          127
       124: goto          36
       127: aload         7
       129: iconst_0
       130: aaload
       131: ldc_w         #1182               // String interface
       134: invokevirtual #330                // Method java/lang/String.equalsIgnoreCase:(Ljava/lang/String;)Z
       137: ifeq          179
       140: aload         7
       142: iconst_1
       143: aaload
       144: ldc_w         #1184               // String gui.xaero_minimap
       147: invokevirtual #370                // Method java/lang/String.equals:(Ljava/lang/Object;)Z
       150: ifeq          179
       153: getstatic     #77                 // Field xaero/hud/minimap/BuiltInHudModules.MINIMAP:Lxaero/hud/module/HudModule;
       156: aload_0
       157: getfield      #7                  // Field modMain:Lxaero/common/IXaeroMinimap;
       160: invokeinterface #1186,  1         // InterfaceMethod xaero/common/IXaeroMinimap.getHud:()Lxaero/hud/Hud;
       165: invokevirtual #1190               // Method xaero/hud/Hud.getOldSystemCompatibility:()Lxaero/hud/compat/OldSystemCompatibility;
       168: aload         7
       170: invokevirtual #1196               // Method xaero/hud/compat/OldSystemCompatibility.loadOldTransform:([Ljava/lang/String;)Lxaero/hud/module/ModuleTransform;
       173: invokevirtual #1202               // Method xaero/hud/module/HudModule.setTransform:(Lxaero/hud/module/ModuleTransform;)V
       176: goto          228
       179: aload         7
       181: iconst_0
       182: aaload
       183: ldc_w         #1206               // String infoDisplayOrder
       186: invokevirtual #370                // Method java/lang/String.equals:(Ljava/lang/Object;)Z
       189: ifne          205
       192: aload         7
       194: iconst_0
       195: aaload
       196: ldc_w         #1208               // String infoDisplay
       199: invokevirtual #370                // Method java/lang/String.equals:(Ljava/lang/Object;)Z
       202: ifeq          222
       205: aload         6
       207: aload         4
       209: invokevirtual #1176               // Method java/lang/StringBuilder.append:(Ljava/lang/String;)Ljava/lang/StringBuilder;
       212: ldc_w         #1180               // String \n
       215: invokevirtual #1176               // Method java/lang/StringBuilder.append:(Ljava/lang/String;)Ljava/lang/StringBuilder;
       218: pop
       219: goto          228
       222: aload_0
       223: aload         7
       225: invokevirtual #1210               // Method readSetting:([Ljava/lang/String;)V
       228: goto          250
       231: astore        8
       233: getstatic     #1215               // Field xaero/hud/minimap/MinimapLogs.LOGGER:Lorg/apache/logging/log4j/Logger;
       236: aload         7
       238: iconst_0
       239: aaload
       240: invokedynamic #1221,  0           // InvokeDynamic #6:makeConcatWithConstants:(Ljava/lang/String;)Ljava/lang/String;
       245: invokeinterface #1222,  2         // InterfaceMethod org/apache/logging/log4j/Logger.info:(Ljava/lang/String;)V
       250: goto          36
       253: aload         6
       255: invokevirtual #1227               // Method java/lang/StringBuilder.isEmpty:()Z
       258: ifne          304
       261: getstatic     #43                 // Field xaero/common/HudMod.INSTANCE:Lxaero/common/HudMod;
       264: invokevirtual #1228               // Method xaero/common/HudMod.getMinimap:()Lxaero/hud/minimap/Minimap;
       267: invokevirtual #1229               // Method xaero/hud/minimap/Minimap.getInfoDisplays:()Lxaero/hud/minimap/info/InfoDisplays;
       270: invokevirtual #1233               // Method xaero/hud/minimap/info/InfoDisplays.getIo:()Lxaero/hud/minimap/info/InfoDisplayIO;
       273: aload         6
       275: invokevirtual #1239               // Method java/lang/StringBuilder.toString:()Ljava/lang/String;
       278: invokevirtual #1242               // Method xaero/hud/minimap/info/InfoDisplayIO.decode:(Ljava/lang/String;)Lxaero/hud/minimap/common/config/info/config/InfoDisplayManagerConfigData;
       281: astore        7
       283: getstatic     #43                 // Field xaero/common/HudMod.INSTANCE:Lxaero/common/HudMod;
       286: invokevirtual #49                 // Method xaero/common/HudMod.getHudConfigs:()Lxaero/lib/common/config/channel/ConfigChannel;
       289: invokevirtual #53                 // Method xaero/lib/common/config/channel/ConfigChannel.getClientConfigManager:()Lxaero/lib/client/config/ClientConfigManager;
       292: invokevirtual #380                // Method xaero/lib/client/config/ClientConfigManager.getCurrentProfile:()Lxaero/lib/common/config/profile/ConfigProfile;
       295: getstatic     #1248               // Field xaero/hud/minimap/common/config/option/MinimapProfiledConfigOptions.INFO_DISPLAY_CONFIG:Lxaero/lib/common/config/option/ConfigOption;
       298: aload         7
       300: invokevirtual #387                // Method xaero/lib/common/config/profile/ConfigProfile.set:(Lxaero/lib/common/config/option/ConfigOption;Ljava/lang/Object;)Ljava/lang/Object;
       303: pop
       304: aload         5
       306: invokevirtual #1227               // Method java/lang/StringBuilder.isEmpty:()Z
       309: ifne          321
       312: aload_0
       313: aload         5
       315: invokevirtual #1239               // Method java/lang/StringBuilder.toString:()Ljava/lang/String;
       318: putfield      #304                // Field loadedWaypointLines:Ljava/lang/String;
       321: aload_3
       322: ifnull        345
       325: aload_3
       326: invokevirtual #1251               // Method java/io/BufferedReader.close:()V
       329: goto          345
       332: astore        9
       334: aload_3
       335: ifnull        342
       338: aload_3
       339: invokevirtual #1251               // Method java/io/BufferedReader.close:()V
       342: aload         9
       344: athrow
       345: return
      Exception table:
         from    to  target type
           127   228   231   Class java/lang/Exception
             2   321   332   any
           332   334   332   any

  public static java.lang.String getTranslation(boolean);
    Code:
         0: iload_0
         1: ifeq          10
         4: ldc_w         #1252               // String on
         7: goto          13
        10: ldc_w         #1254               // String off
        13: invokedynamic #1256,  0           // InvokeDynamic #7:makeConcatWithConstants:(Ljava/lang/String;)Ljava/lang/String;
        18: iconst_0
        19: anewarray     #2                  // class java/lang/Object
        22: invokestatic  #1257               // Method net/minecraft/client/resources/language/I18n.get:(Ljava/lang/String;[Ljava/lang/Object;)Ljava/lang/String;
        25: areturn

  private void refreshScreen();
    Code:
         0: invokestatic  #1262               // Method xaero/hud/gui/util/GuiUtils.refreshScreenBase:()V
         3: return

  public boolean minimapDisabled();
    Code:
         0: getstatic     #40                 // Field serverSettings:I
         3: iconst_1
         4: iand
         5: iconst_1
         6: if_icmpeq     13
         9: iconst_1
        10: goto          14
        13: iconst_0
        14: ireturn

  public boolean caveMapsDisabled();
    Code:
         0: getstatic     #43                 // Field xaero/common/HudMod.INSTANCE:Lxaero/common/HudMod;
         3: invokevirtual #49                 // Method xaero/common/HudMod.getHudConfigs:()Lxaero/lib/common/config/channel/ConfigChannel;
         6: invokevirtual #53                 // Method xaero/lib/common/config/channel/ConfigChannel.getClientConfigManager:()Lxaero/lib/client/config/ClientConfigManager;
         9: invokevirtual #1265               // Method xaero/lib/client/config/ClientConfigManager.getServerSynced:()Lxaero/lib/client/config/sync/SyncedConfigManager;
        12: invokevirtual #1269               // Method xaero/lib/client/config/sync/SyncedConfigManager.isChannelPresentOnServer:()Z
        15: ifeq          20
        18: iconst_0
        19: ireturn
        20: getstatic     #40                 // Field serverSettings:I
        23: sipush        16384
        26: iand
        27: sipush        16384
        30: if_icmpne     96
        33: invokestatic  #152                // Method net/minecraft/client/Minecraft.getInstance:()Lnet/minecraft/client/Minecraft;
        36: getfield      #1274               // Field net/minecraft/client/Minecraft.level:Lnet/minecraft/client/multiplayer/ClientLevel;
        39: ifnull        100
        42: invokestatic  #1278               // Method xaero/common/minimap/mcworld/MinimapClientWorldDataHelper.getCurrentWorldData:()Lxaero/common/minimap/mcworld/MinimapClientWorldData;
        45: invokevirtual #1284               // Method xaero/common/minimap/mcworld/MinimapClientWorldData.getSyncedRules:()Lxaero/hud/packet/basic/ClientboundRulesPacket;
        48: getfield      #1290               // Field xaero/hud/packet/basic/ClientboundRulesPacket.allowCaveModeOnServer:Z
        51: ifne          69
        54: invokestatic  #152                // Method net/minecraft/client/Minecraft.getInstance:()Lnet/minecraft/client/Minecraft;
        57: getfield      #1274               // Field net/minecraft/client/Minecraft.level:Lnet/minecraft/client/multiplayer/ClientLevel;
        60: invokevirtual #1295               // Method net/minecraft/client/multiplayer/ClientLevel.dimension:()Lnet/minecraft/resources/ResourceKey;
        63: getstatic     #1301               // Field net/minecraft/world/level/Level.NETHER:Lnet/minecraft/resources/ResourceKey;
        66: if_acmpne     96
        69: invokestatic  #1278               // Method xaero/common/minimap/mcworld/MinimapClientWorldDataHelper.getCurrentWorldData:()Lxaero/common/minimap/mcworld/MinimapClientWorldData;
        72: invokevirtual #1284               // Method xaero/common/minimap/mcworld/MinimapClientWorldData.getSyncedRules:()Lxaero/hud/packet/basic/ClientboundRulesPacket;
        75: getfield      #1307               // Field xaero/hud/packet/basic/ClientboundRulesPacket.allowNetherCaveModeOnServer:Z
        78: ifne          100
        81: invokestatic  #152                // Method net/minecraft/client/Minecraft.getInstance:()Lnet/minecraft/client/Minecraft;
        84: getfield      #1274               // Field net/minecraft/client/Minecraft.level:Lnet/minecraft/client/multiplayer/ClientLevel;
        87: invokevirtual #1295               // Method net/minecraft/client/multiplayer/ClientLevel.dimension:()Lnet/minecraft/resources/ResourceKey;
        90: getstatic     #1301               // Field net/minecraft/world/level/Level.NETHER:Lnet/minecraft/resources/ResourceKey;
        93: if_acmpne     100
        96: iconst_1
        97: goto          101
       100: iconst_0
       101: ireturn

  public boolean showWaypointsDisabled();
    Code:
         0: getstatic     #40                 // Field serverSettings:I
         3: ldc_w         #1310               // int 65536
         6: iand
         7: ldc_w         #1310               // int 65536
        10: if_icmpeq     17
        13: iconst_1
        14: goto          18
        17: iconst_0
        18: ireturn

  public boolean deathpointsDisabled();
    Code:
         0: getstatic     #40                 // Field serverSettings:I
         3: ldc_w         #1311               // int 2097152
         6: iand
         7: ifne          14
        10: iconst_1
        11: goto          15
        14: iconst_0
        15: ireturn

  public void resetServerSettings();
    Code:
         0: getstatic     #36                 // Field defaultSettings:I
         3: putstatic     #40                 // Field serverSettings:I
         6: return

  public static void setServerSettings();
    Code:
         0: return

  public static boolean canEditIngameSettings();
    Code:
         0: getstatic     #77                 // Field xaero/hud/minimap/BuiltInHudModules.MINIMAP:Lxaero/hud/module/HudModule;
         3: invokevirtual #83                 // Method xaero/hud/module/HudModule.getCurrentSession:()Lxaero/hud/module/ModuleSession;
         6: checkcast     #89                 // class xaero/hud/minimap/module/MinimapSession
         9: astore_0
        10: aload_0
        11: ifnull        28
        14: aload_0
        15: invokevirtual #162                // Method xaero/hud/minimap/module/MinimapSession.getWorldState:()Lxaero/hud/minimap/world/state/MinimapWorldState;
        18: invokevirtual #166                // Method xaero/hud/minimap/world/state/MinimapWorldState.getAutoWorldPath:()Lxaero/hud/path/XaeroPath;
        21: ifnull        28
        24: iconst_1
        25: goto          29
        28: iconst_0
        29: ireturn

  public xaero.hud.minimap.radar.category.EntityRadarBackwardsCompatibilityConfig getEntityRadarBackwardsCompatibilityConfig();
    Code:
         0: aload_0
         1: getfield      #16                 // Field entityRadarBackwardsCompatibilityConfig:Lxaero/hud/minimap/radar/category/EntityRadarBackwardsCompatibilityConfig;
         4: areturn

  public void resetEntityRadarBackwardsCompatibilityConfig();
    Code:
         0: aload_0
         1: new           #13                 // class xaero/hud/minimap/radar/category/EntityRadarBackwardsCompatibilityConfig
         4: dup
         5: invokespecial #15                 // Method xaero/hud/minimap/radar/category/EntityRadarBackwardsCompatibilityConfig."<init>":()V
         8: putfield      #16                 // Field entityRadarBackwardsCompatibilityConfig:Lxaero/hud/minimap/radar/category/EntityRadarBackwardsCompatibilityConfig;
        11: aload_0
        12: iconst_0
        13: putfield      #931                // Field foundOldRadarSettings:Z
        16: return

  public boolean foundOldRadarSettings();
    Code:
         0: aload_0
         1: getfield      #931                // Field foundOldRadarSettings:Z
         4: ireturn

  public java.lang.String getLoadedWaypointLines();
    Code:
         0: aload_0
         1: getfield      #304                // Field loadedWaypointLines:Ljava/lang/String;
         4: areturn

  public void removeLoadedWaypointLines();
    Code:
         0: aload_0
         1: aconst_null
         2: putfield      #304                // Field loadedWaypointLines:Ljava/lang/String;
         5: return

  static {};
    Code:
         0: new           #102                // class java/util/HashMap
         3: dup
         4: invokespecial #1312               // Method java/util/HashMap."<init>":()V
         7: putstatic     #91                 // Field legacyServerSlimeSeeds:Ljava/util/HashMap;
        10: iconst_5
        11: anewarray     #29                 // class java/lang/String
        14: dup
        15: iconst_0
        16: ldc_w         #1313               // String gui.xaero_off
        19: aastore
        20: dup
        21: iconst_1
        22: ldc_w         #1315               // String gui.xaero_light_block
        25: aastore
        26: dup
        27: iconst_2
        28: ldc_w         #1317               // String gui.xaero_light_sky
        31: aastore
        32: dup
        33: iconst_3
        34: ldc_w         #1319               // String gui.xaero_light_all
        37: aastore
        38: dup
        39: iconst_4
        40: ldc_w         #1321               // String gui.xaero_light_both2
        43: aastore
        44: putstatic     #1323               // Field SHOW_LIGHT_LEVEL_NAMES:[Ljava/lang/String;
        47: iconst_4
        48: newarray       int
        50: dup
        51: iconst_0
        52: bipush        57
        54: iastore
        55: dup
        56: iconst_1
        57: bipush        85
        59: iastore
        60: dup
        61: iconst_2
        62: bipush        113
        64: iastore
        65: dup
        66: iconst_3
        67: sipush        169
        70: iastore
        71: putstatic     #512                // Field OLD_MINIMAP_SIZES:[I
        74: return
}

