Compiled from "MapWriter.java"
public abstract class xaero.map.MapWriter {
  public static final int NO_Y_VALUE = 32767;

  public static final int MAX_TRANSPARENCY_BLEND_DEPTH = 5;

  public static final java.lang.String[] DEFAULT_RESOURCE;

  private int X;

  private int Z;

  private int playerChunkX;

  private int playerChunkZ;

  private int loadDistance;

  private int startTileChunkX;

  private int startTileChunkZ;

  private int endTileChunkX;

  private int endTileChunkZ;

  private int insideX;

  private int insideZ;

  private long updateCounter;

  private int caveStart;

  private int writingLayer;

  private int writtenCaveStart;

  private boolean clearCachedColours;

  private xaero.map.region.MapBlock loadingObject;

  private xaero.map.region.OverlayBuilder overlayBuilder;

  private final net.minecraft.core.BlockPos$MutableBlockPos mutableLocalPos;

  private final net.minecraft.core.BlockPos$MutableBlockPos mutableGlobalPos;

  protected java.lang.ThreadLocal<net.minecraft.util.RandomSource> threadRandomSource;

  private long lastWrite;

  private long lastWriteTry;

  private int workingFrameCount;

  private long framesFreedTime;

  public long writeFreeSinceLastWrite;

  private int writeFreeSizeTiles;

  private int writeFreeFullUpdateTargetTime;

  private xaero.map.MapProcessor mapProcessor;

  private java.util.ArrayList<net.minecraft.world.level.block.state.BlockState> buggedStates;

  private xaero.map.cache.BlockStateShortShapeCache blockStateShortShapeCache;

  private int topH;

  private final xaero.map.misc.CachedFunction<net.minecraft.world.level.block.state.StateHolder<?, ?>, java.lang.Boolean> transparentCache;

  private int firstTransparentStateY;

  private final net.minecraft.core.BlockPos$MutableBlockPos mutableBlockPos3;

  private xaero.map.misc.CachedFunction<net.minecraft.world.level.material.FluidState, net.minecraft.world.level.block.state.BlockState> fluidToBlock;

  private xaero.map.biome.BiomeGetter biomeGetter;

  private java.util.ArrayList<xaero.map.region.MapRegion> regionBuffer;

  private xaero.map.region.MapTileChunk rightChunk;

  private xaero.map.region.MapTileChunk bottomRightChunk;

  private java.util.HashMap<java.lang.String, java.lang.Integer> textureColours;

  private java.util.HashMap<net.minecraft.world.level.block.state.BlockState, java.lang.Integer> blockColours;

  private final it.unimi.dsi.fastutil.objects.Object2IntMap<net.minecraft.world.level.block.state.BlockState> blockTintIndices;

  private long lastLayerSwitch;

  protected java.lang.ThreadLocal<java.util.List<net.minecraft.client.renderer.block.dispatch.BlockStateModelPart>> threadReusableBlockModelPartList;

  private boolean clearTransparencyCache;

  private net.minecraft.world.level.block.state.BlockState lastBlockStateForTextureColor;

  private int lastBlockStateForTextureColorResult;

  public xaero.map.MapWriter(xaero.map.region.OverlayManager, xaero.map.cache.BlockStateShortShapeCache, xaero.map.biome.BiomeGetter);
    Code:
         0: aload_0
         1: invokespecial #3                  // Method java/lang/Object."<init>":()V
         4: aload_0
         5: ldc           #11                 // int 2147483647
         7: putfield      #12                 // Field writingLayer:I
        10: aload_0
        11: ldc           #11                 // int 2147483647
        13: putfield      #18                 // Field writtenCaveStart:I
        16: aload_0
        17: ldc2_w        #21                 // long -1l
        20: putfield      #23                 // Field lastWrite:J
        23: aload_0
        24: ldc2_w        #21                 // long -1l
        27: putfield      #27                 // Field lastWriteTry:J
        30: aload_0
        31: ldc2_w        #21                 // long -1l
        34: putfield      #30                 // Field framesFreedTime:J
        37: aload_0
        38: ldc2_w        #21                 // long -1l
        41: putfield      #33                 // Field writeFreeSinceLastWrite:J
        44: aload_0
        45: new           #36                 // class java/util/ArrayList
        48: dup
        49: invokespecial #38                 // Method java/util/ArrayList."<init>":()V
        52: putfield      #39                 // Field regionBuffer:Ljava/util/ArrayList;
        55: aload_0
        56: aconst_null
        57: putfield      #43                 // Field rightChunk:Lxaero/map/region/MapTileChunk;
        60: aload_0
        61: aconst_null
        62: putfield      #47                 // Field bottomRightChunk:Lxaero/map/region/MapTileChunk;
        65: aload_0
        66: aconst_null
        67: putfield      #50                 // Field lastBlockStateForTextureColor:Lnet/minecraft/world/level/block/state/BlockState;
        70: aload_0
        71: iconst_m1
        72: putfield      #54                 // Field lastBlockStateForTextureColorResult:I
        75: aload_0
        76: invokedynamic #57,  0             // InvokeDynamic #0:get:()Ljava/util/function/Supplier;
        81: invokestatic  #61                 // Method java/lang/ThreadLocal.withInitial:(Ljava/util/function/Supplier;)Ljava/lang/ThreadLocal;
        84: putfield      #67                 // Field threadRandomSource:Ljava/lang/ThreadLocal;
        87: aload_0
        88: new           #71                 // class xaero/map/region/MapBlock
        91: dup
        92: invokespecial #73                 // Method xaero/map/region/MapBlock."<init>":()V
        95: putfield      #74                 // Field loadingObject:Lxaero/map/region/MapBlock;
        98: aload_0
        99: new           #78                 // class java/util/HashMap
       102: dup
       103: invokespecial #80                 // Method java/util/HashMap."<init>":()V
       106: putfield      #81                 // Field textureColours:Ljava/util/HashMap;
       109: aload_0
       110: new           #78                 // class java/util/HashMap
       113: dup
       114: invokespecial #80                 // Method java/util/HashMap."<init>":()V
       117: putfield      #85                 // Field blockColours:Ljava/util/HashMap;
       120: aload_0
       121: new           #88                 // class xaero/map/region/OverlayBuilder
       124: dup
       125: aload_1
       126: invokespecial #90                 // Method xaero/map/region/OverlayBuilder."<init>":(Lxaero/map/region/OverlayManager;)V
       129: putfield      #93                 // Field overlayBuilder:Lxaero/map/region/OverlayBuilder;
       132: aload_0
       133: new           #97                 // class net/minecraft/core/BlockPos$MutableBlockPos
       136: dup
       137: invokespecial #99                 // Method net/minecraft/core/BlockPos$MutableBlockPos."<init>":()V
       140: putfield      #100                // Field mutableLocalPos:Lnet/minecraft/core/BlockPos$MutableBlockPos;
       143: aload_0
       144: new           #97                 // class net/minecraft/core/BlockPos$MutableBlockPos
       147: dup
       148: invokespecial #99                 // Method net/minecraft/core/BlockPos$MutableBlockPos."<init>":()V
       151: putfield      #104                // Field mutableGlobalPos:Lnet/minecraft/core/BlockPos$MutableBlockPos;
       154: aload_0
       155: new           #36                 // class java/util/ArrayList
       158: dup
       159: invokespecial #38                 // Method java/util/ArrayList."<init>":()V
       162: putfield      #107                // Field buggedStates:Ljava/util/ArrayList;
       165: aload_0
       166: aload_2
       167: putfield      #110                // Field blockStateShortShapeCache:Lxaero/map/cache/BlockStateShortShapeCache;
       170: aload_0
       171: new           #114                // class xaero/map/misc/CachedFunction
       174: dup
       175: aload_0
       176: invokedynamic #116,  0            // InvokeDynamic #1:apply:(Lxaero/map/MapWriter;)Ljava/util/function/Function;
       181: invokespecial #120                // Method xaero/map/misc/CachedFunction."<init>":(Ljava/util/function/Function;)V
       184: putfield      #123                // Field transparentCache:Lxaero/map/misc/CachedFunction;
       187: aload_0
       188: new           #97                 // class net/minecraft/core/BlockPos$MutableBlockPos
       191: dup
       192: invokespecial #99                 // Method net/minecraft/core/BlockPos$MutableBlockPos."<init>":()V
       195: putfield      #127                // Field mutableBlockPos3:Lnet/minecraft/core/BlockPos$MutableBlockPos;
       198: aload_0
       199: new           #114                // class xaero/map/misc/CachedFunction
       202: dup
       203: invokedynamic #130,  0            // InvokeDynamic #2:apply:()Ljava/util/function/Function;
       208: invokespecial #120                // Method xaero/map/misc/CachedFunction."<init>":(Ljava/util/function/Function;)V
       211: putfield      #133                // Field fluidToBlock:Lxaero/map/misc/CachedFunction;
       214: aload_0
       215: aload_3
       216: putfield      #136                // Field biomeGetter:Lxaero/map/biome/BiomeGetter;
       219: aload_0
       220: new           #140                // class it/unimi/dsi/fastutil/objects/Object2IntOpenHashMap
       223: dup
       224: invokespecial #142                // Method it/unimi/dsi/fastutil/objects/Object2IntOpenHashMap."<init>":()V
       227: putfield      #143                // Field blockTintIndices:Lit/unimi/dsi/fastutil/objects/Object2IntMap;
       230: aload_0
       231: invokedynamic #147,  0            // InvokeDynamic #3:get:()Ljava/util/function/Supplier;
       236: invokestatic  #61                 // Method java/lang/ThreadLocal.withInitial:(Ljava/util/function/Supplier;)Ljava/lang/ThreadLocal;
       239: putfield      #148                // Field threadReusableBlockModelPartList:Ljava/lang/ThreadLocal;
       242: return

  protected abstract boolean blockStateHasTranslucentRenderType(net.minecraft.world.level.block.state.BlockState);

  private boolean fluidStateHasTranslucentRenderType(net.minecraft.world.level.material.FluidState);
    Code:
         0: invokestatic  #151                // Method net/minecraft/client/Minecraft.getInstance:()Lnet/minecraft/client/Minecraft;
         3: invokevirtual #157                // Method net/minecraft/client/Minecraft.getModelManager:()Lnet/minecraft/client/resources/model/ModelManager;
         6: invokevirtual #161                // Method net/minecraft/client/resources/model/ModelManager.getFluidStateModelSet:()Lnet/minecraft/client/renderer/block/FluidStateModelSet;
         9: astore_2
        10: aload_2
        11: aload_1
        12: invokevirtual #167                // Method net/minecraft/client/renderer/block/FluidStateModelSet.get:(Lnet/minecraft/world/level/material/FluidState;)Lnet/minecraft/client/renderer/block/FluidModel;
        15: astore_3
        16: aload_3
        17: invokevirtual #172                // Method net/minecraft/client/renderer/block/FluidModel.layer:()Lnet/minecraft/client/renderer/chunk/ChunkSectionLayer;
        20: invokevirtual #178                // Method net/minecraft/client/renderer/chunk/ChunkSectionLayer.translucent:()Z
        23: ireturn

  public void onRender(xaero.map.biome.BiomeColorCalculator, xaero.map.region.OverlayManager);
    Code:
         0: invokestatic  #184                // Method java/lang/System.nanoTime:()J
         3: lstore_3
         4: getstatic     #190                // Field xaero/map/WorldMap.crashHandler:Lxaero/map/CrashHandler;
         7: invokevirtual #196                // Method xaero/map/CrashHandler.getCrashedBy:()Ljava/lang/Throwable;
        10: ifnonnull     1293
        13: aload_0
        14: getfield      #202                // Field mapProcessor:Lxaero/map/MapProcessor;
        17: getfield      #206                // Field xaero/map/MapProcessor.renderThreadPauseSync:Ljava/lang/Object;
        20: dup
        21: astore        5
        23: monitorenter
        24: aload_0
        25: getfield      #202                // Field mapProcessor:Lxaero/map/MapProcessor;
        28: invokevirtual #212                // Method xaero/map/MapProcessor.isWritingPaused:()Z
        31: ifne          1279
        34: aload_0
        35: getfield      #202                // Field mapProcessor:Lxaero/map/MapProcessor;
        38: invokevirtual #215                // Method xaero/map/MapProcessor.isWaitingForWorldUpdate:()Z
        41: ifne          1279
        44: aload_0
        45: getfield      #202                // Field mapProcessor:Lxaero/map/MapProcessor;
        48: invokevirtual #218                // Method xaero/map/MapProcessor.getMapSaveLoad:()Lxaero/map/file/MapSaveLoad;
        51: invokevirtual #222                // Method xaero/map/file/MapSaveLoad.isRegionDetectionComplete:()Z
        54: ifeq          1279
        57: aload_0
        58: getfield      #202                // Field mapProcessor:Lxaero/map/MapProcessor;
        61: invokevirtual #227                // Method xaero/map/MapProcessor.isCurrentMultiworldWritable:()Z
        64: ifeq          1279
        67: getstatic     #230                // Field xaero/map/WorldMap.INSTANCE:Lxaero/map/WorldMap;
        70: invokevirtual #234                // Method xaero/map/WorldMap.getConfigs:()Lxaero/lib/common/config/channel/ConfigChannel;
        73: invokevirtual #238                // Method xaero/lib/common/config/channel/ConfigChannel.getClientConfigManager:()Lxaero/lib/client/config/ClientConfigManager;
        76: astore        6
        78: aload         6
        80: getstatic     #244                // Field xaero/map/common/config/option/WorldMapProfiledConfigOptions.LOAD_NEW_CHUNKS:Lxaero/lib/common/config/option/BooleanConfigOption;
        83: invokevirtual #250                // Method xaero/lib/client/config/ClientConfigManager.getEffective:(Lxaero/lib/common/config/option/ConfigOption;)Ljava/lang/Object;
        86: checkcast     #256                // class java/lang/Boolean
        89: invokevirtual #258                // Method java/lang/Boolean.booleanValue:()Z
        92: istore        7
        94: aload         6
        96: getstatic     #261                // Field xaero/map/common/config/option/WorldMapProfiledConfigOptions.UPDATE_CHUNKS:Lxaero/lib/common/config/option/BooleanConfigOption;
        99: invokevirtual #250                // Method xaero/lib/client/config/ClientConfigManager.getEffective:(Lxaero/lib/common/config/option/ConfigOption;)Ljava/lang/Object;
       102: checkcast     #256                // class java/lang/Boolean
       105: invokevirtual #258                // Method java/lang/Boolean.booleanValue:()Z
       108: istore        8
       110: aload_0
       111: getfield      #202                // Field mapProcessor:Lxaero/map/MapProcessor;
       114: invokevirtual #264                // Method xaero/map/MapProcessor.getWorld:()Lnet/minecraft/client/multiplayer/ClientLevel;
       117: ifnull        143
       120: aload_0
       121: getfield      #202                // Field mapProcessor:Lxaero/map/MapProcessor;
       124: invokevirtual #268                // Method xaero/map/MapProcessor.isCurrentMapLocked:()Z
       127: ifne          143
       130: aload_0
       131: getfield      #202                // Field mapProcessor:Lxaero/map/MapProcessor;
       134: invokevirtual #271                // Method xaero/map/MapProcessor.getMapWorld:()Lxaero/map/world/MapWorld;
       137: invokevirtual #275                // Method xaero/map/world/MapWorld.isCacheOnlyMode:()Z
       140: ifeq          147
       143: aload         5
       145: monitorexit
       146: return
       147: aload_0
       148: getfield      #202                // Field mapProcessor:Lxaero/map/MapProcessor;
       151: invokevirtual #280                // Method xaero/map/MapProcessor.getCurrentWorldId:()Ljava/lang/String;
       154: ifnull        1279
       157: aload_0
       158: getfield      #202                // Field mapProcessor:Lxaero/map/MapProcessor;
       161: aload_0
       162: getfield      #202                // Field mapProcessor:Lxaero/map/MapProcessor;
       165: invokevirtual #264                // Method xaero/map/MapProcessor.getWorld:()Lnet/minecraft/client/multiplayer/ClientLevel;
       168: invokevirtual #284                // Method xaero/map/MapProcessor.ignoreWorld:(Lnet/minecraft/world/level/Level;)Z
       171: ifne          1279
       174: iload         8
       176: ifne          200
       179: iload         7
       181: ifne          200
       184: aload_0
       185: getfield      #202                // Field mapProcessor:Lxaero/map/MapProcessor;
       188: invokevirtual #271                // Method xaero/map/MapProcessor.getMapWorld:()Lxaero/map/world/MapWorld;
       191: invokevirtual #288                // Method xaero/map/world/MapWorld.getCurrentDimension:()Lxaero/map/world/MapDimension;
       194: invokevirtual #292                // Method xaero/map/world/MapDimension.isUsingWorldSave:()Z
       197: ifeq          1279
       200: aload_0
       201: getfield      #202                // Field mapProcessor:Lxaero/map/MapProcessor;
       204: getfield      #297                // Field xaero/map/MapProcessor.mainStuffSync:Ljava/lang/Object;
       207: dup
       208: astore        15
       210: monitorenter
       211: aload_0
       212: getfield      #202                // Field mapProcessor:Lxaero/map/MapProcessor;
       215: getfield      #300                // Field xaero/map/MapProcessor.mainWorld:Lnet/minecraft/client/multiplayer/ClientLevel;
       218: aload_0
       219: getfield      #202                // Field mapProcessor:Lxaero/map/MapProcessor;
       222: invokevirtual #264                // Method xaero/map/MapProcessor.getWorld:()Lnet/minecraft/client/multiplayer/ClientLevel;
       225: if_acmpeq     235
       228: aload         15
       230: monitorexit
       231: aload         5
       233: monitorexit
       234: return
       235: aload_0
       236: getfield      #202                // Field mapProcessor:Lxaero/map/MapProcessor;
       239: invokevirtual #264                // Method xaero/map/MapProcessor.getWorld:()Lnet/minecraft/client/multiplayer/ClientLevel;
       242: invokevirtual #304                // Method net/minecraft/client/multiplayer/ClientLevel.dimension:()Lnet/minecraft/resources/ResourceKey;
       245: aload_0
       246: getfield      #202                // Field mapProcessor:Lxaero/map/MapProcessor;
       249: invokevirtual #271                // Method xaero/map/MapProcessor.getMapWorld:()Lxaero/map/world/MapWorld;
       252: invokevirtual #310                // Method xaero/map/world/MapWorld.getCurrentDimensionId:()Lnet/minecraft/resources/ResourceKey;
       255: if_acmpeq     265
       258: aload         15
       260: monitorexit
       261: aload         5
       263: monitorexit
       264: return
       265: aload_0
       266: getfield      #202                // Field mapProcessor:Lxaero/map/MapProcessor;
       269: getfield      #313                // Field xaero/map/MapProcessor.mainPlayerX:D
       272: dstore        9
       274: aload_0
       275: getfield      #202                // Field mapProcessor:Lxaero/map/MapProcessor;
       278: getfield      #317                // Field xaero/map/MapProcessor.mainPlayerY:D
       281: dstore        11
       283: aload_0
       284: getfield      #202                // Field mapProcessor:Lxaero/map/MapProcessor;
       287: getfield      #320                // Field xaero/map/MapProcessor.mainPlayerZ:D
       290: dstore        13
       292: aload         15
       294: monitorexit
       295: goto          306
       298: astore        16
       300: aload         15
       302: monitorexit
       303: aload         16
       305: athrow
       306: invokestatic  #323                // Method xaero/map/core/XaeroWorldMapCore.ensureField:()V
       309: aload_0
       310: getfield      #328                // Field clearTransparencyCache:Z
       313: ifeq          328
       316: aload_0
       317: getfield      #123                // Field transparentCache:Lxaero/map/misc/CachedFunction;
       320: invokevirtual #332                // Method xaero/map/misc/CachedFunction.clear:()V
       323: aload_0
       324: iconst_0
       325: putfield      #328                // Field clearTransparencyCache:Z
       328: aload_0
       329: getfield      #335                // Field endTileChunkX:I
       332: aload_0
       333: getfield      #338                // Field startTileChunkX:I
       336: isub
       337: iconst_1
       338: iadd
       339: istore        15
       341: aload_0
       342: getfield      #341                // Field endTileChunkZ:I
       345: aload_0
       346: getfield      #344                // Field startTileChunkZ:I
       349: isub
       350: iconst_1
       351: iadd
       352: istore        16
       354: aload_0
       355: getfield      #27                 // Field lastWriteTry:J
       358: ldc2_w        #21                 // long -1l
       361: lcmp
       362: ifne          371
       365: iconst_3
       366: istore        15
       368: iconst_3
       369: istore        16
       371: iload         15
       373: iload         16
       375: imul
       376: istore        17
       378: iload         17
       380: iconst_4
       381: imul
       382: iconst_4
       383: imul
       384: istore        18
       386: iload         18
       388: sipush        1000
       391: imul
       392: sipush        1500
       395: idiv
       396: istore        19
       398: bipush        100
       400: iload         19
       402: invokestatic  #349                // Method java/lang/Math.max:(II)I
       405: istore        20
       407: invokestatic  #355                // Method java/lang/System.currentTimeMillis:()J
       410: lstore        21
       412: aload_0
       413: getfield      #23                 // Field lastWrite:J
       416: ldc2_w        #21                 // long -1l
       419: lcmp
       420: ifne          427
       423: lconst_0
       424: goto          434
       427: lload         21
       429: aload_0
       430: getfield      #23                 // Field lastWrite:J
       433: lsub
       434: lstore        23
       436: aload_0
       437: getfield      #27                 // Field lastWriteTry:J
       440: ldc2_w        #21                 // long -1l
       443: lcmp
       444: ifeq          474
       447: aload_0
       448: getfield      #358                // Field writeFreeSizeTiles:I
       451: iload         18
       453: if_icmpne     474
       456: aload_0
       457: getfield      #361                // Field writeFreeFullUpdateTargetTime:I
       460: iload         20
       462: if_icmpne     474
       465: aload_0
       466: getfield      #364                // Field workingFrameCount:I
       469: bipush        30
       471: if_icmple     497
       474: aload_0
       475: lload         21
       477: putfield      #30                 // Field framesFreedTime:J
       480: aload_0
       481: iload         18
       483: putfield      #358                // Field writeFreeSizeTiles:I
       486: aload_0
       487: iload         20
       489: putfield      #361                // Field writeFreeFullUpdateTargetTime:I
       492: aload_0
       493: iconst_0
       494: putfield      #364                // Field workingFrameCount:I
       497: lload         23
       499: aload_0
       500: getfield      #33                 // Field writeFreeSinceLastWrite:J
       503: invokestatic  #367                // Method java/lang/Math.min:(JJ)J
       506: lstore        25
       508: aload_0
       509: getfield      #30                 // Field framesFreedTime:J
       512: ldc2_w        #21                 // long -1l
       515: lcmp
       516: ifeq          528
       519: lload         21
       521: aload_0
       522: getfield      #30                 // Field framesFreedTime:J
       525: lsub
       526: lstore        25
       528: lload         25
       530: iload         18
       532: i2l
       533: lmul
       534: iload         20
       536: i2l
       537: ldiv
       538: ldc2_w        #371                // long 100l
       541: invokestatic  #367                // Method java/lang/Math.min:(JJ)J
       544: lstore        27
       546: aload_0
       547: getfield      #23                 // Field lastWrite:J
       550: ldc2_w        #21                 // long -1l
       553: lcmp
       554: ifeq          564
       557: lload         27
       559: lconst_0
       560: lcmp
       561: ifeq          570
       564: aload_0
       565: lload         21
       567: putfield      #23                 // Field lastWrite:J
       570: lload         27
       572: lconst_0
       573: lcmp
       574: ifeq          866
       577: aload_0
       578: getfield      #30                 // Field framesFreedTime:J
       581: ldc2_w        #21                 // long -1l
       584: lcmp
       585: ifne          853
       588: lload         25
       590: ldc2_w        #373                // long 50l
       593: invokestatic  #367                // Method java/lang/Math.min:(JJ)J
       596: ldc2_w        #375                // long 86960l
       599: lmul
       600: l2i
       601: istore        29
       603: invokestatic  #184                // Method java/lang/System.nanoTime:()J
       606: lstore        30
       608: aload_0
       609: getfield      #202                // Field mapProcessor:Lxaero/map/MapProcessor;
       612: getfield      #377                // Field xaero/map/MapProcessor.worldBiomeRegistry:Lnet/minecraft/core/Registry;
       615: astore        32
       617: iload         7
       619: ifne          638
       622: aload_0
       623: getfield      #202                // Field mapProcessor:Lxaero/map/MapProcessor;
       626: invokevirtual #271                // Method xaero/map/MapProcessor.getMapWorld:()Lxaero/map/world/MapWorld;
       629: invokevirtual #288                // Method xaero/map/world/MapWorld.getCurrentDimension:()Lxaero/map/world/MapDimension;
       632: invokevirtual #292                // Method xaero/map/world/MapDimension.isUsingWorldSave:()Z
       635: ifeq          642
       638: iconst_1
       639: goto          643
       642: iconst_0
       643: istore        33
       645: iload         8
       647: ifne          666
       650: aload_0
       651: getfield      #202                // Field mapProcessor:Lxaero/map/MapProcessor;
       654: invokevirtual #271                // Method xaero/map/MapProcessor.getMapWorld:()Lxaero/map/world/MapWorld;
       657: invokevirtual #288                // Method xaero/map/world/MapWorld.getCurrentDimension:()Lxaero/map/world/MapDimension;
       660: invokevirtual #292                // Method xaero/map/world/MapDimension.isUsingWorldSave:()Z
       663: ifeq          670
       666: iconst_1
       667: goto          671
       670: iconst_0
       671: istore        34
       673: aload_0
       674: getfield      #202                // Field mapProcessor:Lxaero/map/MapProcessor;
       677: invokevirtual #271                // Method xaero/map/MapProcessor.getMapWorld:()Lxaero/map/world/MapWorld;
       680: invokevirtual #381                // Method xaero/map/world/MapWorld.isIgnoreHeightmaps:()Z
       683: istore        35
       685: aload         6
       687: getstatic     #384                // Field xaero/map/common/config/option/WorldMapProfiledConfigOptions.FLOWERS:Lxaero/lib/common/config/option/BooleanConfigOption;
       690: invokevirtual #250                // Method xaero/lib/client/config/ClientConfigManager.getEffective:(Lxaero/lib/common/config/option/ConfigOption;)Ljava/lang/Object;
       693: checkcast     #256                // class java/lang/Boolean
       696: invokevirtual #258                // Method java/lang/Boolean.booleanValue:()Z
       699: istore        36
       701: getstatic     #387                // Field xaero/map/WorldMap.detailed_debug:Z
       704: istore        37
       706: aload         6
       708: getstatic     #390                // Field xaero/map/common/config/option/WorldMapProfiledConfigOptions.CAVE_MODE_DEPTH:Lxaero/lib/common/config/option/RangeConfigOption;
       711: invokevirtual #250                // Method xaero/lib/client/config/ClientConfigManager.getEffective:(Lxaero/lib/common/config/option/ConfigOption;)Ljava/lang/Object;
       714: checkcast     #9                  // class java/lang/Integer
       717: invokevirtual #394                // Method java/lang/Integer.intValue:()I
       720: istore        38
       722: aload_0
       723: getfield      #127                // Field mutableBlockPos3:Lnet/minecraft/core/BlockPos$MutableBlockPos;
       726: astore        39
       728: aload_0
       729: getfield      #202                // Field mapProcessor:Lxaero/map/MapProcessor;
       732: invokevirtual #398                // Method xaero/map/MapProcessor.getWorldBlockTintProvider:()Lxaero/map/biome/BlockTintProvider;
       735: astore        40
       737: new           #402                // class xaero/map/region/MapUpdateFastConfig
       740: dup
       741: invokespecial #404                // Method xaero/map/region/MapUpdateFastConfig."<init>":()V
       744: astore        41
       746: aload_0
       747: getfield      #202                // Field mapProcessor:Lxaero/map/MapProcessor;
       750: invokevirtual #264                // Method xaero/map/MapProcessor.getWorld:()Lnet/minecraft/client/multiplayer/ClientLevel;
       753: astore        42
       755: aload_0
       756: getfield      #202                // Field mapProcessor:Lxaero/map/MapProcessor;
       759: invokevirtual #405                // Method xaero/map/MapProcessor.getWorldBlockRegistry:()Lnet/minecraft/core/Registry;
       762: astore        43
       764: iconst_0
       765: istore        44
       767: iload         44
       769: i2l
       770: lload         27
       772: lcmp
       773: ifge          840
       776: aload_0
       777: aload         42
       779: aload         43
       781: dload         9
       783: dload         11
       785: dload         13
       787: aload         32
       789: aload_1
       790: aload_2
       791: iload         33
       793: iload         34
       795: iload         35
       797: iload         36
       799: iload         37
       801: aload         39
       803: aload         40
       805: iload         38
       807: aload         41
       809: invokevirtual #409                // Method writeMap:(Lnet/minecraft/world/level/Level;Lnet/minecraft/core/Registry;DDDLnet/minecraft/core/Registry;Lxaero/map/biome/BiomeColorCalculator;Lxaero/map/region/OverlayManager;ZZZZZLnet/minecraft/core/BlockPos$MutableBlockPos;Lxaero/map/biome/BlockTintProvider;ILxaero/map/region/MapUpdateFastConfig;)Z
       812: ifeq          818
       815: iinc          44, -1
       818: invokestatic  #184                // Method java/lang/System.nanoTime:()J
       821: lload         30
       823: lsub
       824: iload         29
       826: i2l
       827: lcmp
       828: iflt          834
       831: goto          840
       834: iinc          44, 1
       837: goto          767
       840: aload_0
       841: dup
       842: getfield      #364                // Field workingFrameCount:I
       845: iconst_1
       846: iadd
       847: putfield      #364                // Field workingFrameCount:I
       850: goto          866
       853: aload_0
       854: lload         25
       856: putfield      #33                 // Field writeFreeSinceLastWrite:J
       859: aload_0
       860: ldc2_w        #21                 // long -1l
       863: putfield      #30                 // Field framesFreedTime:J
       866: aload_0
       867: lload         21
       869: putfield      #27                 // Field lastWriteTry:J
       872: aload_0
       873: getfield      #338                // Field startTileChunkX:I
       876: iconst_3
       877: ishr
       878: istore        29
       880: aload_0
       881: getfield      #344                // Field startTileChunkZ:I
       884: iconst_3
       885: ishr
       886: istore        30
       888: aload_0
       889: getfield      #335                // Field endTileChunkX:I
       892: iconst_3
       893: ishr
       894: istore        31
       896: aload_0
       897: getfield      #341                // Field endTileChunkZ:I
       900: iconst_3
       901: ishr
       902: istore        32
       904: iconst_0
       905: istore        33
       907: aload_0
       908: getfield      #202                // Field mapProcessor:Lxaero/map/MapProcessor;
       911: invokevirtual #218                // Method xaero/map/MapProcessor.getMapSaveLoad:()Lxaero/map/file/MapSaveLoad;
       914: invokevirtual #413                // Method xaero/map/file/MapSaveLoad.getNextToLoadByViewing:()Lxaero/map/region/LeveledRegion;
       917: astore        34
       919: aload         34
       921: ifnull        934
       924: aload         34
       926: invokevirtual #417                // Method xaero/map/region/LeveledRegion.shouldAllowAnotherRegionToLoad:()Z
       929: istore        33
       931: goto          937
       934: iconst_1
       935: istore        33
       937: aload_0
       938: getfield      #39                 // Field regionBuffer:Ljava/util/ArrayList;
       941: invokevirtual #422                // Method java/util/ArrayList.clear:()V
       944: aload_0
       945: getfield      #423                // Field playerChunkX:I
       948: bipush        16
       950: isub
       951: istore        35
       953: aload_0
       954: getfield      #426                // Field playerChunkZ:I
       957: bipush        16
       959: isub
       960: istore        36
       962: iload         35
       964: iload         36
       966: iconst_0
       967: iload         35
       969: iload         36
       971: invokestatic  #429                // Method xaero/map/region/LeveledRegion.setComparison:(IIIII)V
       974: iload         29
       976: istore        37
       978: iload         37
       980: iload         31
       982: if_icmpgt     1111
       985: iload         30
       987: istore        38
       989: iload         38
       991: iload         32
       993: if_icmpgt     1105
       996: aload_0
       997: getfield      #202                // Field mapProcessor:Lxaero/map/MapProcessor;
      1000: aload_0
      1001: getfield      #12                 // Field writingLayer:I
      1004: iload         37
      1006: iload         38
      1008: iconst_1
      1009: invokevirtual #433                // Method xaero/map/MapProcessor.getLeafMapRegion:(IIIZ)Lxaero/map/region/MapRegion;
      1012: astore        39
      1014: aload         39
      1016: ifnull        1033
      1019: aload         39
      1021: invokevirtual #437                // Method xaero/map/region/MapRegion.getLoadState:()B
      1024: iconst_2
      1025: if_icmpne     1033
      1028: aload         39
      1030: invokevirtual #443                // Method xaero/map/region/MapRegion.registerVisit:()V
      1033: aload         39
      1035: dup
      1036: astore        40
      1038: monitorenter
      1039: aload         39
      1041: invokevirtual #446                // Method xaero/map/region/MapRegion.isResting:()Z
      1044: ifeq          1085
      1047: iload         33
      1049: ifeq          1085
      1052: aload         39
      1054: invokevirtual #449                // Method xaero/map/region/MapRegion.canRequestReload_unsynced:()Z
      1057: ifeq          1085
      1060: aload         39
      1062: invokevirtual #437                // Method xaero/map/region/MapRegion.getLoadState:()B
      1065: iconst_2
      1066: if_icmpeq     1085
      1069: aload         39
      1071: invokevirtual #452                // Method xaero/map/region/MapRegion.calculateSortingChunkDistance:()V
      1074: bipush        10
      1076: aload_0
      1077: getfield      #39                 // Field regionBuffer:Ljava/util/ArrayList;
      1080: aload         39
      1082: invokestatic  #455                // Method xaero/map/misc/Misc.addToListOfSmallest:(ILjava/util/List;Ljava/lang/Comparable;)V
      1085: aload         40
      1087: monitorexit
      1088: goto          1099
      1091: astore        45
      1093: aload         40
      1095: monitorexit
      1096: aload         45
      1098: athrow
      1099: iinc          38, 1
      1102: goto          989
      1105: iinc          37, 1
      1108: goto          978
      1111: iconst_1
      1112: istore        37
      1114: iconst_0
      1115: istore        38
      1117: iconst_0
      1118: istore        39
      1120: iload         39
      1122: aload_0
      1123: getfield      #39                 // Field regionBuffer:Ljava/util/ArrayList;
      1126: invokevirtual #461                // Method java/util/ArrayList.size:()I
      1129: if_icmpge     1279
      1132: iload         38
      1134: iload         37
      1136: if_icmpge     1279
      1139: aload_0
      1140: getfield      #39                 // Field regionBuffer:Ljava/util/ArrayList;
      1143: iload         39
      1145: invokevirtual #464                // Method java/util/ArrayList.get:(I)Ljava/lang/Object;
      1148: checkcast     #438                // class xaero/map/region/MapRegion
      1151: astore        40
      1153: aload         40
      1155: aload         34
      1157: if_acmpne     1174
      1160: aload_0
      1161: getfield      #39                 // Field regionBuffer:Ljava/util/ArrayList;
      1164: invokevirtual #461                // Method java/util/ArrayList.size:()I
      1167: iconst_1
      1168: if_icmple     1174
      1171: goto          1273
      1174: aload         40
      1176: dup
      1177: astore        41
      1179: monitorenter
      1180: aload         40
      1182: invokevirtual #449                // Method xaero/map/region/MapRegion.canRequestReload_unsynced:()Z
      1185: ifeq          1197
      1188: aload         40
      1190: invokevirtual #437                // Method xaero/map/region/MapRegion.getLoadState:()B
      1193: iconst_2
      1194: if_icmpne     1203
      1197: aload         41
      1199: monitorexit
      1200: goto          1273
      1203: aload         40
      1205: iconst_1
      1206: invokevirtual #467                // Method xaero/map/region/MapRegion.setBeingWritten:(Z)V
      1209: aload_0
      1210: getfield      #202                // Field mapProcessor:Lxaero/map/MapProcessor;
      1213: invokevirtual #218                // Method xaero/map/MapProcessor.getMapSaveLoad:()Lxaero/map/file/MapSaveLoad;
      1216: aload         40
      1218: ldc_w         #471                // String writing
      1221: invokevirtual #473                // Method xaero/map/file/MapSaveLoad.requestLoad:(Lxaero/map/region/MapRegion;Ljava/lang/String;)V
      1224: iload         38
      1226: ifne          1241
      1229: aload_0
      1230: getfield      #202                // Field mapProcessor:Lxaero/map/MapProcessor;
      1233: invokevirtual #218                // Method xaero/map/MapProcessor.getMapSaveLoad:()Lxaero/map/file/MapSaveLoad;
      1236: aload         40
      1238: invokevirtual #477                // Method xaero/map/file/MapSaveLoad.setNextToLoadByViewing:(Lxaero/map/region/LeveledRegion;)V
      1241: iinc          38, 1
      1244: aload         40
      1246: invokevirtual #437                // Method xaero/map/region/MapRegion.getLoadState:()B
      1249: iconst_4
      1250: if_icmpne     1259
      1253: aload         41
      1255: monitorexit
      1256: goto          1279
      1259: aload         41
      1261: monitorexit
      1262: goto          1273
      1265: astore        46
      1267: aload         41
      1269: monitorexit
      1270: aload         46
      1272: athrow
      1273: iinc          39, 1
      1276: goto          1120
      1279: aload         5
      1281: monitorexit
      1282: goto          1293
      1285: astore        47
      1287: aload         5
      1289: monitorexit
      1290: aload         47
      1292: athrow
      1293: goto          1306
      1296: astore        5
      1298: getstatic     #190                // Field xaero/map/WorldMap.crashHandler:Lxaero/map/CrashHandler;
      1301: aload         5
      1303: invokevirtual #483                // Method xaero/map/CrashHandler.setCrashedBy:(Ljava/lang/Throwable;)V
      1306: return
      Exception table:
         from    to  target type
           211   231   298   any
           235   261   298   any
           265   295   298   any
           298   303   298   any
          1039  1088  1091   any
          1091  1096  1091   any
          1180  1200  1265   any
          1203  1256  1265   any
          1259  1262  1265   any
          1265  1270  1265   any
            24   146  1285   any
           147   234  1285   any
           235   264  1285   any
           265  1282  1285   any
          1285  1290  1285   any
             4   146  1296   Class java/lang/Throwable
           147   234  1296   Class java/lang/Throwable
           235   264  1296   Class java/lang/Throwable
           265  1293  1296   Class java/lang/Throwable

  private int getWriteDistance();
    Code:
         0: aload_0
         1: getfield      #202                // Field mapProcessor:Lxaero/map/MapProcessor;
         4: invokevirtual #271                // Method xaero/map/MapProcessor.getMapWorld:()Lxaero/map/world/MapWorld;
         7: invokevirtual #288                // Method xaero/map/world/MapWorld.getCurrentDimension:()Lxaero/map/world/MapDimension;
        10: astore_1
        11: aload_1
        12: ifnull        27
        15: aload_1
        16: invokevirtual #292                // Method xaero/map/world/MapDimension.isUsingWorldSave:()Z
        19: ifeq          27
        22: ldc           #11                 // int 2147483647
        24: goto          48
        27: getstatic     #230                // Field xaero/map/WorldMap.INSTANCE:Lxaero/map/WorldMap;
        30: invokevirtual #234                // Method xaero/map/WorldMap.getConfigs:()Lxaero/lib/common/config/channel/ConfigChannel;
        33: invokevirtual #238                // Method xaero/lib/common/config/channel/ConfigChannel.getClientConfigManager:()Lxaero/lib/client/config/ClientConfigManager;
        36: getstatic     #487                // Field xaero/map/common/config/option/WorldMapProfiledConfigOptions.WRITING_DISTANCE:Lxaero/lib/common/config/option/RangeConfigOption;
        39: invokevirtual #250                // Method xaero/lib/client/config/ClientConfigManager.getEffective:(Lxaero/lib/common/config/option/ConfigOption;)Ljava/lang/Object;
        42: checkcast     #9                  // class java/lang/Integer
        45: invokevirtual #394                // Method java/lang/Integer.intValue:()I
        48: istore_2
        49: iload_2
        50: ifge          56
        53: ldc           #11                 // int 2147483647
        55: istore_2
        56: iload_2
        57: bipush        32
        59: invokestatic  #151                // Method net/minecraft/client/Minecraft.getInstance:()Lnet/minecraft/client/Minecraft;
        62: getfield      #490                // Field net/minecraft/client/Minecraft.options:Lnet/minecraft/client/Options;
        65: invokevirtual #494                // Method net/minecraft/client/Options.renderDistance:()Lnet/minecraft/client/OptionInstance;
        68: invokevirtual #500                // Method net/minecraft/client/OptionInstance.get:()Ljava/lang/Object;
        71: checkcast     #9                  // class java/lang/Integer
        74: invokevirtual #394                // Method java/lang/Integer.intValue:()I
        77: invokestatic  #505                // Method java/lang/Math.min:(II)I
        80: invokestatic  #505                // Method java/lang/Math.min:(II)I
        83: ireturn

  public boolean writeMap(net.minecraft.world.level.Level, net.minecraft.core.Registry<net.minecraft.world.level.block.Block>, double, double, double, net.minecraft.core.Registry<net.minecraft.world.level.biome.Biome>, xaero.map.biome.BiomeColorCalculator, xaero.map.region.OverlayManager, boolean, boolean, boolean, boolean, boolean, net.minecraft.core.BlockPos$MutableBlockPos, xaero.map.biome.BlockTintProvider, int, xaero.map.region.MapUpdateFastConfig);
    Code:
         0: iload         12
         2: ifeq          27
         5: iload         13
         7: ifeq          23
        10: aload_0
        11: getfield      #507                // Field updateCounter:J
        14: ldc2_w        #510                // long 5l
        17: lrem
        18: lconst_0
        19: lcmp
        20: ifeq          27
        23: iconst_1
        24: goto          28
        27: iconst_0
        28: istore        21
        30: aload_1
        31: dup
        32: astore        22
        34: monitorenter
        35: aload_0
        36: getfield      #512                // Field insideX:I
        39: ifne          302
        42: aload_0
        43: getfield      #515                // Field insideZ:I
        46: ifne          302
        49: aload_0
        50: getfield      #518                // Field X:I
        53: ifne          71
        56: aload_0
        57: getfield      #521                // Field Z:I
        60: ifne          71
        63: aload_0
        64: aload_0
        65: getfield      #523                // Field caveStart:I
        68: putfield      #18                 // Field writtenCaveStart:I
        71: aload_0
        72: getfield      #202                // Field mapProcessor:Lxaero/map/MapProcessor;
        75: invokevirtual #526                // Method xaero/map/MapProcessor.updateCaveStart:()V
        78: aload_0
        79: getfield      #202                // Field mapProcessor:Lxaero/map/MapProcessor;
        82: invokevirtual #529                // Method xaero/map/MapProcessor.getCurrentCaveLayer:()I
        85: istore        23
        87: aload_0
        88: getfield      #12                 // Field writingLayer:I
        91: iload         23
        93: if_icmpeq     124
        96: invokestatic  #355                // Method java/lang/System.currentTimeMillis:()J
        99: aload_0
       100: getfield      #532                // Field lastLayerSwitch:J
       103: lsub
       104: ldc2_w        #535                // long 300l
       107: lcmp
       108: ifle          124
       111: aload_0
       112: iload         23
       114: putfield      #12                 // Field writingLayer:I
       117: aload_0
       118: invokestatic  #355                // Method java/lang/System.currentTimeMillis:()J
       121: putfield      #532                // Field lastLayerSwitch:J
       124: aload_0
       125: aload_0
       126: invokevirtual #537                // Method getWriteDistance:()I
       129: putfield      #540                // Field loadDistance:I
       132: aload_0
       133: getfield      #12                 // Field writingLayer:I
       136: ldc           #11                 // int 2147483647
       138: if_icmpeq     169
       141: invokestatic  #151                // Method net/minecraft/client/Minecraft.getInstance:()Lnet/minecraft/client/Minecraft;
       144: getfield      #543                // Field net/minecraft/client/Minecraft.gui:Lnet/minecraft/client/gui/Gui;
       147: invokevirtual #547                // Method net/minecraft/client/gui/Gui.screen:()Lnet/minecraft/client/gui/screens/Screen;
       150: instanceof    #553                // class xaero/map/gui/GuiMap
       153: ifne          169
       156: aload_0
       157: bipush        16
       159: aload_0
       160: getfield      #540                // Field loadDistance:I
       163: invokestatic  #505                // Method java/lang/Math.min:(II)I
       166: putfield      #540                // Field loadDistance:I
       169: aload_0
       170: aload_0
       171: getfield      #202                // Field mapProcessor:Lxaero/map/MapProcessor;
       174: invokevirtual #271                // Method xaero/map/MapProcessor.getMapWorld:()Lxaero/map/world/MapWorld;
       177: invokevirtual #288                // Method xaero/map/world/MapWorld.getCurrentDimension:()Lxaero/map/world/MapDimension;
       180: invokevirtual #555                // Method xaero/map/world/MapDimension.getLayeredMapRegions:()Lxaero/map/region/LayeredRegionManager;
       183: aload_0
       184: getfield      #12                 // Field writingLayer:I
       187: invokevirtual #559                // Method xaero/map/region/LayeredRegionManager.getLayer:(I)Lxaero/map/region/MapLayer;
       190: invokevirtual #565                // Method xaero/map/region/MapLayer.getCaveStart:()I
       193: putfield      #523                // Field caveStart:I
       196: aload_0
       197: getfield      #523                // Field caveStart:I
       200: aload_0
       201: getfield      #18                 // Field writtenCaveStart:I
       204: if_icmpeq     219
       207: aload_0
       208: iconst_4
       209: aload_0
       210: getfield      #540                // Field loadDistance:I
       213: invokestatic  #505                // Method java/lang/Math.min:(II)I
       216: putfield      #540                // Field loadDistance:I
       219: aload_0
       220: dload_3
       221: invokestatic  #570                // Method java/lang/Math.floor:(D)D
       224: d2i
       225: iconst_4
       226: ishr
       227: putfield      #423                // Field playerChunkX:I
       230: aload_0
       231: dload         7
       233: invokestatic  #570                // Method java/lang/Math.floor:(D)D
       236: d2i
       237: iconst_4
       238: ishr
       239: putfield      #426                // Field playerChunkZ:I
       242: aload_0
       243: aload_0
       244: getfield      #423                // Field playerChunkX:I
       247: aload_0
       248: getfield      #540                // Field loadDistance:I
       251: isub
       252: iconst_2
       253: ishr
       254: putfield      #338                // Field startTileChunkX:I
       257: aload_0
       258: aload_0
       259: getfield      #426                // Field playerChunkZ:I
       262: aload_0
       263: getfield      #540                // Field loadDistance:I
       266: isub
       267: iconst_2
       268: ishr
       269: putfield      #344                // Field startTileChunkZ:I
       272: aload_0
       273: aload_0
       274: getfield      #423                // Field playerChunkX:I
       277: aload_0
       278: getfield      #540                // Field loadDistance:I
       281: iadd
       282: iconst_2
       283: ishr
       284: putfield      #335                // Field endTileChunkX:I
       287: aload_0
       288: aload_0
       289: getfield      #426                // Field playerChunkZ:I
       292: aload_0
       293: getfield      #540                // Field loadDistance:I
       296: iadd
       297: iconst_2
       298: ishr
       299: putfield      #341                // Field endTileChunkZ:I
       302: aload_0
       303: getfield      #338                // Field startTileChunkX:I
       306: aload_0
       307: getfield      #518                // Field X:I
       310: iadd
       311: istore        23
       313: aload_0
       314: getfield      #344                // Field startTileChunkZ:I
       317: aload_0
       318: getfield      #521                // Field Z:I
       321: iadd
       322: istore        24
       324: iload         23
       326: bipush        7
       328: iand
       329: istore        25
       331: iload         24
       333: bipush        7
       335: iand
       336: istore        26
       338: iload         23
       340: iconst_4
       341: imul
       342: aload_0
       343: getfield      #512                // Field insideX:I
       346: iadd
       347: istore        27
       349: iload         24
       351: iconst_4
       352: imul
       353: aload_0
       354: getfield      #515                // Field insideZ:I
       357: iadd
       358: istore        28
       360: aload_0
       361: aload_1
       362: aload_2
       363: aload_0
       364: getfield      #540                // Field loadDistance:I
       367: iload         21
       369: aload         9
       371: aload         11
       373: iload         12
       375: iload         13
       377: iload         14
       379: iload         15
       381: iload         16
       383: aload         17
       385: aload         18
       387: iload         19
       389: aload_0
       390: getfield      #523                // Field caveStart:I
       393: aload_0
       394: getfield      #12                 // Field writingLayer:I
       397: iload         23
       399: iload         24
       401: iload         25
       403: iload         26
       405: iload         27
       407: iload         28
       409: aload         20
       411: invokevirtual #574                // Method writeChunk:(Lnet/minecraft/world/level/Level;Lnet/minecraft/core/Registry;IZLnet/minecraft/core/Registry;Lxaero/map/region/OverlayManager;ZZZZZLnet/minecraft/core/BlockPos$MutableBlockPos;Lxaero/map/biome/BlockTintProvider;IIIIIIIIILxaero/map/region/MapUpdateFastConfig;)Z
       414: istore        29
       416: iload         29
       418: ifeq          455
       421: iload         27
       423: aload_0
       424: getfield      #423                // Field playerChunkX:I
       427: isub
       428: invokestatic  #578                // Method java/lang/Math.abs:(I)I
       431: bipush        8
       433: if_icmpgt     451
       436: iload         28
       438: aload_0
       439: getfield      #426                // Field playerChunkZ:I
       442: isub
       443: invokestatic  #578                // Method java/lang/Math.abs:(I)I
       446: bipush        8
       448: if_icmple     455
       451: iconst_1
       452: goto          456
       455: iconst_0
       456: aload         22
       458: monitorexit
       459: ireturn
       460: astore        30
       462: aload         22
       464: monitorexit
       465: aload         30
       467: athrow
      Exception table:
         from    to  target type
            35   459   460   any
           460   465   460   any

  public boolean writeChunk(net.minecraft.world.level.Level, net.minecraft.core.Registry<net.minecraft.world.level.block.Block>, int, boolean, net.minecraft.core.Registry<net.minecraft.world.level.biome.Biome>, xaero.map.region.OverlayManager, boolean, boolean, boolean, boolean, boolean, net.minecraft.core.BlockPos$MutableBlockPos, xaero.map.biome.BlockTintProvider, int, int, int, int, int, int, int, int, int, xaero.map.region.MapUpdateFastConfig);
    Code:
         0: iload         17
         2: iconst_3
         3: ishr
         4: istore        24
         6: iload         18
         8: iconst_3
         9: ishr
        10: istore        25
        12: aconst_null
        13: astore        26
        15: aload_0
        16: aconst_null
        17: putfield      #43                 // Field rightChunk:Lxaero/map/region/MapTileChunk;
        20: aconst_null
        21: astore        27
        23: aload_0
        24: aconst_null
        25: putfield      #47                 // Field bottomRightChunk:Lxaero/map/region/MapTileChunk;
        28: aload_1
        29: invokevirtual #582                // Method net/minecraft/world/level/Level.getMinY:()I
        32: istore        28
        34: aload_1
        35: invokevirtual #587                // Method net/minecraft/world/level/Level.getMaxY:()I
        38: iconst_1
        39: iadd
        40: istore        29
        42: aload_0
        43: getfield      #202                // Field mapProcessor:Lxaero/map/MapProcessor;
        46: iload         16
        48: iload         24
        50: iload         25
        52: iconst_1
        53: invokevirtual #433                // Method xaero/map/MapProcessor.getLeafMapRegion:(IIIZ)Lxaero/map/region/MapRegion;
        56: astore        30
        58: iconst_1
        59: istore        31
        61: aload         30
        63: getfield      #590                // Field xaero/map/region/MapRegion.writerThreadPauseSync:Ljava/lang/Object;
        66: dup
        67: astore        32
        69: monitorenter
        70: aload         30
        72: invokevirtual #593                // Method xaero/map/region/MapRegion.isWritingPaused:()Z
        75: ifne          1792
        78: iconst_0
        79: istore        35
        81: aload         30
        83: dup
        84: astore        36
        86: monitorenter
        87: aload         30
        89: invokevirtual #437                // Method xaero/map/region/MapRegion.getLoadState:()B
        92: iconst_2
        93: if_icmpne     100
        96: iconst_1
        97: goto          101
       100: iconst_0
       101: istore        34
       103: iload         34
       105: ifeq          113
       108: aload         30
       110: invokevirtual #443                // Method xaero/map/region/MapRegion.registerVisit:()V
       113: aload         30
       115: invokevirtual #446                // Method xaero/map/region/MapRegion.isResting:()Z
       118: istore        33
       120: iload         33
       122: ifeq          223
       125: aload         30
       127: iconst_1
       128: invokevirtual #467                // Method xaero/map/region/MapRegion.setBeingWritten:(Z)V
       131: aload         30
       133: iload         19
       135: iload         20
       137: invokevirtual #594                // Method xaero/map/region/MapRegion.getChunk:(II)Lxaero/map/region/MapTileChunk;
       140: astore        26
       142: iload         34
       144: ifeq          192
       147: aload         26
       149: ifnonnull     192
       152: aload         30
       154: iload         19
       156: iload         20
       158: new           #347                // class xaero/map/region/MapTileChunk
       161: dup
       162: aload         30
       164: iload         17
       166: iload         18
       168: invokespecial #598                // Method xaero/map/region/MapTileChunk."<init>":(Lxaero/map/region/MapRegion;II)V
       171: dup
       172: astore        26
       174: invokevirtual #601                // Method xaero/map/region/MapRegion.setChunk:(IILxaero/map/region/MapTileChunk;)V
       177: aload         26
       179: iconst_2
       180: invokevirtual #605                // Method xaero/map/region/MapTileChunk.setLoadState:(B)V
       183: aload         30
       185: iconst_0
       186: invokevirtual #609                // Method xaero/map/region/MapRegion.setAllCachePrepared:(Z)V
       189: iconst_1
       190: istore        35
       192: aload         30
       194: invokevirtual #612                // Method xaero/map/region/MapRegion.isNormalMapData:()Z
       197: ifne          223
       200: aload         30
       202: invokevirtual #615                // Method xaero/map/region/MapRegion.getDim:()Lxaero/map/world/MapDimension;
       205: invokevirtual #555                // Method xaero/map/world/MapDimension.getLayeredMapRegions:()Lxaero/map/region/LayeredRegionManager;
       208: aload_0
       209: aload         30
       211: iload         24
       213: iload         25
       215: invokedynamic #618,  0            // InvokeDynamic #4:accept:(Lxaero/map/MapWriter;Lxaero/map/region/MapRegion;II)Ljava/util/function/BiConsumer;
       220: invokevirtual #622                // Method xaero/map/region/LayeredRegionManager.applyToEachLoadedLayer:(Ljava/util/function/BiConsumer;)V
       223: aload         36
       225: monitorexit
       226: goto          237
       229: astore        37
       231: aload         36
       233: monitorexit
       234: aload         37
       236: athrow
       237: iload         33
       239: ifeq          1789
       242: iload         34
       244: ifeq          1789
       247: aload         26
       249: ifnull        1535
       252: aload         26
       254: invokevirtual #626                // Method xaero/map/region/MapTileChunk.getLoadState:()I
       257: iconst_2
       258: if_icmpne     1535
       261: aload         26
       263: invokevirtual #628                // Method xaero/map/region/MapTileChunk.getLeafTexture:()Lxaero/map/region/texture/LeafRegionTexture;
       266: invokevirtual #632                // Method xaero/map/region/texture/LeafRegionTexture.shouldUpload:()Z
       269: ifne          1471
       272: iload         15
       274: ldc           #11                 // int 2147483647
       276: if_icmpeq     283
       279: iconst_1
       280: goto          284
       283: iconst_0
       284: istore        36
       286: iload         15
       288: ldc_w         #637                // int -2147483648
       291: if_icmpne     298
       294: iconst_1
       295: goto          299
       298: iconst_0
       299: istore        37
       301: iload         28
       303: istore        38
       305: iload         36
       307: ifeq          335
       310: iload         37
       312: ifne          335
       315: iload         15
       317: iconst_1
       318: iadd
       319: iload         14
       321: isub
       322: istore        38
       324: iload         38
       326: iload         28
       328: if_icmpge     335
       331: iload         28
       333: istore        38
       335: iload         21
       337: aload_0
       338: getfield      #423                // Field playerChunkX:I
       341: iload_3
       342: isub
       343: if_icmplt     1471
       346: iload         21
       348: aload_0
       349: getfield      #423                // Field playerChunkX:I
       352: iload_3
       353: iadd
       354: if_icmpgt     1471
       357: iload         22
       359: aload_0
       360: getfield      #426                // Field playerChunkZ:I
       363: iload_3
       364: isub
       365: if_icmplt     1471
       368: iload         22
       370: aload_0
       371: getfield      #426                // Field playerChunkZ:I
       374: iload_3
       375: iadd
       376: if_icmpgt     1471
       379: aload_1
       380: iload         21
       382: iload         22
       384: getstatic     #638                // Field net/minecraft/world/level/chunk/status/ChunkStatus.FULL:Lnet/minecraft/world/level/chunk/status/ChunkStatus;
       387: iconst_0
       388: invokevirtual #644                // Method net/minecraft/world/level/Level.getChunk:(IILnet/minecraft/world/level/chunk/status/ChunkStatus;Z)Lnet/minecraft/world/level/chunk/ChunkAccess;
       391: checkcast     #647                // class net/minecraft/world/level/chunk/LevelChunk
       394: astore        39
       396: aload         26
       398: aload_0
       399: getfield      #512                // Field insideX:I
       402: aload_0
       403: getfield      #515                // Field insideZ:I
       406: invokevirtual #649                // Method xaero/map/region/MapTileChunk.getTile:(II)Lxaero/map/region/MapTile;
       409: astore        40
       411: iconst_0
       412: istore        41
       414: aload         39
       416: ifnull        465
       419: aload         40
       421: ifnull        461
       424: aload         40
       426: invokevirtual #653                // Method xaero/map/region/MapTile.getWrittenCaveStart:()I
       429: iload         15
       431: if_icmpne     461
       434: aload         40
       436: invokevirtual #658                // Method xaero/map/region/MapTile.getWrittenCaveDepth:()I
       439: iload         14
       441: if_icmpne     461
       444: getstatic     #661                // Field xaero/map/core/XaeroWorldMapCore.chunkCleanField:Ljava/lang/reflect/Field;
       447: aload         39
       449: invokevirtual #665                // Method java/lang/reflect/Field.get:(Ljava/lang/Object;)Ljava/lang/Object;
       452: checkcast     #256                // class java/lang/Boolean
       455: invokevirtual #258                // Method java/lang/Boolean.booleanValue:()Z
       458: ifne          465
       461: iconst_1
       462: goto          466
       465: iconst_0
       466: istore        41
       468: goto          483
       471: astore        42
       473: new           #674                // class java/lang/RuntimeException
       476: dup
       477: aload         42
       479: invokespecial #676                // Method java/lang/RuntimeException."<init>":(Ljava/lang/Throwable;)V
       482: athrow
       483: iload         41
       485: ifeq          1471
       488: aload         39
       490: instanceof    #678                // class net/minecraft/world/level/chunk/EmptyLevelChunk
       493: ifne          1471
       496: iconst_0
       497: istore        42
       499: iconst_m1
       500: istore        43
       502: iload         43
       504: iconst_2
       505: if_icmpge     577
       508: iconst_m1
       509: istore        44
       511: iload         44
       513: iconst_2
       514: if_icmpge     571
       517: iload         43
       519: ifne          530
       522: iload         44
       524: ifne          530
       527: goto          565
       530: aload_1
       531: iload         21
       533: iload         43
       535: iadd
       536: iload         22
       538: iload         44
       540: iadd
       541: invokevirtual #680                // Method net/minecraft/world/level/Level.getChunk:(II)Lnet/minecraft/world/level/chunk/LevelChunk;
       544: astore        45
       546: aload         45
       548: ifnull        559
       551: aload         45
       553: instanceof    #678                // class net/minecraft/world/level/chunk/EmptyLevelChunk
       556: ifeq          565
       559: iconst_1
       560: istore        42
       562: goto          577
       565: iinc          44, 1
       568: goto          511
       571: iinc          43, 1
       574: goto          502
       577: iload         42
       579: ifne          1471
       582: aload         40
       584: ifnonnull     592
       587: iload         7
       589: ifne          627
       592: aload         40
       594: ifnull        1471
       597: iload         8
       599: ifeq          1471
       602: iload         4
       604: ifeq          627
       607: aload         40
       609: invokevirtual #653                // Method xaero/map/region/MapTile.getWrittenCaveStart:()I
       612: iload         15
       614: if_icmpne     627
       617: aload         40
       619: invokevirtual #658                // Method xaero/map/region/MapTile.getWrittenCaveDepth:()I
       622: iload         14
       624: if_icmpeq     1471
       627: iconst_0
       628: istore        31
       630: aload         40
       632: ifnonnull     664
       635: aload_0
       636: getfield      #202                // Field mapProcessor:Lxaero/map/MapProcessor;
       639: invokevirtual #683                // Method xaero/map/MapProcessor.getTilePool:()Lxaero/map/pool/MapTilePool;
       642: aload_0
       643: getfield      #202                // Field mapProcessor:Lxaero/map/MapProcessor;
       646: invokevirtual #687                // Method xaero/map/MapProcessor.getCurrentDimension:()Ljava/lang/String;
       649: iload         21
       651: iload         22
       653: invokevirtual #689                // Method xaero/map/pool/MapTilePool.get:(Ljava/lang/String;II)Lxaero/map/region/MapTile;
       656: astore        40
       658: aload         26
       660: iconst_1
       661: invokevirtual #694                // Method xaero/map/region/MapTileChunk.setChanged:(Z)V
       664: aload         26
       666: iconst_0
       667: iconst_m1
       668: aload_0
       669: getfield      #202                // Field mapProcessor:Lxaero/map/MapProcessor;
       672: iconst_0
       673: invokevirtual #697                // Method xaero/map/region/MapTileChunk.getNeighbourTileChunk:(IILxaero/map/MapProcessor;Z)Lxaero/map/region/MapTileChunk;
       676: astore        43
       678: aload         26
       680: iconst_m1
       681: iconst_m1
       682: aload_0
       683: getfield      #202                // Field mapProcessor:Lxaero/map/MapProcessor;
       686: iconst_0
       687: invokevirtual #697                // Method xaero/map/region/MapTileChunk.getNeighbourTileChunk:(IILxaero/map/MapProcessor;Z)Lxaero/map/region/MapTileChunk;
       690: astore        44
       692: aload         26
       694: iconst_m1
       695: iconst_0
       696: aload_0
       697: getfield      #202                // Field mapProcessor:Lxaero/map/MapProcessor;
       700: iconst_0
       701: invokevirtual #697                // Method xaero/map/region/MapTileChunk.getNeighbourTileChunk:(IILxaero/map/MapProcessor;Z)Lxaero/map/region/MapTileChunk;
       704: astore        45
       706: aload_0
       707: aload         39
       709: bipush        64
       711: invokevirtual #701                // Method getSectionBasedHeight:(Lnet/minecraft/world/level/chunk/LevelChunk;I)I
       714: istore        46
       716: getstatic     #705                // Field net/minecraft/world/level/levelgen/Heightmap$Types.WORLD_SURFACE:Lnet/minecraft/world/level/levelgen/Heightmap$Types;
       719: astore        47
       721: aload_0
       722: getfield      #515                // Field insideZ:I
       725: iconst_3
       726: if_icmpge     747
       729: aload         26
       731: aload_0
       732: getfield      #512                // Field insideX:I
       735: aload_0
       736: getfield      #515                // Field insideZ:I
       739: iconst_1
       740: iadd
       741: invokevirtual #649                // Method xaero/map/region/MapTileChunk.getTile:(II)Lxaero/map/region/MapTile;
       744: goto          748
       747: aconst_null
       748: astore        48
       750: aload_0
       751: getfield      #512                // Field insideX:I
       754: iconst_3
       755: if_icmpge     776
       758: aload         26
       760: aload_0
       761: getfield      #512                // Field insideX:I
       764: iconst_1
       765: iadd
       766: aload_0
       767: getfield      #515                // Field insideZ:I
       770: invokevirtual #649                // Method xaero/map/region/MapTileChunk.getTile:(II)Lxaero/map/region/MapTile;
       773: goto          777
       776: aconst_null
       777: astore        49
       779: iconst_0
       780: istore        50
       782: iconst_0
       783: istore        51
       785: iconst_0
       786: istore        52
       788: iload         52
       790: bipush        16
       792: if_icmpge     1397
       795: iconst_0
       796: istore        53
       798: iload         53
       800: bipush        16
       802: if_icmpge     1391
       805: aload         39
       807: aload         47
       809: iload         52
       811: iload         53
       813: invokevirtual #711                // Method net/minecraft/world/level/chunk/LevelChunk.getHeight:(Lnet/minecraft/world/level/levelgen/Heightmap$Types;II)I
       816: istore        54
       818: iload         36
       820: ifeq          835
       823: iload         37
       825: ifne          835
       828: iload         15
       830: istore        55
       832: goto          858
       835: iload         9
       837: ifne          847
       840: iload         54
       842: iload         28
       844: if_icmpge     854
       847: iload         46
       849: istore        55
       851: goto          858
       854: iload         54
       856: istore        55
       858: iload         55
       860: iload         29
       862: if_icmplt     871
       865: iload         29
       867: iconst_1
       868: isub
       869: istore        55
       871: aload         40
       873: invokevirtual #715                // Method xaero/map/region/MapTile.isLoaded:()Z
       876: ifeq          891
       879: aload         40
       881: iload         52
       883: iload         53
       885: invokevirtual #718                // Method xaero/map/region/MapTile.getBlock:(II)Lxaero/map/region/MapBlock;
       888: goto          892
       891: aconst_null
       892: astore        56
       894: aload_0
       895: aload_1
       896: aload_2
       897: aload_0
       898: getfield      #74                 // Field loadingObject:Lxaero/map/region/MapBlock;
       901: aload         56
       903: aload         39
       905: iload         52
       907: iload         53
       909: iload         55
       911: iload         38
       913: iload         36
       915: iload         37
       917: iload         54
       919: aload         40
       921: invokevirtual #722                // Method xaero/map/region/MapTile.wasWrittenOnce:()Z
       924: iload         9
       926: aload         5
       928: iload         10
       930: iload         28
       932: aload         12
       934: invokevirtual #725                // Method loadPixel:(Lnet/minecraft/world/level/Level;Lnet/minecraft/core/Registry;Lxaero/map/region/MapBlock;Lxaero/map/region/MapBlock;Lnet/minecraft/world/level/chunk/LevelChunk;IIIIZZIZZLnet/minecraft/core/Registry;ZILnet/minecraft/core/BlockPos$MutableBlockPos;)V
       937: aload_0
       938: getfield      #74                 // Field loadingObject:Lxaero/map/region/MapBlock;
       941: iload         52
       943: iload         53
       945: aload         40
       947: aload         26
       949: aload         43
       951: aload         44
       953: aload         45
       955: aload_0
       956: getfield      #74                 // Field loadingObject:Lxaero/map/region/MapBlock;
       959: aload_0
       960: getfield      #110                // Field blockStateShortShapeCache:Lxaero/map/cache/BlockStateShortShapeCache;
       963: aload         23
       965: invokevirtual #729                // Method xaero/map/region/MapBlock.getEffectiveHeight:(Lxaero/map/cache/BlockStateShortShapeCache;Lxaero/map/region/MapUpdateFastConfig;)I
       968: iconst_1
       969: aload_0
       970: getfield      #110                // Field blockStateShortShapeCache:Lxaero/map/cache/BlockStateShortShapeCache;
       973: aload         23
       975: invokevirtual #733                // Method xaero/map/region/MapBlock.fixHeightType:(IILxaero/map/region/MapTile;Lxaero/map/region/MapTileChunk;Lxaero/map/region/MapTileChunk;Lxaero/map/region/MapTileChunk;Lxaero/map/region/MapTileChunk;IZLxaero/map/cache/BlockStateShortShapeCache;Lxaero/map/region/MapUpdateFastConfig;)V
       978: aload_0
       979: getfield      #74                 // Field loadingObject:Lxaero/map/region/MapBlock;
       982: aload         56
       984: invokevirtual #737                // Method xaero/map/region/MapBlock.equalsSlopesExcluded:(Lxaero/map/region/MapBlock;)Z
       987: istore        57
       989: aload_0
       990: getfield      #74                 // Field loadingObject:Lxaero/map/region/MapBlock;
       993: aload         56
       995: iload         57
       997: invokevirtual #741                // Method xaero/map/region/MapBlock.equals:(Lxaero/map/region/MapBlock;Z)Z
      1000: istore        58
      1002: iload         58
      1004: ifne          1385
      1007: aload_0
      1008: getfield      #74                 // Field loadingObject:Lxaero/map/region/MapBlock;
      1011: astore        59
      1013: aload         40
      1015: iload         52
      1017: iload         53
      1019: aload         59
      1021: invokevirtual #745                // Method xaero/map/region/MapTile.setBlock:(IILxaero/map/region/MapBlock;)V
      1024: aload         56
      1026: ifnull        1038
      1029: aload_0
      1030: aload         56
      1032: putfield      #74                 // Field loadingObject:Lxaero/map/region/MapBlock;
      1035: goto          1049
      1038: aload_0
      1039: new           #71                 // class xaero/map/region/MapBlock
      1042: dup
      1043: invokespecial #73                 // Method xaero/map/region/MapBlock."<init>":()V
      1046: putfield      #74                 // Field loadingObject:Lxaero/map/region/MapBlock;
      1049: iload         57
      1051: ifne          1385
      1054: aload         26
      1056: iconst_1
      1057: invokevirtual #694                // Method xaero/map/region/MapTileChunk.setChanged:(Z)V
      1060: iload         53
      1062: bipush        15
      1064: if_icmpne     1071
      1067: iconst_1
      1068: goto          1072
      1071: iconst_0
      1072: istore        60
      1074: iload         52
      1076: bipush        15
      1078: if_icmpne     1085
      1081: iconst_1
      1082: goto          1086
      1085: iconst_0
      1086: istore        61
      1088: iload         60
      1090: ifne          1098
      1093: iload         61
      1095: ifeq          1385
      1098: aload         56
      1100: ifnull        1128
      1103: aload         56
      1105: aload_0
      1106: getfield      #110                // Field blockStateShortShapeCache:Lxaero/map/cache/BlockStateShortShapeCache;
      1109: aload         23
      1111: invokevirtual #729                // Method xaero/map/region/MapBlock.getEffectiveHeight:(Lxaero/map/cache/BlockStateShortShapeCache;Lxaero/map/region/MapUpdateFastConfig;)I
      1114: aload         59
      1116: aload_0
      1117: getfield      #110                // Field blockStateShortShapeCache:Lxaero/map/cache/BlockStateShortShapeCache;
      1120: aload         23
      1122: invokevirtual #729                // Method xaero/map/region/MapBlock.getEffectiveHeight:(Lxaero/map/cache/BlockStateShortShapeCache;Lxaero/map/region/MapUpdateFastConfig;)I
      1125: if_icmpeq     1385
      1128: iload         60
      1130: ifeq          1272
      1133: iload         50
      1135: ifne          1206
      1138: aload         48
      1140: ifnonnull     1206
      1143: aload_0
      1144: getfield      #515                // Field insideZ:I
      1147: iconst_3
      1148: if_icmpne     1206
      1151: iload         20
      1153: bipush        7
      1155: if_icmpge     1206
      1158: aload         30
      1160: iload         19
      1162: iload         20
      1164: iconst_1
      1165: iadd
      1166: invokevirtual #594                // Method xaero/map/region/MapRegion.getChunk:(II)Lxaero/map/region/MapTileChunk;
      1169: astore        27
      1171: iconst_1
      1172: istore        50
      1174: aload         27
      1176: ifnull        1192
      1179: aload         27
      1181: aload_0
      1182: getfield      #512                // Field insideX:I
      1185: iconst_0
      1186: invokevirtual #649                // Method xaero/map/region/MapTileChunk.getTile:(II)Lxaero/map/region/MapTile;
      1189: goto          1193
      1192: aconst_null
      1193: astore        48
      1195: aload         48
      1197: ifnull        1206
      1200: aload         27
      1202: iconst_1
      1203: invokevirtual #694                // Method xaero/map/region/MapTileChunk.setChanged:(Z)V
      1206: aload         48
      1208: ifnull        1250
      1211: aload         48
      1213: invokevirtual #715                // Method xaero/map/region/MapTile.isLoaded:()Z
      1216: ifeq          1250
      1219: aload         48
      1221: iload         52
      1223: iconst_0
      1224: invokevirtual #718                // Method xaero/map/region/MapTile.getBlock:(II)Lxaero/map/region/MapBlock;
      1227: iconst_1
      1228: invokevirtual #749                // Method xaero/map/region/MapBlock.setSlopeUnknown:(Z)V
      1231: iload         61
      1233: ifne          1250
      1236: aload         48
      1238: iload         52
      1240: iconst_1
      1241: iadd
      1242: iconst_0
      1243: invokevirtual #718                // Method xaero/map/region/MapTile.getBlock:(II)Lxaero/map/region/MapBlock;
      1246: iconst_1
      1247: invokevirtual #749                // Method xaero/map/region/MapBlock.setSlopeUnknown:(Z)V
      1250: iload         61
      1252: ifeq          1385
      1255: aload_0
      1256: aload         30
      1258: aload         26
      1260: aload         27
      1262: iload         19
      1264: iload         20
      1266: invokevirtual #752                // Method updateBottomRightTile:(Lxaero/map/region/MapRegion;Lxaero/map/region/MapTileChunk;Lxaero/map/region/MapTileChunk;II)V
      1269: goto          1385
      1272: iload         61
      1274: ifeq          1385
      1277: iload         51
      1279: ifne          1358
      1282: aload         49
      1284: ifnonnull     1358
      1287: aload_0
      1288: getfield      #512                // Field insideX:I
      1291: iconst_3
      1292: if_icmpne     1358
      1295: iload         19
      1297: bipush        7
      1299: if_icmpge     1358
      1302: aload_0
      1303: aload         30
      1305: iload         19
      1307: iconst_1
      1308: iadd
      1309: iload         20
      1311: invokevirtual #594                // Method xaero/map/region/MapRegion.getChunk:(II)Lxaero/map/region/MapTileChunk;
      1314: putfield      #43                 // Field rightChunk:Lxaero/map/region/MapTileChunk;
      1317: iconst_1
      1318: istore        51
      1320: aload_0
      1321: getfield      #43                 // Field rightChunk:Lxaero/map/region/MapTileChunk;
      1324: ifnull        1342
      1327: aload_0
      1328: getfield      #43                 // Field rightChunk:Lxaero/map/region/MapTileChunk;
      1331: iconst_0
      1332: aload_0
      1333: getfield      #515                // Field insideZ:I
      1336: invokevirtual #649                // Method xaero/map/region/MapTileChunk.getTile:(II)Lxaero/map/region/MapTile;
      1339: goto          1343
      1342: aconst_null
      1343: astore        49
      1345: aload         49
      1347: ifnull        1358
      1350: aload_0
      1351: getfield      #43                 // Field rightChunk:Lxaero/map/region/MapTileChunk;
      1354: iconst_1
      1355: invokevirtual #694                // Method xaero/map/region/MapTileChunk.setChanged:(Z)V
      1358: aload         49
      1360: ifnull        1385
      1363: aload         49
      1365: invokevirtual #715                // Method xaero/map/region/MapTile.isLoaded:()Z
      1368: ifeq          1385
      1371: aload         49
      1373: iconst_0
      1374: iload         53
      1376: iconst_1
      1377: iadd
      1378: invokevirtual #718                // Method xaero/map/region/MapTile.getBlock:(II)Lxaero/map/region/MapBlock;
      1381: iconst_1
      1382: invokevirtual #749                // Method xaero/map/region/MapBlock.setSlopeUnknown:(Z)V
      1385: iinc          53, 1
      1388: goto          798
      1391: iinc          52, 1
      1394: goto          788
      1397: aload         40
      1399: iconst_1
      1400: invokevirtual #756                // Method xaero/map/region/MapTile.setWorldInterpretationVersion:(I)V
      1403: aload         40
      1405: invokevirtual #653                // Method xaero/map/region/MapTile.getWrittenCaveStart:()I
      1408: iload         15
      1410: if_icmpeq     1419
      1413: aload         26
      1415: iconst_1
      1416: invokevirtual #694                // Method xaero/map/region/MapTileChunk.setChanged:(Z)V
      1419: aload         40
      1421: iload         15
      1423: iload         14
      1425: invokevirtual #760                // Method xaero/map/region/MapTile.setWrittenCave:(II)V
      1428: aload         26
      1430: aload_0
      1431: getfield      #512                // Field insideX:I
      1434: aload_0
      1435: getfield      #515                // Field insideZ:I
      1438: aload         40
      1440: aload_0
      1441: getfield      #110                // Field blockStateShortShapeCache:Lxaero/map/cache/BlockStateShortShapeCache;
      1444: invokevirtual #764                // Method xaero/map/region/MapTileChunk.setTile:(IILxaero/map/region/MapTile;Lxaero/map/cache/BlockStateShortShapeCache;)V
      1447: aload         40
      1449: iconst_1
      1450: invokevirtual #768                // Method xaero/map/region/MapTile.setWrittenOnce:(Z)V
      1453: aload         40
      1455: iconst_1
      1456: invokevirtual #771                // Method xaero/map/region/MapTile.setLoaded:(Z)V
      1459: aload         39
      1461: getstatic     #661                // Field xaero/map/core/XaeroWorldMapCore.chunkCleanField:Ljava/lang/reflect/Field;
      1464: iconst_1
      1465: invokestatic  #774                // Method java/lang/Boolean.valueOf:(Z)Ljava/lang/Boolean;
      1468: invokestatic  #778                // Method xaero/lib/common/reflection/util/ReflectionUtils.setReflectFieldValue:(Ljava/lang/Object;Ljava/lang/reflect/Field;Ljava/lang/Object;)V
      1471: iload         35
      1473: ifeq          1535
      1476: aload         26
      1478: invokevirtual #784                // Method xaero/map/region/MapTileChunk.includeInSave:()Z
      1481: ifeq          1489
      1484: aload         26
      1486: invokevirtual #787                // Method xaero/map/region/MapTileChunk.setHasHadTerrain:()V
      1489: aload_0
      1490: getfield      #202                // Field mapProcessor:Lxaero/map/MapProcessor;
      1493: invokevirtual #790                // Method xaero/map/MapProcessor.getMapRegionHighlightsPreparer:()Lxaero/map/highlight/MapRegionHighlightsPreparer;
      1496: aload         30
      1498: iload         19
      1500: iload         20
      1502: iconst_0
      1503: invokevirtual #794                // Method xaero/map/highlight/MapRegionHighlightsPreparer.prepare:(Lxaero/map/region/MapRegion;IIZ)V
      1506: aload         26
      1508: invokevirtual #784                // Method xaero/map/region/MapTileChunk.includeInSave:()Z
      1511: ifne          1535
      1514: aload         26
      1516: invokevirtual #800                // Method xaero/map/region/MapTileChunk.hasHighlightsIfUndiscovered:()Z
      1519: ifne          1535
      1522: aload         30
      1524: iload         19
      1526: iload         20
      1528: aconst_null
      1529: invokevirtual #601                // Method xaero/map/region/MapRegion.setChunk:(IILxaero/map/region/MapTileChunk;)V
      1532: aconst_null
      1533: astore        26
      1535: aload         26
      1537: ifnull        1789
      1540: aload_0
      1541: getfield      #512                // Field insideX:I
      1544: iconst_3
      1545: if_icmpne     1789
      1548: aload_0
      1549: getfield      #515                // Field insideZ:I
      1552: iconst_3
      1553: if_icmpne     1789
      1556: aload         26
      1558: invokevirtual #803                // Method xaero/map/region/MapTileChunk.wasChanged:()Z
      1561: ifeq          1789
      1564: aload         26
      1566: aload_0
      1567: getfield      #202                // Field mapProcessor:Lxaero/map/MapProcessor;
      1570: aload         13
      1572: aload         6
      1574: iload         11
      1576: aload_0
      1577: getfield      #110                // Field blockStateShortShapeCache:Lxaero/map/cache/BlockStateShortShapeCache;
      1580: aload         23
      1582: invokevirtual #806                // Method xaero/map/region/MapTileChunk.updateBuffers:(Lxaero/map/MapProcessor;Lxaero/map/biome/BlockTintProvider;Lxaero/map/region/OverlayManager;ZLxaero/map/cache/BlockStateShortShapeCache;Lxaero/map/region/MapUpdateFastConfig;)V
      1585: aload         27
      1587: ifnonnull     1610
      1590: iload         20
      1592: bipush        7
      1594: if_icmpge     1610
      1597: aload         30
      1599: iload         19
      1601: iload         20
      1603: iconst_1
      1604: iadd
      1605: invokevirtual #594                // Method xaero/map/region/MapRegion.getChunk:(II)Lxaero/map/region/MapTileChunk;
      1608: astore        27
      1610: aload_0
      1611: getfield      #43                 // Field rightChunk:Lxaero/map/region/MapTileChunk;
      1614: ifnonnull     1639
      1617: iload         19
      1619: bipush        7
      1621: if_icmpge     1639
      1624: aload_0
      1625: aload         30
      1627: iload         19
      1629: iconst_1
      1630: iadd
      1631: iload         20
      1633: invokevirtual #594                // Method xaero/map/region/MapRegion.getChunk:(II)Lxaero/map/region/MapTileChunk;
      1636: putfield      #43                 // Field rightChunk:Lxaero/map/region/MapTileChunk;
      1639: aload_0
      1640: getfield      #47                 // Field bottomRightChunk:Lxaero/map/region/MapTileChunk;
      1643: ifnonnull     1677
      1646: iload         19
      1648: bipush        7
      1650: if_icmpge     1677
      1653: iload         20
      1655: bipush        7
      1657: if_icmpge     1677
      1660: aload_0
      1661: aload         30
      1663: iload         19
      1665: iconst_1
      1666: iadd
      1667: iload         20
      1669: iconst_1
      1670: iadd
      1671: invokevirtual #594                // Method xaero/map/region/MapRegion.getChunk:(II)Lxaero/map/region/MapTileChunk;
      1674: putfield      #47                 // Field bottomRightChunk:Lxaero/map/region/MapTileChunk;
      1677: aload         27
      1679: ifnull        1717
      1682: aload         27
      1684: invokevirtual #803                // Method xaero/map/region/MapTileChunk.wasChanged:()Z
      1687: ifeq          1717
      1690: aload         27
      1692: aload_0
      1693: getfield      #202                // Field mapProcessor:Lxaero/map/MapProcessor;
      1696: aload         13
      1698: aload         6
      1700: iload         11
      1702: aload_0
      1703: getfield      #110                // Field blockStateShortShapeCache:Lxaero/map/cache/BlockStateShortShapeCache;
      1706: aload         23
      1708: invokevirtual #806                // Method xaero/map/region/MapTileChunk.updateBuffers:(Lxaero/map/MapProcessor;Lxaero/map/biome/BlockTintProvider;Lxaero/map/region/OverlayManager;ZLxaero/map/cache/BlockStateShortShapeCache;Lxaero/map/region/MapUpdateFastConfig;)V
      1711: aload         27
      1713: iconst_0
      1714: invokevirtual #694                // Method xaero/map/region/MapTileChunk.setChanged:(Z)V
      1717: aload_0
      1718: getfield      #43                 // Field rightChunk:Lxaero/map/region/MapTileChunk;
      1721: ifnull        1750
      1724: aload_0
      1725: getfield      #43                 // Field rightChunk:Lxaero/map/region/MapTileChunk;
      1728: invokevirtual #803                // Method xaero/map/region/MapTileChunk.wasChanged:()Z
      1731: ifeq          1750
      1734: aload_0
      1735: getfield      #43                 // Field rightChunk:Lxaero/map/region/MapTileChunk;
      1738: iconst_1
      1739: invokevirtual #810                // Method xaero/map/region/MapTileChunk.setToUpdateBuffers:(Z)V
      1742: aload_0
      1743: getfield      #43                 // Field rightChunk:Lxaero/map/region/MapTileChunk;
      1746: iconst_0
      1747: invokevirtual #694                // Method xaero/map/region/MapTileChunk.setChanged:(Z)V
      1750: aload_0
      1751: getfield      #47                 // Field bottomRightChunk:Lxaero/map/region/MapTileChunk;
      1754: ifnull        1783
      1757: aload_0
      1758: getfield      #47                 // Field bottomRightChunk:Lxaero/map/region/MapTileChunk;
      1761: invokevirtual #803                // Method xaero/map/region/MapTileChunk.wasChanged:()Z
      1764: ifeq          1783
      1767: aload_0
      1768: getfield      #47                 // Field bottomRightChunk:Lxaero/map/region/MapTileChunk;
      1771: iconst_1
      1772: invokevirtual #810                // Method xaero/map/region/MapTileChunk.setToUpdateBuffers:(Z)V
      1775: aload_0
      1776: getfield      #47                 // Field bottomRightChunk:Lxaero/map/region/MapTileChunk;
      1779: iconst_0
      1780: invokevirtual #694                // Method xaero/map/region/MapTileChunk.setChanged:(Z)V
      1783: aload         26
      1785: iconst_0
      1786: invokevirtual #694                // Method xaero/map/region/MapTileChunk.setChanged:(Z)V
      1789: goto          1802
      1792: aload_0
      1793: iconst_3
      1794: putfield      #512                // Field insideX:I
      1797: aload_0
      1798: iconst_3
      1799: putfield      #515                // Field insideZ:I
      1802: aload         32
      1804: monitorexit
      1805: goto          1816
      1808: astore        62
      1810: aload         32
      1812: monitorexit
      1813: aload         62
      1815: athrow
      1816: aload_0
      1817: dup
      1818: getfield      #515                // Field insideZ:I
      1821: iconst_1
      1822: iadd
      1823: putfield      #515                // Field insideZ:I
      1826: aload_0
      1827: getfield      #515                // Field insideZ:I
      1830: iconst_3
      1831: if_icmple     1934
      1834: aload_0
      1835: iconst_0
      1836: putfield      #515                // Field insideZ:I
      1839: aload_0
      1840: dup
      1841: getfield      #512                // Field insideX:I
      1844: iconst_1
      1845: iadd
      1846: putfield      #512                // Field insideX:I
      1849: aload_0
      1850: getfield      #512                // Field insideX:I
      1853: iconst_3
      1854: if_icmple     1934
      1857: aload_0
      1858: iconst_0
      1859: putfield      #512                // Field insideX:I
      1862: aload_0
      1863: dup
      1864: getfield      #521                // Field Z:I
      1867: iconst_1
      1868: iadd
      1869: putfield      #521                // Field Z:I
      1872: aload_0
      1873: getfield      #521                // Field Z:I
      1876: aload_0
      1877: getfield      #341                // Field endTileChunkZ:I
      1880: aload_0
      1881: getfield      #344                // Field startTileChunkZ:I
      1884: isub
      1885: if_icmple     1934
      1888: aload_0
      1889: iconst_0
      1890: putfield      #521                // Field Z:I
      1893: aload_0
      1894: dup
      1895: getfield      #518                // Field X:I
      1898: iconst_1
      1899: iadd
      1900: putfield      #518                // Field X:I
      1903: aload_0
      1904: getfield      #518                // Field X:I
      1907: aload_0
      1908: getfield      #335                // Field endTileChunkX:I
      1911: aload_0
      1912: getfield      #338                // Field startTileChunkX:I
      1915: isub
      1916: if_icmple     1934
      1919: aload_0
      1920: iconst_0
      1921: putfield      #518                // Field X:I
      1924: aload_0
      1925: dup
      1926: getfield      #507                // Field updateCounter:J
      1929: lconst_1
      1930: ladd
      1931: putfield      #507                // Field updateCounter:J
      1934: iload         31
      1936: ireturn
      Exception table:
         from    to  target type
            87   226   229   any
           229   234   229   any
           414   468   471   Class java/lang/IllegalArgumentException
           414   468   471   Class java/lang/IllegalAccessException
            70  1805  1808   any
          1808  1813  1808   any

  public void updateBottomRightTile(xaero.map.region.MapRegion, xaero.map.region.MapTileChunk, xaero.map.region.MapTileChunk, int, int);
    Code:
         0: aload_0
         1: getfield      #512                // Field insideX:I
         4: iconst_3
         5: if_icmpge     35
         8: aload_0
         9: getfield      #515                // Field insideZ:I
        12: iconst_3
        13: if_icmpge     35
        16: aload_2
        17: aload_0
        18: getfield      #512                // Field insideX:I
        21: iconst_1
        22: iadd
        23: aload_0
        24: getfield      #515                // Field insideZ:I
        27: iconst_1
        28: iadd
        29: invokevirtual #649                // Method xaero/map/region/MapTileChunk.getTile:(II)Lxaero/map/region/MapTile;
        32: goto          36
        35: aconst_null
        36: astore        6
        38: aload         6
        40: ifnonnull     245
        43: aload_0
        44: getfield      #512                // Field insideX:I
        47: iconst_3
        48: if_icmpne     191
        51: iload         4
        53: bipush        7
        55: if_icmpge     191
        58: aload_0
        59: getfield      #515                // Field insideZ:I
        62: iconst_3
        63: if_icmpne     127
        66: iload         5
        68: bipush        7
        70: if_icmpge     89
        73: aload_0
        74: aload_1
        75: iload         4
        77: iconst_1
        78: iadd
        79: iload         5
        81: iconst_1
        82: iadd
        83: invokevirtual #594                // Method xaero/map/region/MapRegion.getChunk:(II)Lxaero/map/region/MapTileChunk;
        86: putfield      #47                 // Field bottomRightChunk:Lxaero/map/region/MapTileChunk;
        89: aload_0
        90: getfield      #47                 // Field bottomRightChunk:Lxaero/map/region/MapTileChunk;
        93: ifnull        108
        96: aload_0
        97: getfield      #47                 // Field bottomRightChunk:Lxaero/map/region/MapTileChunk;
       100: iconst_0
       101: iconst_0
       102: invokevirtual #649                // Method xaero/map/region/MapTileChunk.getTile:(II)Lxaero/map/region/MapTile;
       105: goto          109
       108: aconst_null
       109: astore        6
       111: aload         6
       113: ifnull        245
       116: aload_0
       117: getfield      #47                 // Field bottomRightChunk:Lxaero/map/region/MapTileChunk;
       120: iconst_1
       121: invokevirtual #694                // Method xaero/map/region/MapTileChunk.setChanged:(Z)V
       124: goto          245
       127: aload_0
       128: getfield      #43                 // Field rightChunk:Lxaero/map/region/MapTileChunk;
       131: ifnonnull     148
       134: aload_0
       135: aload_1
       136: iload         4
       138: iconst_1
       139: iadd
       140: iload         5
       142: invokevirtual #594                // Method xaero/map/region/MapRegion.getChunk:(II)Lxaero/map/region/MapTileChunk;
       145: putfield      #43                 // Field rightChunk:Lxaero/map/region/MapTileChunk;
       148: aload_0
       149: getfield      #43                 // Field rightChunk:Lxaero/map/region/MapTileChunk;
       152: ifnull        172
       155: aload_0
       156: getfield      #43                 // Field rightChunk:Lxaero/map/region/MapTileChunk;
       159: iconst_0
       160: aload_0
       161: getfield      #515                // Field insideZ:I
       164: iconst_1
       165: iadd
       166: invokevirtual #649                // Method xaero/map/region/MapTileChunk.getTile:(II)Lxaero/map/region/MapTile;
       169: goto          173
       172: aconst_null
       173: astore        6
       175: aload         6
       177: ifnull        245
       180: aload_0
       181: getfield      #43                 // Field rightChunk:Lxaero/map/region/MapTileChunk;
       184: iconst_1
       185: invokevirtual #694                // Method xaero/map/region/MapTileChunk.setChanged:(Z)V
       188: goto          245
       191: aload_0
       192: getfield      #512                // Field insideX:I
       195: iconst_3
       196: if_icmpeq     245
       199: aload_0
       200: getfield      #515                // Field insideZ:I
       203: iconst_3
       204: if_icmpne     245
       207: iload         5
       209: bipush        7
       211: if_icmpge     245
       214: aload_3
       215: ifnull        232
       218: aload_3
       219: aload_0
       220: getfield      #512                // Field insideX:I
       223: iconst_1
       224: iadd
       225: iconst_0
       226: invokevirtual #649                // Method xaero/map/region/MapTileChunk.getTile:(II)Lxaero/map/region/MapTile;
       229: goto          233
       232: aconst_null
       233: astore        6
       235: aload         6
       237: ifnull        245
       240: aload_3
       241: iconst_1
       242: invokevirtual #694                // Method xaero/map/region/MapTileChunk.setChanged:(Z)V
       245: aload         6
       247: ifnull        269
       250: aload         6
       252: invokevirtual #715                // Method xaero/map/region/MapTile.isLoaded:()Z
       255: ifeq          269
       258: aload         6
       260: iconst_0
       261: iconst_0
       262: invokevirtual #718                // Method xaero/map/region/MapTile.getBlock:(II)Lxaero/map/region/MapBlock;
       265: iconst_1
       266: invokevirtual #749                // Method xaero/map/region/MapBlock.setSlopeUnknown:(Z)V
       269: return

  public int getSectionBasedHeight(net.minecraft.world.level.chunk.LevelChunk, int);
    Code:
         0: aload_1
         1: invokevirtual #813                // Method net/minecraft/world/level/chunk/LevelChunk.getSections:()[Lnet/minecraft/world/level/chunk/LevelChunkSection;
         4: astore_3
         5: aload_3
         6: arraylength
         7: ifne          12
        10: iconst_0
        11: ireturn
        12: aload_1
        13: invokevirtual #817                // Method net/minecraft/world/level/chunk/LevelChunk.getMinY:()I
        16: istore        4
        18: iload_2
        19: iload         4
        21: isub
        22: iconst_4
        23: ishr
        24: aload_3
        25: arraylength
        26: iconst_1
        27: isub
        28: invokestatic  #505                // Method java/lang/Math.min:(II)I
        31: istore        5
        33: iload         5
        35: ifge          41
        38: iconst_0
        39: istore        5
        41: iconst_0
        42: istore        6
        44: iload         5
        46: istore        7
        48: iload         7
        50: aload_3
        51: arraylength
        52: if_icmpge     87
        55: aload_3
        56: iload         7
        58: aaload
        59: astore        8
        61: aload         8
        63: invokevirtual #818                // Method net/minecraft/world/level/chunk/LevelChunkSection.hasOnlyAir:()Z
        66: ifne          81
        69: iload         4
        71: iload         7
        73: iconst_4
        74: ishl
        75: iadd
        76: bipush        15
        78: iadd
        79: istore        6
        81: iinc          7, 1
        84: goto          48
        87: iload         5
        89: ifle          143
        92: iload         6
        94: ifne          143
        97: iload         5
        99: iconst_1
       100: isub
       101: istore        7
       103: iload         7
       105: iflt          143
       108: aload_3
       109: iload         7
       111: aaload
       112: astore        8
       114: aload         8
       116: invokevirtual #818                // Method net/minecraft/world/level/chunk/LevelChunkSection.hasOnlyAir:()Z
       119: ifne          137
       122: iload         4
       124: iload         7
       126: iconst_4
       127: ishl
       128: iadd
       129: bipush        15
       131: iadd
       132: istore        6
       134: goto          143
       137: iinc          7, -1
       140: goto          103
       143: iload         6
       145: ireturn

  public boolean isGlowing(net.minecraft.world.level.block.state.BlockState);
    Code:
         0: aload_1
         1: invokevirtual #823                // Method net/minecraft/world/level/block/state/BlockState.getLightEmission:()I
         4: i2d
         5: ldc2_w        #828                // double 0.5d
         8: dcmpl
         9: iflt          16
        12: iconst_1
        13: goto          17
        16: iconst_0
        17: ireturn

  private boolean shouldOverlayCached(net.minecraft.world.level.block.state.StateHolder<?, ?>);
    Code:
         0: aload_0
         1: getfield      #123                // Field transparentCache:Lxaero/map/misc/CachedFunction;
         4: aload_1
         5: invokevirtual #830                // Method xaero/map/misc/CachedFunction.apply:(Ljava/lang/Object;)Ljava/lang/Object;
         8: checkcast     #256                // class java/lang/Boolean
        11: invokevirtual #258                // Method java/lang/Boolean.booleanValue:()Z
        14: ireturn

  public boolean shouldOverlay(net.minecraft.world.level.block.state.StateHolder<?, ?>);
    Code:
         0: aload_1
         1: instanceof    #824                // class net/minecraft/world/level/block/state/BlockState
         4: ifeq          40
         7: aload_1
         8: checkcast     #824                // class net/minecraft/world/level/block/state/BlockState
        11: astore_2
        12: aload_2
        13: invokevirtual #832                // Method net/minecraft/world/level/block/state/BlockState.getBlock:()Lnet/minecraft/world/level/block/Block;
        16: instanceof    #835                // class net/minecraft/world/level/block/AirBlock
        19: ifne          32
        22: aload_2
        23: invokevirtual #832                // Method net/minecraft/world/level/block/state/BlockState.getBlock:()Lnet/minecraft/world/level/block/Block;
        26: instanceof    #837                // class net/minecraft/world/level/block/TransparentBlock
        29: ifeq          34
        32: iconst_1
        33: ireturn
        34: aload_0
        35: aload_2
        36: invokevirtual #839                // Method blockStateHasTranslucentRenderType:(Lnet/minecraft/world/level/block/state/BlockState;)Z
        39: ireturn
        40: aload_1
        41: checkcast     #843                // class net/minecraft/world/level/material/FluidState
        44: astore_2
        45: aload_0
        46: aload_2
        47: invokevirtual #845                // Method fluidStateHasTranslucentRenderType:(Lnet/minecraft/world/level/material/FluidState;)Z
        50: ireturn

  public boolean isInvisible(net.minecraft.world.level.block.state.BlockState, net.minecraft.world.level.block.Block, boolean);
    Code:
         0: aload_2
         1: instanceof    #849                // class net/minecraft/world/level/block/LiquidBlock
         4: ifne          19
         7: aload_1
         8: invokevirtual #851                // Method net/minecraft/world/level/block/state/BlockState.getRenderShape:()Lnet/minecraft/world/level/block/RenderShape;
        11: getstatic     #855                // Field net/minecraft/world/level/block/RenderShape.INVISIBLE:Lnet/minecraft/world/level/block/RenderShape;
        14: if_acmpne     19
        17: iconst_1
        18: ireturn
        19: aload_2
        20: getstatic     #861                // Field net/minecraft/world/level/block/Blocks.TORCH:Lnet/minecraft/world/level/block/Block;
        23: if_acmpne     28
        26: iconst_1
        27: ireturn
        28: aload_2
        29: getstatic     #867                // Field net/minecraft/world/level/block/Blocks.SHORT_GRASS:Lnet/minecraft/world/level/block/Block;
        32: if_acmpne     37
        35: iconst_1
        36: ireturn
        37: aload_2
        38: getstatic     #870                // Field net/minecraft/world/level/block/Blocks.GLASS:Lnet/minecraft/world/level/block/Block;
        41: if_acmpeq     51
        44: aload_2
        45: getstatic     #873                // Field net/minecraft/world/level/block/Blocks.GLASS_PANE:Lnet/minecraft/world/level/block/Block;
        48: if_acmpne     53
        51: iconst_1
        52: ireturn
        53: aload_2
        54: instanceof    #876                // class net/minecraft/world/level/block/PitcherCropBlock
        57: ifne          84
        60: aload_2
        61: instanceof    #878                // class net/minecraft/world/level/block/TallFlowerBlock
        64: ifne          84
        67: aload_2
        68: instanceof    #880                // class net/minecraft/world/level/block/FlowerBlock
        71: ifne          84
        74: aload_1
        75: getstatic     #882                // Field net/minecraft/tags/BlockTags.FLOWERS:Lnet/minecraft/tags/TagKey;
        78: invokevirtual #887                // Method net/minecraft/world/level/block/state/BlockState.is:(Lnet/minecraft/tags/TagKey;)Z
        81: ifeq          88
        84: iconst_1
        85: goto          89
        88: iconst_0
        89: istore        4
        91: aload_2
        92: instanceof    #891                // class net/minecraft/world/level/block/DoublePlantBlock
        95: ifeq          105
        98: iload         4
       100: ifne          105
       103: iconst_1
       104: ireturn
       105: iload         4
       107: ifeq          116
       110: iload_3
       111: ifne          116
       114: iconst_1
       115: ireturn
       116: aload_0
       117: getfield      #107                // Field buggedStates:Ljava/util/ArrayList;
       120: dup
       121: astore        5
       123: monitorenter
       124: aload_0
       125: getfield      #107                // Field buggedStates:Ljava/util/ArrayList;
       128: aload_1
       129: invokevirtual #893                // Method java/util/ArrayList.contains:(Ljava/lang/Object;)Z
       132: ifeq          140
       135: iconst_1
       136: aload         5
       138: monitorexit
       139: ireturn
       140: aload         5
       142: monitorexit
       143: goto          154
       146: astore        6
       148: aload         5
       150: monitorexit
       151: aload         6
       153: athrow
       154: iconst_0
       155: ireturn
      Exception table:
         from    to  target type
           124   139   146   any
           140   143   146   any
           146   151   146   any

  public boolean hasVanillaColor(net.minecraft.world.level.block.state.BlockState, net.minecraft.world.level.Level, net.minecraft.core.Registry<net.minecraft.world.level.block.Block>, net.minecraft.core.BlockPos);
    Code:
         0: aconst_null
         1: astore        5
         3: aload_1
         4: aload_2
         5: aload         4
         7: invokevirtual #897                // Method net/minecraft/world/level/block/state/BlockState.getMapColor:(Lnet/minecraft/world/level/BlockGetter;Lnet/minecraft/core/BlockPos;)Lnet/minecraft/world/level/material/MapColor;
        10: astore        5
        12: goto          74
        15: astore        6
        17: aload_0
        18: getfield      #107                // Field buggedStates:Ljava/util/ArrayList;
        21: dup
        22: astore        7
        24: monitorenter
        25: aload_0
        26: getfield      #107                // Field buggedStates:Ljava/util/ArrayList;
        29: aload_1
        30: invokevirtual #901                // Method java/util/ArrayList.add:(Ljava/lang/Object;)Z
        33: pop
        34: aload         7
        36: monitorexit
        37: goto          48
        40: astore        8
        42: aload         7
        44: monitorexit
        45: aload         8
        47: athrow
        48: getstatic     #904                // Field xaero/map/WorldMap.LOGGER:Lorg/apache/logging/log4j/Logger;
        51: aload_3
        52: aload_1
        53: invokevirtual #832                // Method net/minecraft/world/level/block/state/BlockState.getBlock:()Lnet/minecraft/world/level/block/Block;
        56: invokeinterface #908,  2          // InterfaceMethod net/minecraft/core/Registry.getKey:(Ljava/lang/Object;)Lnet/minecraft/resources/Identifier;
        61: invokestatic  #914                // Method java/lang/String.valueOf:(Ljava/lang/Object;)Ljava/lang/String;
        64: invokedynamic #919,  0            // InvokeDynamic #5:makeConcatWithConstants:(Ljava/lang/String;)Ljava/lang/String;
        69: invokeinterface #923,  2          // InterfaceMethod org/apache/logging/log4j/Logger.info:(Ljava/lang/String;)V
        74: aload         5
        76: ifnull        91
        79: aload         5
        81: getfield      #929                // Field net/minecraft/world/level/material/MapColor.col:I
        84: ifeq          91
        87: iconst_1
        88: goto          92
        91: iconst_0
        92: ireturn
      Exception table:
         from    to  target type
             3    12    15   Class java/lang/Throwable
            25    37    40   any
            40    45    40   any

  private net.minecraft.world.level.block.state.BlockState unpackFramedBlocks(net.minecraft.world.level.block.state.BlockState, net.minecraft.world.level.Level, net.minecraft.core.BlockPos);
    Code:
         0: aload_1
         1: invokevirtual #832                // Method net/minecraft/world/level/block/state/BlockState.getBlock:()Lnet/minecraft/world/level/block/Block;
         4: instanceof    #835                // class net/minecraft/world/level/block/AirBlock
         7: ifeq          12
        10: aload_1
        11: areturn
        12: aload_1
        13: astore        4
        15: invokestatic  #934                // Method xaero/map/mods/SupportMods.framedBlocks:()Z
        18: ifeq          77
        21: getstatic     #939                // Field xaero/map/mods/SupportMods.supportFramedBlocks:Lxaero/map/mods/SupportFramedBlocks;
        24: aload_2
        25: aconst_null
        26: aload_1
        27: invokevirtual #943                // Method xaero/map/mods/SupportFramedBlocks.isFrameBlock:(Lnet/minecraft/world/level/Level;Lnet/minecraft/core/Registry;Lnet/minecraft/world/level/block/state/BlockState;)Z
        30: ifeq          77
        33: aload_2
        34: aload_3
        35: invokevirtual #949                // Method net/minecraft/world/level/Level.getBlockEntity:(Lnet/minecraft/core/BlockPos;)Lnet/minecraft/world/level/block/entity/BlockEntity;
        38: astore        5
        40: aload         5
        42: ifnull        77
        45: getstatic     #939                // Field xaero/map/mods/SupportMods.supportFramedBlocks:Lxaero/map/mods/SupportFramedBlocks;
        48: aload_2
        49: aconst_null
        50: aload_1
        51: aload         5
        53: invokevirtual #953                // Method xaero/map/mods/SupportFramedBlocks.unpackFramedBlock:(Lnet/minecraft/world/level/Level;Lnet/minecraft/core/Registry;Lnet/minecraft/world/level/block/state/BlockState;Lnet/minecraft/world/level/block/entity/BlockEntity;)Lnet/minecraft/world/level/block/state/BlockState;
        56: astore        4
        58: aload         4
        60: ifnull        74
        63: aload         4
        65: invokevirtual #832                // Method net/minecraft/world/level/block/state/BlockState.getBlock:()Lnet/minecraft/world/level/block/Block;
        68: instanceof    #835                // class net/minecraft/world/level/block/AirBlock
        71: ifeq          77
        74: aload_1
        75: astore        4
        77: aload         4
        79: areturn

  public void loadPixel(net.minecraft.world.level.Level, net.minecraft.core.Registry<net.minecraft.world.level.block.Block>, xaero.map.region.MapBlock, xaero.map.region.MapBlock, net.minecraft.world.level.chunk.LevelChunk, int, int, int, int, boolean, boolean, int, boolean, boolean, net.minecraft.core.Registry<net.minecraft.world.level.biome.Biome>, boolean, int, net.minecraft.core.BlockPos$MutableBlockPos);
    Code:
         0: aload_3
         1: iload         17
         3: invokevirtual #957                // Method xaero/map/region/MapBlock.prepareForWriting:(I)V
         6: aload_0
         7: getfield      #93                 // Field overlayBuilder:Lxaero/map/region/OverlayBuilder;
        10: invokevirtual #960                // Method xaero/map/region/OverlayBuilder.startBuilding:()V
        13: iload         10
        15: ifeq          23
        18: iload         11
        20: ifeq          27
        23: iconst_1
        24: goto          28
        27: iconst_0
        28: istore        19
        30: iload         11
        32: istore        20
        34: aconst_null
        35: astore        21
        37: iconst_m1
        38: istore        22
        40: aload_1
        41: invokevirtual #963                // Method net/minecraft/world/level/Level.dimensionType:()Lnet/minecraft/world/level/dimension/DimensionType;
        44: invokevirtual #967                // Method net/minecraft/world/level/dimension/DimensionType.hasSkyLight:()Z
        47: istore        23
        49: iload         23
        51: ifeq          59
        54: bipush        15
        56: goto          60
        59: iconst_0
        60: istore        24
        62: aload_0
        63: iload         9
        65: putfield      #972                // Field topH:I
        68: aload_0
        69: getfield      #104                // Field mutableGlobalPos:Lnet/minecraft/core/BlockPos$MutableBlockPos;
        72: aload         5
        74: invokevirtual #975                // Method net/minecraft/world/level/chunk/LevelChunk.getPos:()Lnet/minecraft/world/level/ChunkPos;
        77: invokevirtual #979                // Method net/minecraft/world/level/ChunkPos.x:()I
        80: iconst_4
        81: ishl
        82: iload         6
        84: iadd
        85: iload         9
        87: iconst_1
        88: isub
        89: aload         5
        91: invokevirtual #975                // Method net/minecraft/world/level/chunk/LevelChunk.getPos:()Lnet/minecraft/world/level/ChunkPos;
        94: invokevirtual #984                // Method net/minecraft/world/level/ChunkPos.z:()I
        97: iconst_4
        98: ishl
        99: iload         7
       101: iadd
       102: invokevirtual #987                // Method net/minecraft/core/BlockPos$MutableBlockPos.set:(III)Lnet/minecraft/core/BlockPos$MutableBlockPos;
       105: pop
       106: iconst_0
       107: istore        25
       109: iconst_0
       110: istore        26
       112: iload         8
       114: istore        27
       116: iload         27
       118: iload         9
       120: if_icmplt     707
       123: aload_0
       124: getfield      #100                // Field mutableLocalPos:Lnet/minecraft/core/BlockPos$MutableBlockPos;
       127: iload         6
       129: iload         27
       131: iload         7
       133: invokevirtual #987                // Method net/minecraft/core/BlockPos$MutableBlockPos.set:(III)Lnet/minecraft/core/BlockPos$MutableBlockPos;
       136: pop
       137: aload         5
       139: aload_0
       140: getfield      #100                // Field mutableLocalPos:Lnet/minecraft/core/BlockPos$MutableBlockPos;
       143: invokevirtual #991                // Method net/minecraft/world/level/chunk/LevelChunk.getBlockState:(Lnet/minecraft/core/BlockPos;)Lnet/minecraft/world/level/block/state/BlockState;
       146: astore        28
       148: aload         28
       150: ifnonnull     161
       153: getstatic     #995                // Field net/minecraft/world/level/block/Blocks.AIR:Lnet/minecraft/world/level/block/Block;
       156: invokevirtual #998                // Method net/minecraft/world/level/block/Block.defaultBlockState:()Lnet/minecraft/world/level/block/state/BlockState;
       159: astore        28
       161: aload_0
       162: getfield      #104                // Field mutableGlobalPos:Lnet/minecraft/core/BlockPos$MutableBlockPos;
       165: iload         27
       167: invokevirtual #1004               // Method net/minecraft/core/BlockPos$MutableBlockPos.setY:(I)Lnet/minecraft/core/BlockPos$MutableBlockPos;
       170: pop
       171: aload_0
       172: aload         28
       174: aload_1
       175: aload_0
       176: getfield      #104                // Field mutableGlobalPos:Lnet/minecraft/core/BlockPos$MutableBlockPos;
       179: invokevirtual #1008               // Method unpackFramedBlocks:(Lnet/minecraft/world/level/block/state/BlockState;Lnet/minecraft/world/level/Level;Lnet/minecraft/core/BlockPos;)Lnet/minecraft/world/level/block/state/BlockState;
       182: astore        28
       184: aload         28
       186: invokevirtual #1012               // Method net/minecraft/world/level/block/state/BlockState.getFluidState:()Lnet/minecraft/world/level/material/FluidState;
       189: astore        29
       191: iload         25
       193: ifne          221
       196: aload_0
       197: getfield      #93                 // Field overlayBuilder:Lxaero/map/region/OverlayBuilder;
       200: invokevirtual #1016               // Method xaero/map/region/OverlayBuilder.isEmpty:()Z
       203: ifne          221
       206: aload_0
       207: getfield      #1019               // Field firstTransparentStateY:I
       210: iload         27
       212: isub
       213: iconst_5
       214: if_icmplt     221
       217: iconst_1
       218: goto          222
       221: iconst_0
       222: istore        25
       224: iload         25
       226: ifeq          355
       229: iload         27
       231: iconst_1
       232: isub
       233: istore        26
       235: iload         26
       237: iload         9
       239: if_icmplt     355
       242: aload         5
       244: aload         18
       246: iload         6
       248: iload         26
       250: iload         7
       252: invokevirtual #987                // Method net/minecraft/core/BlockPos$MutableBlockPos.set:(III)Lnet/minecraft/core/BlockPos$MutableBlockPos;
       255: invokevirtual #991                // Method net/minecraft/world/level/chunk/LevelChunk.getBlockState:(Lnet/minecraft/core/BlockPos;)Lnet/minecraft/world/level/block/state/BlockState;
       258: astore        30
       260: aload         30
       262: ifnonnull     273
       265: getstatic     #995                // Field net/minecraft/world/level/block/Blocks.AIR:Lnet/minecraft/world/level/block/Block;
       268: invokevirtual #998                // Method net/minecraft/world/level/block/Block.defaultBlockState:()Lnet/minecraft/world/level/block/state/BlockState;
       271: astore        30
       273: aload         30
       275: invokevirtual #1012               // Method net/minecraft/world/level/block/state/BlockState.getFluidState:()Lnet/minecraft/world/level/material/FluidState;
       278: astore        31
       280: aload         31
       282: invokevirtual #1022               // Method net/minecraft/world/level/material/FluidState.isEmpty:()Z
       285: ifne          337
       288: aload_0
       289: aload         31
       291: invokevirtual #1023               // Method shouldOverlayCached:(Lnet/minecraft/world/level/block/state/StateHolder;)Z
       294: ifne          300
       297: goto          355
       300: aload         30
       302: invokevirtual #832                // Method net/minecraft/world/level/block/state/BlockState.getBlock:()Lnet/minecraft/world/level/block/Block;
       305: instanceof    #835                // class net/minecraft/world/level/block/AirBlock
       308: ifne          337
       311: aload         30
       313: invokevirtual #832                // Method net/minecraft/world/level/block/state/BlockState.getBlock:()Lnet/minecraft/world/level/block/Block;
       316: aload_0
       317: getfield      #133                // Field fluidToBlock:Lxaero/map/misc/CachedFunction;
       320: aload         31
       322: invokevirtual #830                // Method xaero/map/misc/CachedFunction.apply:(Ljava/lang/Object;)Ljava/lang/Object;
       325: checkcast     #824                // class net/minecraft/world/level/block/state/BlockState
       328: invokevirtual #832                // Method net/minecraft/world/level/block/state/BlockState.getBlock:()Lnet/minecraft/world/level/block/Block;
       331: if_acmpne     337
       334: goto          349
       337: aload_0
       338: aload         30
       340: invokevirtual #1023               // Method shouldOverlayCached:(Lnet/minecraft/world/level/block/state/StateHolder;)Z
       343: ifne          349
       346: goto          355
       349: iinc          26, -1
       352: goto          235
       355: aload_0
       356: getfield      #104                // Field mutableGlobalPos:Lnet/minecraft/core/BlockPos$MutableBlockPos;
       359: iload         27
       361: iconst_1
       362: iadd
       363: invokevirtual #1004               // Method net/minecraft/core/BlockPos$MutableBlockPos.setY:(I)Lnet/minecraft/core/BlockPos$MutableBlockPos;
       366: pop
       367: aload_1
       368: getstatic     #1027               // Field net/minecraft/world/level/LightLayer.BLOCK:Lnet/minecraft/world/level/LightLayer;
       371: aload_0
       372: getfield      #104                // Field mutableGlobalPos:Lnet/minecraft/core/BlockPos$MutableBlockPos;
       375: invokevirtual #1033               // Method net/minecraft/world/level/Level.getBrightness:(Lnet/minecraft/world/level/LightLayer;Lnet/minecraft/core/BlockPos;)I
       378: i2b
       379: istore        22
       381: iload         10
       383: ifeq          436
       386: iload         22
       388: bipush        15
       390: if_icmpge     436
       393: iload         23
       395: ifeq          436
       398: iload         14
       400: ifne          422
       403: iload         11
       405: ifne          422
       408: iload         8
       410: iload         12
       412: if_icmplt     422
       415: bipush        15
       417: istore        24
       419: goto          436
       422: aload_1
       423: getstatic     #1037               // Field net/minecraft/world/level/LightLayer.SKY:Lnet/minecraft/world/level/LightLayer;
       426: aload_0
       427: getfield      #104                // Field mutableGlobalPos:Lnet/minecraft/core/BlockPos$MutableBlockPos;
       430: invokevirtual #1033               // Method net/minecraft/world/level/Level.getBrightness:(Lnet/minecraft/world/level/LightLayer;Lnet/minecraft/core/BlockPos;)I
       433: i2b
       434: istore        24
       436: aload_0
       437: getfield      #104                // Field mutableGlobalPos:Lnet/minecraft/core/BlockPos$MutableBlockPos;
       440: iload         27
       442: invokevirtual #1004               // Method net/minecraft/core/BlockPos$MutableBlockPos.setY:(I)Lnet/minecraft/core/BlockPos$MutableBlockPos;
       445: pop
       446: aload         29
       448: invokevirtual #1022               // Method net/minecraft/world/level/material/FluidState.isEmpty:()Z
       451: ifne          530
       454: iload         10
       456: ifeq          464
       459: iload         20
       461: ifne          530
       464: iconst_1
       465: istore        19
       467: aload_0
       468: getfield      #133                // Field fluidToBlock:Lxaero/map/misc/CachedFunction;
       471: aload         29
       473: invokevirtual #830                // Method xaero/map/misc/CachedFunction.apply:(Ljava/lang/Object;)Ljava/lang/Object;
       476: checkcast     #824                // class net/minecraft/world/level/block/state/BlockState
       479: astore        30
       481: aload_0
       482: aload_3
       483: aload         4
       485: aload_1
       486: aload_2
       487: aload         30
       489: iload         22
       491: iload         24
       493: aload         5
       495: iload         6
       497: iload         7
       499: iload         27
       501: iload         13
       503: iload         10
       505: aload         29
       507: aload         15
       509: iload         26
       511: iload         25
       513: iload         16
       515: iload         19
       517: invokevirtual #1040               // Method loadPixelHelp:(Lxaero/map/region/MapBlock;Lxaero/map/region/MapBlock;Lnet/minecraft/world/level/Level;Lnet/minecraft/core/Registry;Lnet/minecraft/world/level/block/state/BlockState;BBLnet/minecraft/world/level/chunk/LevelChunk;IIIZZLnet/minecraft/world/level/material/FluidState;Lnet/minecraft/core/Registry;IZZZ)Z
       520: ifeq          530
       523: aload         28
       525: astore        21
       527: goto          707
       530: aload         28
       532: invokevirtual #832                // Method net/minecraft/world/level/block/state/BlockState.getBlock:()Lnet/minecraft/world/level/block/Block;
       535: astore        30
       537: aload         30
       539: instanceof    #835                // class net/minecraft/world/level/block/AirBlock
       542: ifeq          551
       545: iconst_1
       546: istore        19
       548: goto          688
       551: iload         19
       553: ifne          559
       556: goto          688
       559: aload         28
       561: invokevirtual #832                // Method net/minecraft/world/level/block/state/BlockState.getBlock:()Lnet/minecraft/world/level/block/Block;
       564: aload_0
       565: getfield      #133                // Field fluidToBlock:Lxaero/map/misc/CachedFunction;
       568: aload         29
       570: invokevirtual #830                // Method xaero/map/misc/CachedFunction.apply:(Ljava/lang/Object;)Ljava/lang/Object;
       573: checkcast     #824                // class net/minecraft/world/level/block/state/BlockState
       576: invokevirtual #832                // Method net/minecraft/world/level/block/state/BlockState.getBlock:()Lnet/minecraft/world/level/block/Block;
       579: if_acmpne     585
       582: goto          688
       585: iload         10
       587: ifeq          640
       590: iload         20
       592: ifeq          640
       595: aload         28
       597: invokevirtual #1044               // Method net/minecraft/world/level/block/state/BlockState.ignitedByLava:()Z
       600: ifne          688
       603: aload         28
       605: invokevirtual #1047               // Method net/minecraft/world/level/block/state/BlockState.canBeReplaced:()Z
       608: ifne          688
       611: aload         28
       613: invokevirtual #1050               // Method net/minecraft/world/level/block/state/BlockState.getPistonPushReaction:()Lnet/minecraft/world/level/material/PushReaction;
       616: getstatic     #1054               // Field net/minecraft/world/level/material/PushReaction.DESTROY:Lnet/minecraft/world/level/material/PushReaction;
       619: if_acmpeq     688
       622: aload_0
       623: aload         28
       625: invokevirtual #1023               // Method shouldOverlayCached:(Lnet/minecraft/world/level/block/state/StateHolder;)Z
       628: ifne          688
       631: iconst_0
       632: istore        19
       634: iconst_0
       635: istore        20
       637: goto          688
       640: aload_0
       641: aload_3
       642: aload         4
       644: aload_1
       645: aload_2
       646: aload         28
       648: iload         22
       650: iload         24
       652: aload         5
       654: iload         6
       656: iload         7
       658: iload         27
       660: iload         13
       662: iload         10
       664: aconst_null
       665: aload         15
       667: iload         26
       669: iload         25
       671: iload         16
       673: iload         19
       675: invokevirtual #1040               // Method loadPixelHelp:(Lxaero/map/region/MapBlock;Lxaero/map/region/MapBlock;Lnet/minecraft/world/level/Level;Lnet/minecraft/core/Registry;Lnet/minecraft/world/level/block/state/BlockState;BBLnet/minecraft/world/level/chunk/LevelChunk;IIIZZLnet/minecraft/world/level/material/FluidState;Lnet/minecraft/core/Registry;IZZZ)Z
       678: ifeq          688
       681: aload         28
       683: astore        21
       685: goto          707
       688: iload         25
       690: ifeq          698
       693: iload         26
       695: goto          702
       698: iload         27
       700: iconst_1
       701: isub
       702: istore        27
       704: goto          116
       707: iload         27
       709: iload         9
       711: if_icmpge     718
       714: iload         9
       716: istore        27
       718: aconst_null
       719: astore        28
       721: aload         21
       723: ifnonnull     735
       726: getstatic     #995                // Field net/minecraft/world/level/block/Blocks.AIR:Lnet/minecraft/world/level/block/Block;
       729: invokevirtual #998                // Method net/minecraft/world/level/block/Block.defaultBlockState:()Lnet/minecraft/world/level/block/state/BlockState;
       732: goto          737
       735: aload         21
       737: astore        29
       739: aload_0
       740: getfield      #93                 // Field overlayBuilder:Lxaero/map/region/OverlayBuilder;
       743: aload_3
       744: invokevirtual #1060               // Method xaero/map/region/OverlayBuilder.finishBuilding:(Lxaero/map/region/MapBlock;)V
       747: iconst_0
       748: istore        30
       750: aload         21
       752: ifnull        792
       755: iload         22
       757: istore        30
       759: iload         10
       761: ifeq          796
       764: iload         30
       766: bipush        15
       768: if_icmpge     796
       771: aload_3
       772: invokevirtual #1064               // Method xaero/map/region/MapBlock.getNumberOfOverlays:()I
       775: ifne          796
       778: iload         24
       780: iload         30
       782: if_icmple     796
       785: iload         24
       787: istore        30
       789: goto          796
       792: iload         17
       794: istore        27
       796: iload         13
       798: ifeq          828
       801: aload         4
       803: ifnull        828
       806: aload         4
       808: invokevirtual #1067               // Method xaero/map/region/MapBlock.getState:()Lnet/minecraft/world/level/block/state/BlockState;
       811: aload         29
       813: if_acmpne     828
       816: aload         4
       818: invokevirtual #1070               // Method xaero/map/region/MapBlock.getTopHeight:()I
       821: aload_0
       822: getfield      #972                // Field topH:I
       825: if_icmpeq     869
       828: aload_0
       829: getfield      #104                // Field mutableGlobalPos:Lnet/minecraft/core/BlockPos$MutableBlockPos;
       832: aload_0
       833: getfield      #972                // Field topH:I
       836: invokevirtual #1004               // Method net/minecraft/core/BlockPos$MutableBlockPos.setY:(I)Lnet/minecraft/core/BlockPos$MutableBlockPos;
       839: pop
       840: aload_0
       841: getfield      #136                // Field biomeGetter:Lxaero/map/biome/BiomeGetter;
       844: aload_1
       845: aload_0
       846: getfield      #104                // Field mutableGlobalPos:Lnet/minecraft/core/BlockPos$MutableBlockPos;
       849: aload         15
       851: invokevirtual #1073               // Method xaero/map/biome/BiomeGetter.getBiome:(Lnet/minecraft/world/level/Level;Lnet/minecraft/core/BlockPos;Lnet/minecraft/core/Registry;)Lnet/minecraft/resources/ResourceKey;
       854: astore        28
       856: aload_0
       857: getfield      #104                // Field mutableGlobalPos:Lnet/minecraft/core/BlockPos$MutableBlockPos;
       860: iload         27
       862: invokevirtual #1004               // Method net/minecraft/core/BlockPos$MutableBlockPos.setY:(I)Lnet/minecraft/core/BlockPos$MutableBlockPos;
       865: pop
       866: goto          876
       869: aload         4
       871: invokevirtual #1079               // Method xaero/map/region/MapBlock.getBiome:()Lnet/minecraft/resources/ResourceKey;
       874: astore        28
       876: aload_0
       877: getfield      #93                 // Field overlayBuilder:Lxaero/map/region/OverlayBuilder;
       880: invokevirtual #1081               // Method xaero/map/region/OverlayBuilder.getOverlayBiome:()Lnet/minecraft/resources/ResourceKey;
       883: ifnull        895
       886: aload_0
       887: getfield      #93                 // Field overlayBuilder:Lxaero/map/region/OverlayBuilder;
       890: invokevirtual #1081               // Method xaero/map/region/OverlayBuilder.getOverlayBiome:()Lnet/minecraft/resources/ResourceKey;
       893: astore        28
       895: aload_0
       896: aload         29
       898: invokevirtual #1084               // Method isGlowing:(Lnet/minecraft/world/level/block/state/BlockState;)Z
       901: istore        31
       903: aload_3
       904: aload         29
       906: iload         27
       908: aload_0
       909: getfield      #972                // Field topH:I
       912: aload         28
       914: iload         30
       916: iload         31
       918: iload         10
       920: invokevirtual #1087               // Method xaero/map/region/MapBlock.write:(Lnet/minecraft/world/level/block/state/BlockState;IILnet/minecraft/resources/ResourceKey;BZZ)V
       923: return

  private boolean loadPixelHelp(xaero.map.region.MapBlock, xaero.map.region.MapBlock, net.minecraft.world.level.Level, net.minecraft.core.Registry<net.minecraft.world.level.block.Block>, net.minecraft.world.level.block.state.BlockState, byte, byte, net.minecraft.world.level.chunk.LevelChunk, int, int, int, boolean, boolean, net.minecraft.world.level.material.FluidState, net.minecraft.core.Registry<net.minecraft.world.level.biome.Biome>, int, boolean, boolean, boolean);
    Code:
         0: aload         5
         2: invokevirtual #832                // Method net/minecraft/world/level/block/state/BlockState.getBlock:()Lnet/minecraft/world/level/block/Block;
         5: astore        20
         7: aload_0
         8: aload         5
        10: aload         20
        12: iload         18
        14: invokevirtual #1091               // Method isInvisible:(Lnet/minecraft/world/level/block/state/BlockState;Lnet/minecraft/world/level/block/Block;Z)Z
        17: ifeq          22
        20: iconst_0
        21: ireturn
        22: aload_0
        23: aload         14
        25: ifnonnull     33
        28: aload         5
        30: goto          35
        33: aload         14
        35: invokevirtual #1023               // Method shouldOverlayCached:(Lnet/minecraft/world/level/block/state/StateHolder;)Z
        38: ifeq          239
        41: iload         13
        43: ifeq          53
        46: iload         19
        48: ifne          53
        51: iconst_0
        52: ireturn
        53: iload         11
        55: aload_0
        56: getfield      #972                // Field topH:I
        59: if_icmple     68
        62: aload_0
        63: iload         11
        65: putfield      #972                // Field topH:I
        68: iload         6
        70: istore        21
        72: aload_0
        73: getfield      #93                 // Field overlayBuilder:Lxaero/map/region/OverlayBuilder;
        76: invokevirtual #1016               // Method xaero/map/region/OverlayBuilder.isEmpty:()Z
        79: ifeq          104
        82: aload_0
        83: iload         11
        85: putfield      #1019               // Field firstTransparentStateY:I
        88: iload         13
        90: ifeq          104
        93: iload         7
        95: iload         21
        97: if_icmple     104
       100: iload         7
       102: istore        21
       104: iload         17
       106: ifeq          141
       109: aload_0
       110: getfield      #93                 // Field overlayBuilder:Lxaero/map/region/OverlayBuilder;
       113: invokevirtual #1095               // Method xaero/map/region/OverlayBuilder.getCurrentOverlay:()Lxaero/map/region/Overlay;
       116: aload_0
       117: getfield      #93                 // Field overlayBuilder:Lxaero/map/region/OverlayBuilder;
       120: invokevirtual #1095               // Method xaero/map/region/OverlayBuilder.getCurrentOverlay:()Lxaero/map/region/Overlay;
       123: invokevirtual #1099               // Method xaero/map/region/Overlay.getState:()Lnet/minecraft/world/level/block/state/BlockState;
       126: invokevirtual #1102               // Method net/minecraft/world/level/block/state/BlockState.getLightDampening:()I
       129: iload         11
       131: iload         16
       133: isub
       134: imul
       135: invokevirtual #1105               // Method xaero/map/region/Overlay.increaseOpacity:(I)V
       138: goto          237
       141: aload_0
       142: getfield      #93                 // Field overlayBuilder:Lxaero/map/region/OverlayBuilder;
       145: invokevirtual #1081               // Method xaero/map/region/OverlayBuilder.getOverlayBiome:()Lnet/minecraft/resources/ResourceKey;
       148: astore        22
       150: aload         22
       152: ifnonnull     215
       155: iload         12
       157: ifeq          199
       160: aload_2
       161: ifnull        199
       164: aload_2
       165: invokevirtual #1064               // Method xaero/map/region/MapBlock.getNumberOfOverlays:()I
       168: ifle          199
       171: aload_2
       172: invokevirtual #1108               // Method xaero/map/region/MapBlock.getOverlays:()Ljava/util/ArrayList;
       175: iconst_0
       176: invokevirtual #464                // Method java/util/ArrayList.get:(I)Ljava/lang/Object;
       179: checkcast     #1100               // class xaero/map/region/Overlay
       182: invokevirtual #1099               // Method xaero/map/region/Overlay.getState:()Lnet/minecraft/world/level/block/state/BlockState;
       185: aload         5
       187: if_acmpne     199
       190: aload_2
       191: invokevirtual #1079               // Method xaero/map/region/MapBlock.getBiome:()Lnet/minecraft/resources/ResourceKey;
       194: astore        22
       196: goto          215
       199: aload_0
       200: getfield      #136                // Field biomeGetter:Lxaero/map/biome/BiomeGetter;
       203: aload_3
       204: aload_0
       205: getfield      #104                // Field mutableGlobalPos:Lnet/minecraft/core/BlockPos$MutableBlockPos;
       208: aload         15
       210: invokevirtual #1073               // Method xaero/map/biome/BiomeGetter.getBiome:(Lnet/minecraft/world/level/Level;Lnet/minecraft/core/BlockPos;Lnet/minecraft/core/Registry;)Lnet/minecraft/resources/ResourceKey;
       213: astore        22
       215: aload_0
       216: getfield      #93                 // Field overlayBuilder:Lxaero/map/region/OverlayBuilder;
       219: aload         5
       221: aload         5
       223: invokevirtual #1102               // Method net/minecraft/world/level/block/state/BlockState.getLightDampening:()I
       226: iload         21
       228: aload_0
       229: getfield      #202                // Field mapProcessor:Lxaero/map/MapProcessor;
       232: aload         22
       234: invokevirtual #1112               // Method xaero/map/region/OverlayBuilder.build:(Lnet/minecraft/world/level/block/state/BlockState;IBLxaero/map/MapProcessor;Lnet/minecraft/resources/ResourceKey;)V
       237: iconst_0
       238: ireturn
       239: aload_0
       240: aload         5
       242: aload_3
       243: aload         4
       245: aload_0
       246: getfield      #104                // Field mutableGlobalPos:Lnet/minecraft/core/BlockPos$MutableBlockPos;
       249: invokevirtual #1116               // Method hasVanillaColor:(Lnet/minecraft/world/level/block/state/BlockState;Lnet/minecraft/world/level/Level;Lnet/minecraft/core/Registry;Lnet/minecraft/core/BlockPos;)Z
       252: ifne          257
       255: iconst_0
       256: ireturn
       257: iload         13
       259: ifeq          269
       262: iload         19
       264: ifne          269
       267: iconst_1
       268: ireturn
       269: iload         11
       271: aload_0
       272: getfield      #972                // Field topH:I
       275: if_icmple     284
       278: aload_0
       279: iload         11
       281: putfield      #972                // Field topH:I
       284: iconst_1
       285: ireturn

  protected abstract java.util.List<net.minecraft.client.resources.model.geometry.BakedQuad> getQuads(net.minecraft.client.renderer.block.dispatch.BlockStateModel, net.minecraft.client.multiplayer.ClientLevel, net.minecraft.core.BlockPos, net.minecraft.world.level.block.state.BlockState, net.minecraft.core.Direction);

  protected abstract net.minecraft.client.renderer.texture.TextureAtlasSprite getParticleIcon(net.minecraft.client.renderer.block.BlockStateModelSet, net.minecraft.client.renderer.block.dispatch.BlockStateModel, net.minecraft.client.multiplayer.ClientLevel, net.minecraft.core.BlockPos, net.minecraft.world.level.block.state.BlockState);

  public int loadBlockColourFromTexture(net.minecraft.world.level.block.state.BlockState, boolean, net.minecraft.client.multiplayer.ClientLevel, net.minecraft.core.Registry<net.minecraft.world.level.block.Block>, net.minecraft.core.BlockPos);
    Code:
         0: aload_0
         1: getfield      #1120               // Field clearCachedColours:Z
         4: ifeq          62
         7: aload_0
         8: getfield      #81                 // Field textureColours:Ljava/util/HashMap;
        11: invokevirtual #1123               // Method java/util/HashMap.clear:()V
        14: aload_0
        15: getfield      #85                 // Field blockColours:Ljava/util/HashMap;
        18: invokevirtual #1123               // Method java/util/HashMap.clear:()V
        21: aload_0
        22: getfield      #143                // Field blockTintIndices:Lit/unimi/dsi/fastutil/objects/Object2IntMap;
        25: invokeinterface #1124,  1         // InterfaceMethod it/unimi/dsi/fastutil/objects/Object2IntMap.clear:()V
        30: aload_0
        31: aconst_null
        32: putfield      #50                 // Field lastBlockStateForTextureColor:Lnet/minecraft/world/level/block/state/BlockState;
        35: aload_0
        36: iconst_m1
        37: putfield      #54                 // Field lastBlockStateForTextureColorResult:I
        40: aload_0
        41: iconst_0
        42: putfield      #1120               // Field clearCachedColours:Z
        45: invokestatic  #1127               // Method xaero/map/config/util/WorldMapClientConfigUtils.getDebug:()Z
        48: ifeq          62
        51: getstatic     #904                // Field xaero/map/WorldMap.LOGGER:Lorg/apache/logging/log4j/Logger;
        54: ldc_w         #1132               // String Xaero\'s World Map cache cleared!
        57: invokeinterface #923,  2          // InterfaceMethod org/apache/logging/log4j/Logger.info:(Ljava/lang/String;)V
        62: aload_1
        63: aload_0
        64: getfield      #50                 // Field lastBlockStateForTextureColor:Lnet/minecraft/world/level/block/state/BlockState;
        67: if_acmpne     75
        70: aload_0
        71: getfield      #54                 // Field lastBlockStateForTextureColorResult:I
        74: ireturn
        75: aload_0
        76: getfield      #85                 // Field blockColours:Ljava/util/HashMap;
        79: aload_1
        80: invokevirtual #1134               // Method java/util/HashMap.get:(Ljava/lang/Object;)Ljava/lang/Object;
        83: checkcast     #9                  // class java/lang/Integer
        86: astore        6
        88: iconst_0
        89: istore        7
        91: iconst_0
        92: istore        8
        94: iconst_0
        95: istore        9
        97: iconst_0
        98: istore        10
       100: aload_1
       101: invokevirtual #832                // Method net/minecraft/world/level/block/state/BlockState.getBlock:()Lnet/minecraft/world/level/block/Block;
       104: astore        11
       106: aload         6
       108: ifnonnull     1108
       111: aconst_null
       112: astore        12
       114: iconst_m1
       115: istore        13
       117: aconst_null
       118: astore        14
       120: invokestatic  #151                // Method net/minecraft/client/Minecraft.getInstance:()Lnet/minecraft/client/Minecraft;
       123: invokevirtual #157                // Method net/minecraft/client/Minecraft.getModelManager:()Lnet/minecraft/client/resources/model/ModelManager;
       126: invokevirtual #1135               // Method net/minecraft/client/resources/model/ModelManager.getBlockStateModelSet:()Lnet/minecraft/client/renderer/block/BlockStateModelSet;
       129: astore        15
       131: aload         15
       133: aload_1
       134: invokevirtual #1139               // Method net/minecraft/client/renderer/block/BlockStateModelSet.get:(Lnet/minecraft/world/level/block/state/BlockState;)Lnet/minecraft/client/renderer/block/dispatch/BlockStateModel;
       137: astore        16
       139: iload_2
       140: ifeq          158
       143: aload_0
       144: aload         16
       146: aload_3
       147: aload         5
       149: aload_1
       150: getstatic     #1144               // Field net/minecraft/core/Direction.UP:Lnet/minecraft/core/Direction;
       153: invokevirtual #1150               // Method getQuads:(Lnet/minecraft/client/renderer/block/dispatch/BlockStateModel;Lnet/minecraft/client/multiplayer/ClientLevel;Lnet/minecraft/core/BlockPos;Lnet/minecraft/world/level/block/state/BlockState;Lnet/minecraft/core/Direction;)Ljava/util/List;
       156: astore        14
       158: invokestatic  #151                // Method net/minecraft/client/Minecraft.getInstance:()Lnet/minecraft/client/Minecraft;
       161: invokevirtual #1154               // Method net/minecraft/client/Minecraft.getAtlasManager:()Lnet/minecraft/client/resources/model/sprite/AtlasManager;
       164: getstatic     #1158               // Field net/minecraft/data/AtlasIds.BLOCKS:Lnet/minecraft/resources/Identifier;
       167: invokevirtual #1164               // Method net/minecraft/client/resources/model/sprite/AtlasManager.getAtlasOrThrow:(Lnet/minecraft/resources/Identifier;)Lnet/minecraft/client/renderer/texture/TextureAtlas;
       170: invokestatic  #1170               // Method net/minecraft/client/renderer/texture/MissingTextureAtlasSprite.getLocation:()Lnet/minecraft/resources/Identifier;
       173: invokevirtual #1176               // Method net/minecraft/client/renderer/texture/TextureAtlas.getSprite:(Lnet/minecraft/resources/Identifier;)Lnet/minecraft/client/renderer/texture/TextureAtlasSprite;
       176: astore        18
       178: aload         14
       180: ifnull        214
       183: aload         14
       185: invokeinterface #1182,  1         // InterfaceMethod java/util/List.isEmpty:()Z
       190: ifne          214
       193: aload         14
       195: invokeinterface #1185,  1         // InterfaceMethod java/util/List.getFirst:()Ljava/lang/Object;
       200: checkcast     #1188               // class net/minecraft/client/resources/model/geometry/BakedQuad
       203: invokevirtual #1190               // Method net/minecraft/client/resources/model/geometry/BakedQuad.materialInfo:()Lnet/minecraft/client/resources/model/geometry/BakedQuad$MaterialInfo;
       206: invokevirtual #1194               // Method net/minecraft/client/resources/model/geometry/BakedQuad$MaterialInfo.sprite:()Lnet/minecraft/client/renderer/texture/TextureAtlasSprite;
       209: aload         18
       211: if_acmpne     234
       214: aload_0
       215: aload         15
       217: aload         16
       219: aload_3
       220: aload         5
       222: aload_1
       223: invokevirtual #1200               // Method getParticleIcon:(Lnet/minecraft/client/renderer/block/BlockStateModelSet;Lnet/minecraft/client/renderer/block/dispatch/BlockStateModel;Lnet/minecraft/client/multiplayer/ClientLevel;Lnet/minecraft/core/BlockPos;Lnet/minecraft/world/level/block/state/BlockState;)Lnet/minecraft/client/renderer/texture/TextureAtlasSprite;
       226: astore        17
       228: iconst_0
       229: istore        13
       231: goto          270
       234: aload         14
       236: invokeinterface #1185,  1         // InterfaceMethod java/util/List.getFirst:()Ljava/lang/Object;
       241: checkcast     #1188               // class net/minecraft/client/resources/model/geometry/BakedQuad
       244: invokevirtual #1190               // Method net/minecraft/client/resources/model/geometry/BakedQuad.materialInfo:()Lnet/minecraft/client/resources/model/geometry/BakedQuad$MaterialInfo;
       247: invokevirtual #1194               // Method net/minecraft/client/resources/model/geometry/BakedQuad$MaterialInfo.sprite:()Lnet/minecraft/client/renderer/texture/TextureAtlasSprite;
       250: astore        17
       252: aload         14
       254: invokeinterface #1185,  1         // InterfaceMethod java/util/List.getFirst:()Ljava/lang/Object;
       259: checkcast     #1188               // class net/minecraft/client/resources/model/geometry/BakedQuad
       262: invokevirtual #1190               // Method net/minecraft/client/resources/model/geometry/BakedQuad.materialInfo:()Lnet/minecraft/client/resources/model/geometry/BakedQuad$MaterialInfo;
       265: invokevirtual #1204               // Method net/minecraft/client/resources/model/geometry/BakedQuad$MaterialInfo.tintIndex:()I
       268: istore        13
       270: aload         17
       272: ifnonnull     292
       275: new           #1207               // class xaero/map/exception/SilentException
       278: dup
       279: aload_1
       280: invokestatic  #914                // Method java/lang/String.valueOf:(Ljava/lang/Object;)Ljava/lang/String;
       283: invokedynamic #1209,  0           // InvokeDynamic #6:makeConcatWithConstants:(Ljava/lang/String;)Ljava/lang/String;
       288: invokespecial #1210               // Method xaero/map/exception/SilentException."<init>":(Ljava/lang/String;)V
       291: athrow
       292: iconst_m1
       293: invokestatic  #1212               // Method java/lang/Integer.valueOf:(I)Ljava/lang/Integer;
       296: astore        6
       298: aload         17
       300: invokevirtual #1215               // Method net/minecraft/client/renderer/texture/TextureAtlasSprite.contents:()Lnet/minecraft/client/renderer/texture/SpriteContents;
       303: invokevirtual #1221               // Method net/minecraft/client/renderer/texture/SpriteContents.name:()Lnet/minecraft/resources/Identifier;
       306: invokestatic  #914                // Method java/lang/String.valueOf:(Ljava/lang/Object;)Ljava/lang/String;
       309: invokedynamic #1226,  0           // InvokeDynamic #7:makeConcatWithConstants:(Ljava/lang/String;)Ljava/lang/String;
       314: astore        12
       316: aload         12
       318: ldc_w         #1227               // String :
       321: invokevirtual #1229               // Method java/lang/String.split:(Ljava/lang/String;)[Ljava/lang/String;
       324: astore        19
       326: aload         19
       328: arraylength
       329: iconst_2
       330: if_icmpge     347
       333: getstatic     #1233               // Field DEFAULT_RESOURCE:[Ljava/lang/String;
       336: iconst_1
       337: aload         19
       339: iconst_0
       340: aaload
       341: aastore
       342: getstatic     #1233               // Field DEFAULT_RESOURCE:[Ljava/lang/String;
       345: astore        19
       347: aload_0
       348: getfield      #81                 // Field textureColours:Ljava/util/HashMap;
       351: aload         12
       353: invokevirtual #1134               // Method java/util/HashMap.get:(Ljava/lang/Object;)Ljava/lang/Object;
       356: checkcast     #9                  // class java/lang/Integer
       359: astore        20
       361: aload         20
       363: ifnonnull     862
       366: aload         19
       368: iconst_0
       369: aaload
       370: aload         19
       372: iconst_1
       373: aaload
       374: invokedynamic #1237,  0           // InvokeDynamic #8:makeConcatWithConstants:(Ljava/lang/String;)Ljava/lang/String;
       379: invokestatic  #1238               // Method net/minecraft/resources/Identifier.fromNamespaceAndPath:(Ljava/lang/String;Ljava/lang/String;)Lnet/minecraft/resources/Identifier;
       382: astore        21
       384: invokestatic  #151                // Method net/minecraft/client/Minecraft.getInstance:()Lnet/minecraft/client/Minecraft;
       387: invokevirtual #1244               // Method net/minecraft/client/Minecraft.getResourceManager:()Lnet/minecraft/server/packs/resources/ResourceManager;
       390: aload         21
       392: invokeinterface #1248,  2         // InterfaceMethod net/minecraft/server/packs/resources/ResourceManager.getResource:(Lnet/minecraft/resources/Identifier;)Ljava/util/Optional;
       397: aconst_null
       398: invokevirtual #1254               // Method java/util/Optional.orElse:(Ljava/lang/Object;)Ljava/lang/Object;
       401: checkcast     #1259               // class net/minecraft/server/packs/resources/Resource
       404: astore        22
       406: aload         22
       408: ifnonnull     429
       411: new           #1207               // class xaero/map/exception/SilentException
       414: dup
       415: aload         21
       417: invokestatic  #914                // Method java/lang/String.valueOf:(Ljava/lang/Object;)Ljava/lang/String;
       420: invokedynamic #1261,  0           // InvokeDynamic #9:makeConcatWithConstants:(Ljava/lang/String;)Ljava/lang/String;
       425: invokespecial #1210               // Method xaero/map/exception/SilentException."<init>":(Ljava/lang/String;)V
       428: athrow
       429: aload         22
       431: invokevirtual #1262               // Method net/minecraft/server/packs/resources/Resource.open:()Ljava/io/InputStream;
       434: astore        23
       436: aload         23
       438: invokestatic  #1266               // Method javax/imageio/ImageIO.createImageInputStream:(Ljava/lang/Object;)Ljavax/imageio/stream/ImageInputStream;
       441: astore        24
       443: aload         24
       445: aload         21
       447: invokevirtual #1272               // Method net/minecraft/resources/Identifier.toString:()Ljava/lang/String;
       450: invokestatic  #1275               // Method xaero/lib/common/util/ImageIOUtils.getImageThroughZipError:(Ljavax/imageio/stream/ImageInputStream;Ljava/lang/String;)Ljava/awt/image/BufferedImage;
       453: astore        25
       455: aload         24
       457: invokeinterface #1281,  1         // InterfaceMethod javax/imageio/stream/ImageInputStream.close:()V
       462: aload         25
       464: ifnonnull     485
       467: new           #1207               // class xaero/map/exception/SilentException
       470: dup
       471: aload         21
       473: invokestatic  #914                // Method java/lang/String.valueOf:(Ljava/lang/Object;)Ljava/lang/String;
       476: invokedynamic #1286,  0           // InvokeDynamic #10:makeConcatWithConstants:(Ljava/lang/String;)Ljava/lang/String;
       481: invokespecial #1210               // Method xaero/map/exception/SilentException."<init>":(Ljava/lang/String;)V
       484: athrow
       485: iconst_0
       486: istore        7
       488: iconst_0
       489: istore        8
       491: iconst_0
       492: istore        9
       494: iconst_0
       495: istore        26
       497: aload         25
       499: invokevirtual #1287               // Method java/awt/image/BufferedImage.getWidth:()I
       502: aload         25
       504: invokevirtual #1292               // Method java/awt/image/BufferedImage.getHeight:()I
       507: invokestatic  #505                // Method java/lang/Math.min:(II)I
       510: istore        27
       512: iload         27
       514: ifle          752
       517: iconst_1
       518: iconst_4
       519: iload         27
       521: bipush        8
       523: idiv
       524: invokestatic  #505                // Method java/lang/Math.min:(II)I
       527: invokestatic  #349                // Method java/lang/Math.max:(II)I
       530: istore        28
       532: iload         27
       534: iload         28
       536: idiv
       537: istore        29
       539: aload         25
       541: invokevirtual #1294               // Method java/awt/image/BufferedImage.getData:()Ljava/awt/image/Raster;
       544: astore        30
       546: aconst_null
       547: astore        31
       549: iconst_0
       550: istore        32
       552: iload         32
       554: iload         29
       556: if_icmpge     752
       559: iconst_0
       560: istore        33
       562: iload         33
       564: iload         29
       566: if_icmpge     746
       569: aload         25
       571: invokevirtual #1298               // Method java/awt/image/BufferedImage.getColorModel:()Ljava/awt/image/ColorModel;
       574: invokevirtual #1302               // Method java/awt/image/ColorModel.getNumComponents:()I
       577: iconst_3
       578: if_icmpge     653
       581: aload         30
       583: iload         32
       585: iload         28
       587: imul
       588: iload         33
       590: iload         28
       592: imul
       593: aload         31
       595: invokevirtual #1307               // Method java/awt/image/Raster.getPixel:(II[I)[I
       598: astore        31
       600: aload         31
       602: iconst_0
       603: iaload
       604: sipush        255
       607: iand
       608: istore        35
       610: sipush        255
       613: istore        36
       615: aload         31
       617: arraylength
       618: iconst_1
       619: if_icmple     628
       622: aload         31
       624: iconst_1
       625: iaload
       626: istore        36
       628: iload         36
       630: bipush        24
       632: ishl
       633: iload         35
       635: bipush        16
       637: ishl
       638: ior
       639: iload         35
       641: bipush        8
       643: ishl
       644: ior
       645: iload         35
       647: ior
       648: istore        34
       650: goto          670
       653: aload         25
       655: iload         32
       657: iload         28
       659: imul
       660: iload         33
       662: iload         28
       664: imul
       665: invokevirtual #1313               // Method java/awt/image/BufferedImage.getRGB:(II)I
       668: istore        34
       670: iload         34
       672: bipush        24
       674: ishr
       675: sipush        255
       678: iand
       679: istore        35
       681: iload         34
       683: ifeq          740
       686: iload         35
       688: ifeq          740
       691: iload         7
       693: iload         34
       695: bipush        16
       697: ishr
       698: sipush        255
       701: iand
       702: iadd
       703: istore        7
       705: iload         8
       707: iload         34
       709: bipush        8
       711: ishr
       712: sipush        255
       715: iand
       716: iadd
       717: istore        8
       719: iload         9
       721: iload         34
       723: sipush        255
       726: iand
       727: iadd
       728: istore        9
       730: iload         10
       732: iload         35
       734: iadd
       735: istore        10
       737: iinc          26, 1
       740: iinc          33, 1
       743: goto          562
       746: iinc          32, 1
       749: goto          552
       752: iload         26
       754: ifne          760
       757: iconst_1
       758: istore        26
       760: iload         7
       762: iload         26
       764: idiv
       765: istore        7
       767: iload         8
       769: iload         26
       771: idiv
       772: istore        8
       774: iload         9
       776: iload         26
       778: idiv
       779: istore        9
       781: iload         10
       783: iload         26
       785: idiv
       786: istore        10
       788: iload_2
       789: ifeq          822
       792: iload         7
       794: ifne          822
       797: iload         8
       799: ifne          822
       802: iload         9
       804: ifne          822
       807: new           #1207               // class xaero/map/exception/SilentException
       810: dup
       811: iload         27
       813: invokedynamic #1316,  0           // InvokeDynamic #11:makeConcatWithConstants:(I)Ljava/lang/String;
       818: invokespecial #1210               // Method xaero/map/exception/SilentException."<init>":(Ljava/lang/String;)V
       821: athrow
       822: iload         10
       824: bipush        24
       826: ishl
       827: iload         7
       829: bipush        16
       831: ishl
       832: ior
       833: iload         8
       835: bipush        8
       837: ishl
       838: ior
       839: iload         9
       841: ior
       842: invokestatic  #1212               // Method java/lang/Integer.valueOf:(I)Ljava/lang/Integer;
       845: astore        6
       847: aload_0
       848: getfield      #81                 // Field textureColours:Ljava/util/HashMap;
       851: aload         12
       853: aload         6
       855: invokevirtual #1319               // Method java/util/HashMap.put:(Ljava/lang/Object;Ljava/lang/Object;)Ljava/lang/Object;
       858: pop
       859: goto          866
       862: aload         20
       864: astore        6
       866: goto          1079
       869: astore        14
       871: iload_2
       872: ifeq          887
       875: aload_0
       876: aload_1
       877: iconst_0
       878: aload_3
       879: aload         4
       881: aload         5
       883: invokevirtual #1325               // Method loadBlockColourFromTexture:(Lnet/minecraft/world/level/block/state/BlockState;ZLnet/minecraft/client/multiplayer/ClientLevel;Lnet/minecraft/core/Registry;Lnet/minecraft/core/BlockPos;)I
       886: ireturn
       887: getstatic     #904                // Field xaero/map/WorldMap.LOGGER:Lorg/apache/logging/log4j/Logger;
       890: aload         4
       892: aload         11
       894: invokeinterface #908,  2          // InterfaceMethod net/minecraft/core/Registry.getKey:(Ljava/lang/Object;)Lnet/minecraft/resources/Identifier;
       899: invokestatic  #914                // Method java/lang/String.valueOf:(Ljava/lang/Object;)Ljava/lang/String;
       902: invokedynamic #1329,  0           // InvokeDynamic #12:makeConcatWithConstants:(Ljava/lang/String;)Ljava/lang/String;
       907: invokeinterface #923,  2          // InterfaceMethod org/apache/logging/log4j/Logger.info:(Ljava/lang/String;)V
       912: iconst_0
       913: invokestatic  #1212               // Method java/lang/Integer.valueOf:(I)Ljava/lang/Integer;
       916: astore        6
       918: aload_1
       919: ifnull        947
       922: aload_1
       923: aload_3
       924: aload         5
       926: invokevirtual #897                // Method net/minecraft/world/level/block/state/BlockState.getMapColor:(Lnet/minecraft/world/level/BlockGetter;Lnet/minecraft/core/BlockPos;)Lnet/minecraft/world/level/material/MapColor;
       929: ifnull        947
       932: aload_1
       933: aload_3
       934: aload         5
       936: invokevirtual #897                // Method net/minecraft/world/level/block/state/BlockState.getMapColor:(Lnet/minecraft/world/level/BlockGetter;Lnet/minecraft/core/BlockPos;)Lnet/minecraft/world/level/material/MapColor;
       939: getfield      #929                // Field net/minecraft/world/level/material/MapColor.col:I
       942: invokestatic  #1212               // Method java/lang/Integer.valueOf:(I)Ljava/lang/Integer;
       945: astore        6
       947: aload         12
       949: ifnull        964
       952: aload_0
       953: getfield      #81                 // Field textureColours:Ljava/util/HashMap;
       956: aload         12
       958: aload         6
       960: invokevirtual #1319               // Method java/util/HashMap.put:(Ljava/lang/Object;Ljava/lang/Object;)Ljava/lang/Object;
       963: pop
       964: goto          1079
       967: astore        14
       969: getstatic     #904                // Field xaero/map/WorldMap.LOGGER:Lorg/apache/logging/log4j/Logger;
       972: aload         4
       974: aload         11
       976: invokeinterface #908,  2          // InterfaceMethod net/minecraft/core/Registry.getKey:(Ljava/lang/Object;)Lnet/minecraft/resources/Identifier;
       981: invokestatic  #914                // Method java/lang/String.valueOf:(Ljava/lang/Object;)Ljava/lang/String;
       984: invokedynamic #1332,  0           // InvokeDynamic #13:makeConcatWithConstants:(Ljava/lang/String;)Ljava/lang/String;
       989: invokeinterface #923,  2          // InterfaceMethod org/apache/logging/log4j/Logger.info:(Ljava/lang/String;)V
       994: iconst_0
       995: invokestatic  #1212               // Method java/lang/Integer.valueOf:(I)Ljava/lang/Integer;
       998: astore        6
      1000: aload_1
      1001: aload_3
      1002: aload         5
      1004: invokevirtual #897                // Method net/minecraft/world/level/block/state/BlockState.getMapColor:(Lnet/minecraft/world/level/BlockGetter;Lnet/minecraft/core/BlockPos;)Lnet/minecraft/world/level/material/MapColor;
      1007: ifnull        1025
      1010: aload_1
      1011: aload_3
      1012: aload         5
      1014: invokevirtual #897                // Method net/minecraft/world/level/block/state/BlockState.getMapColor:(Lnet/minecraft/world/level/BlockGetter;Lnet/minecraft/core/BlockPos;)Lnet/minecraft/world/level/material/MapColor;
      1017: getfield      #929                // Field net/minecraft/world/level/material/MapColor.col:I
      1020: invokestatic  #1212               // Method java/lang/Integer.valueOf:(I)Ljava/lang/Integer;
      1023: astore        6
      1025: aload         12
      1027: ifnull        1042
      1030: aload_0
      1031: getfield      #81                 // Field textureColours:Ljava/util/HashMap;
      1034: aload         12
      1036: aload         6
      1038: invokevirtual #1319               // Method java/util/HashMap.put:(Ljava/lang/Object;Ljava/lang/Object;)Ljava/lang/Object;
      1041: pop
      1042: aload         14
      1044: instanceof    #1207               // class xaero/map/exception/SilentException
      1047: ifeq          1066
      1050: getstatic     #904                // Field xaero/map/WorldMap.LOGGER:Lorg/apache/logging/log4j/Logger;
      1053: aload         14
      1055: invokevirtual #1333               // Method java/lang/Exception.getMessage:()Ljava/lang/String;
      1058: invokeinterface #923,  2          // InterfaceMethod org/apache/logging/log4j/Logger.info:(Ljava/lang/String;)V
      1063: goto          1079
      1066: getstatic     #904                // Field xaero/map/WorldMap.LOGGER:Lorg/apache/logging/log4j/Logger;
      1069: ldc_w         #1336               // String suppressed exception
      1072: aload         14
      1074: invokeinterface #1338,  3         // InterfaceMethod org/apache/logging/log4j/Logger.error:(Ljava/lang/String;Ljava/lang/Throwable;)V
      1079: aload         6
      1081: ifnull        1108
      1084: aload_0
      1085: getfield      #85                 // Field blockColours:Ljava/util/HashMap;
      1088: aload_1
      1089: aload         6
      1091: invokevirtual #1319               // Method java/util/HashMap.put:(Ljava/lang/Object;Ljava/lang/Object;)Ljava/lang/Object;
      1094: pop
      1095: aload_0
      1096: getfield      #143                // Field blockTintIndices:Lit/unimi/dsi/fastutil/objects/Object2IntMap;
      1099: aload_1
      1100: iload         13
      1102: invokeinterface #1342,  3         // InterfaceMethod it/unimi/dsi/fastutil/objects/Object2IntMap.put:(Ljava/lang/Object;I)I
      1107: pop
      1108: aload_0
      1109: aload_1
      1110: putfield      #50                 // Field lastBlockStateForTextureColor:Lnet/minecraft/world/level/block/state/BlockState;
      1113: aload_0
      1114: aload         6
      1116: invokevirtual #394                // Method java/lang/Integer.intValue:()I
      1119: putfield      #54                 // Field lastBlockStateForTextureColorResult:I
      1122: aload         6
      1124: invokevirtual #394                // Method java/lang/Integer.intValue:()I
      1127: ireturn
      Exception table:
         from    to  target type
           117   866   869   Class java/io/FileNotFoundException
           117   866   967   Class java/lang/Exception

  public long getUpdateCounter();
    Code:
         0: aload_0
         1: getfield      #507                // Field updateCounter:J
         4: lreturn

  public void resetPosition();
    Code:
         0: aload_0
         1: iconst_0
         2: putfield      #518                // Field X:I
         5: aload_0
         6: iconst_0
         7: putfield      #521                // Field Z:I
        10: aload_0
        11: iconst_0
        12: putfield      #512                // Field insideX:I
        15: aload_0
        16: iconst_0
        17: putfield      #515                // Field insideZ:I
        20: return

  public void requestCachedColoursClear();
    Code:
         0: aload_0
         1: iconst_1
         2: putfield      #328                // Field clearTransparencyCache:Z
         5: aload_0
         6: iconst_1
         7: putfield      #1120               // Field clearCachedColours:Z
        10: return

  public void setMapProcessor(xaero.map.MapProcessor);
    Code:
         0: aload_0
         1: aload_1
         2: putfield      #202                // Field mapProcessor:Lxaero/map/MapProcessor;
         5: return

  public xaero.map.MapProcessor getMapProcessor();
    Code:
         0: aload_0
         1: getfield      #202                // Field mapProcessor:Lxaero/map/MapProcessor;
         4: areturn

  public void setDirtyInWriteDistance(net.minecraft.world.entity.player.Player, net.minecraft.world.level.Level);
    Code:
         0: aload_0
         1: invokevirtual #537                // Method getWriteDistance:()I
         4: istore_3
         5: aload_1
         6: invokevirtual #1345               // Method net/minecraft/world/entity/player/Player.blockPosition:()Lnet/minecraft/core/BlockPos;
         9: invokevirtual #1351               // Method net/minecraft/core/BlockPos.getX:()I
        12: iconst_4
        13: ishr
        14: istore        4
        16: aload_1
        17: invokevirtual #1345               // Method net/minecraft/world/entity/player/Player.blockPosition:()Lnet/minecraft/core/BlockPos;
        20: invokevirtual #1356               // Method net/minecraft/core/BlockPos.getZ:()I
        23: iconst_4
        24: ishr
        25: istore        5
        27: iload         4
        29: iload_3
        30: isub
        31: istore        6
        33: iload         5
        35: iload_3
        36: isub
        37: istore        7
        39: iload         4
        41: iload_3
        42: iadd
        43: istore        8
        45: iload         5
        47: iload_3
        48: iadd
        49: istore        9
        51: invokestatic  #323                // Method xaero/map/core/XaeroWorldMapCore.ensureField:()V
        54: iload         6
        56: istore        10
        58: iload         10
        60: iload         8
        62: if_icmpge     130
        65: iload         7
        67: istore        11
        69: iload         11
        71: iload         9
        73: if_icmpge     124
        76: aload_2
        77: iload         10
        79: iload         11
        81: invokevirtual #680                // Method net/minecraft/world/level/Level.getChunk:(II)Lnet/minecraft/world/level/chunk/LevelChunk;
        84: astore        12
        86: aload         12
        88: ifnull        118
        91: getstatic     #661                // Field xaero/map/core/XaeroWorldMapCore.chunkCleanField:Ljava/lang/reflect/Field;
        94: aload         12
        96: iconst_0
        97: invokestatic  #774                // Method java/lang/Boolean.valueOf:(Z)Ljava/lang/Boolean;
       100: invokevirtual #1359               // Method java/lang/reflect/Field.set:(Ljava/lang/Object;Ljava/lang/Object;)V
       103: goto          118
       106: astore        13
       108: new           #674                // class java/lang/RuntimeException
       111: dup
       112: aload         13
       114: invokespecial #676                // Method java/lang/RuntimeException."<init>":(Ljava/lang/Throwable;)V
       117: athrow
       118: iinc          11, 1
       121: goto          69
       124: iinc          10, 1
       127: goto          58
       130: return
      Exception table:
         from    to  target type
            91   103   106   Class java/lang/IllegalArgumentException
            91   103   106   Class java/lang/IllegalAccessException

  public int getBlockTintIndex(net.minecraft.world.level.block.state.BlockState);
    Code:
         0: aload_0
         1: getfield      #143                // Field blockTintIndices:Lit/unimi/dsi/fastutil/objects/Object2IntMap;
         4: aload_1
         5: invokeinterface #1362,  2         // InterfaceMethod it/unimi/dsi/fastutil/objects/Object2IntMap.getInt:(Ljava/lang/Object;)I
        10: ireturn

  private void lambda$writeChunk$0(xaero.map.region.MapRegion, int, int, java.lang.Integer, xaero.map.region.MapLayer);
    Code:
         0: aload         4
         2: invokevirtual #394                // Method java/lang/Integer.intValue:()I
         5: aload_1
         6: invokevirtual #1366               // Method xaero/map/region/MapRegion.getCaveLayer:()I
         9: if_icmpeq     40
        12: aload_0
        13: getfield      #202                // Field mapProcessor:Lxaero/map/MapProcessor;
        16: aload         4
        18: invokevirtual #394                // Method java/lang/Integer.intValue:()I
        21: iload_2
        22: iload_3
        23: iconst_1
        24: invokevirtual #433                // Method xaero/map/MapProcessor.getLeafMapRegion:(IIIZ)Lxaero/map/region/MapRegion;
        27: astore        6
        29: aload         6
        31: iconst_1
        32: invokevirtual #1369               // Method xaero/map/region/MapRegion.setOutdatedWithOtherLayers:(Z)V
        35: aload         6
        37: invokevirtual #1372               // Method xaero/map/region/MapRegion.setHasHadTerrain:()V
        40: return

  private java.lang.Boolean lambda$new$1(net.minecraft.world.level.block.state.StateHolder);
    Code:
         0: aload_0
         1: aload_1
         2: invokevirtual #1373               // Method shouldOverlay:(Lnet/minecraft/world/level/block/state/StateHolder;)Z
         5: invokestatic  #774                // Method java/lang/Boolean.valueOf:(Z)Ljava/lang/Boolean;
         8: areturn

  private static net.minecraft.util.RandomSource lambda$new$0();
    Code:
         0: lconst_0
         1: invokestatic  #1376               // InterfaceMethod net/minecraft/util/RandomSource.create:(J)Lnet/minecraft/util/RandomSource;
         4: areturn

  static {};
    Code:
         0: iconst_2
         1: anewarray     #915                // class java/lang/String
         4: dup
         5: iconst_0
         6: ldc_w         #1382               // String minecraft
         9: aastore
        10: dup
        11: iconst_1
        12: ldc_w         #1384               // String
        15: aastore
        16: putstatic     #1233               // Field DEFAULT_RESOURCE:[Ljava/lang/String;
        19: return
}
